Workbook

Sheet Answer
A1: Project NOVADRIVE – CRO answer on one page
A2: Management question: Where are our most material supplier-network vulnerabilities, how confident are we, and what practical sourcing options do we have when a supplier becomes a concern?
A4: 1. WHERE ARE WE MOST VULNERABLE?
A5: ="(a) One flood-watch zone sits behind 100% of revenue. East Delta (Z01) hosts IonPeak – the only qualified die source for BOTH power assemblers – and Jade – the only substrate source for every control and battery board. Weekly revenue exposed: "&TEXT(Scorecard!AJ15,"$#,##0.0")&"m. Revenue-at-risk over the die re-qualification window: "&TEXT(Scorecard!AK15,"$#,##0")&"m (no buffer). EV-001 is a WATCH, not damage: verify and pre-position now." -> (a) One flood-watch zone sits behind 100% of revenue. East Delta (Z01) hosts IonPeak – the only qualified die source for BOTH power assemblers – and Jade – the only substrate source for every control and battery board. Weekly revenue exposed: $30.0m. Revenue-at-risk over the die re-qualification window: $1,080m (no buffer). EV-001 is a WATCH, not damage: verify and pre-position now.
A6: ="(b) Our dual sourcing is largely an illusion. M10/M20 look 60/40 and 70/30, but CommonSpan owns both assemblers and both use the same IonPeak dies, Orion ceramics and Lumen magnetics: effective independent sources fall from "&TEXT(Concentration!D5,"0.00")&" to 1.0. B10's 80/20 split collapses from "&TEXT(Concentration!D11,"0.00")&" to 1.0 at the Jade substrate." -> (b) Our dual sourcing is largely an illusion. M10/M20 look 60/40 and 70/30, but CommonSpan owns both assemblers and both use the same IonPeak dies, Orion ceramics and Lumen magnetics: effective independent sources fall from 1.92 to 1.0. B10's 80/20 split collapses from 1.47 to 1.0 at the Jade substrate.
A7: ="(c) The capacitor chain is under live financial stress. Meridian (film for Delta's 100%-allocated C20) has the network's worst finances – current ratio "&TEXT(Scorecard!K21,"0.00")&", net debt/EBITDA "&TEXT(Scorecard!L21,"0.0")&"x, OTD "&TEXT(Scorecard!M21,"0.0")&"% ("&TEXT(Scorecard!N21,"0.0")&"pp) – and EV-003 confirms covenant talks. Meridian's film feeds Delta's C20 capacitor, on which "&TEXT(Scorecard!AI9,"0%")&" of revenue depends (Delta's exposure; Meridian inherits it as Delta's only mapped film supplier)." -> (c) The capacitor chain is under live financial stress. Meridian (film for Delta's 100%-allocated C20) has the network's worst finances – current ratio 0.62, net debt/EBITDA 7.2x, OTD 76.4% (-17.6pp) – and EV-003 confirms covenant talks. Meridian's film feeds Delta's C20 capacitor, on which 73% of revenue depends (Delta's exposure; Meridian inherits it as Delta's only mapped film supplier).
A8: ="(d) Cobalt is a single Tier-1 source for the control board in ALL three products, in a high-hazard zone (Z04). Revenue-at-risk over its 12-week qualification: "&TEXT(Scorecard!AK8,"$#,##0")&"m. Z04 is a second zone that could stop 100% of revenue." -> (d) Cobalt is a single Tier-1 source for the control board in ALL three products, in a high-hazard zone (Z04). Revenue-at-risk over its 12-week qualification: $360m. Z04 is a second zone that could stop 100% of revenue.
A9: (e) Two of the top five (Umber SiC wafers #1, Verdant gases #5) are Tier-3 nodes with sparse data. They rank high because we refuse to treat unknowns as safe – the action is VERIFY, not switch.
A11: Top-10 priority nodes (live from Scorecard)
A12: Rank | B12: Supplier | C12: Tier | D12: Zone | E12: Priority | F12: Band | G12: Confidence | H12: Recommended action | I12: RaR over TTR ($m)
A13: 1 | B13: =INDEX(Scorecard!$B$6:$B$30,MATCH(1,Scorecard!$AP$6:$AP$30,0)) -> Umber Silicon Carbide Ltd. | C13: =INDEX(Scorecard!$C$6:$C$30,MATCH(1,Scorecard!$AP$6:$AP$30,0)) -> 3 | D13: =INDEX(Scorecard!$F$6:$F$30,MATCH(1,Scorecard!$AP$6:$AP$30,0)) -> Z01 | E13: =INDEX(Scorecard!$AO$6:$AO$30,MATCH(1,Scorecard!$AP$6:$AP$30,0)) -> 51.082111 | F13: =INDEX(Scorecard!$AQ$6:$AQ$30,MATCH(1,Scorecard!$AP$6:$AP$30,0)) -> Critical | G13: =INDEX(Scorecard!$AX$6:$AX$30,MATCH(1,Scorecard!$AP$6:$AP$30,0)) -> Low | H13: =INDEX(Scorecard!$AY$6:$AY$30,MATCH(1,Scorecard!$AP$6:$AP$30,0)) -> VERIFY first – urgent sub-tier fact-find | I13: =INDEX(Scorecard!$AK$6:$AK$30,MATCH(1,Scorecard!$AP$6:$AP$30,0)) -> 1080
A14: 2 | B14: =INDEX(Scorecard!$B$6:$B$30,MATCH(2,Scorecard!$AP$6:$AP$30,0)) -> IonPeak Semiconductor Ltd. | C14: =INDEX(Scorecard!$C$6:$C$30,MATCH(2,Scorecard!$AP$6:$AP$30,0)) -> 2 | D14: =INDEX(Scorecard!$F$6:$F$30,MATCH(2,Scorecard!$AP$6:$AP$30,0)) -> Z01 | E14: =INDEX(Scorecard!$AO$6:$AO$30,MATCH(2,Scorecard!$AP$6:$AP$30,0)) -> 47.043111 | F14: =INDEX(Scorecard!$AQ$6:$AQ$30,MATCH(2,Scorecard!$AP$6:$AP$30,0)) -> Critical | G14: =INDEX(Scorecard!$AX$6:$AX$30,MATCH(2,Scorecard!$AP$6:$AP$30,0)) -> High | H14: =INDEX(Scorecard!$AY$6:$AY$30,MATCH(2,Scorecard!$AP$6:$AP$30,0)) -> ACT – mitigate now | I14: =INDEX(Scorecard!$AK$6:$AK$30,MATCH(2,Scorecard!$AP$6:$AP$30,0)) -> 1080
A15: 3 | B15: =INDEX(Scorecard!$B$6:$B$30,MATCH(3,Scorecard!$AP$6:$AP$30,0)) -> Meridian Dielectrics Ltd. | C15: =INDEX(Scorecard!$C$6:$C$30,MATCH(3,Scorecard!$AP$6:$AP$30,0)) -> 2 | D15: =INDEX(Scorecard!$F$6:$F$30,MATCH(3,Scorecard!$AP$6:$AP$30,0)) -> Z03 | E15: =INDEX(Scorecard!$AO$6:$AO$30,MATCH(3,Scorecard!$AP$6:$AP$30,0)) -> 45.068444 | F15: =INDEX(Scorecard!$AQ$6:$AQ$30,MATCH(3,Scorecard!$AP$6:$AP$30,0)) -> Critical | G15: =INDEX(Scorecard!$AX$6:$AX$30,MATCH(3,Scorecard!$AP$6:$AP$30,0)) -> Medium | H15: =INDEX(Scorecard!$AY$6:$AY$30,MATCH(3,Scorecard!$AP$6:$AP$30,0)) -> ACT – mitigate now | I15: =INDEX(Scorecard!$AK$6:$AK$30,MATCH(3,Scorecard!$AP$6:$AP$30,0)) -> 264
A16: 4 | B16: =INDEX(Scorecard!$B$6:$B$30,MATCH(4,Scorecard!$AP$6:$AP$30,0)) -> Jade Printed Circuits Ltd. | C16: =INDEX(Scorecard!$C$6:$C$30,MATCH(4,Scorecard!$AP$6:$AP$30,0)) -> 2 | D16: =INDEX(Scorecard!$F$6:$F$30,MATCH(4,Scorecard!$AP$6:$AP$30,0)) -> Z01 | E16: =INDEX(Scorecard!$AO$6:$AO$30,MATCH(4,Scorecard!$AP$6:$AP$30,0)) -> 42.086667 | F16: =INDEX(Scorecard!$AQ$6:$AQ$30,MATCH(4,Scorecard!$AP$6:$AP$30,0)) -> High | G16: =INDEX(Scorecard!$AX$6:$AX$30,MATCH(4,Scorecard!$AP$6:$AP$30,0)) -> High | H16: =INDEX(Scorecard!$AY$6:$AY$30,MATCH(4,Scorecard!$AP$6:$AP$30,0)) -> ACT – mitigate now | I16: =INDEX(Scorecard!$AK$6:$AK$30,MATCH(4,Scorecard!$AP$6:$AP$30,0)) -> 360
A17: 5 | B17: =INDEX(Scorecard!$B$6:$B$30,MATCH(5,Scorecard!$AP$6:$AP$30,0)) -> Verdant Process Gases Ltd. | C17: =INDEX(Scorecard!$C$6:$C$30,MATCH(5,Scorecard!$AP$6:$AP$30,0)) -> 3 | D17: =INDEX(Scorecard!$F$6:$F$30,MATCH(5,Scorecard!$AP$6:$AP$30,0)) -> Z01 | E17: =INDEX(Scorecard!$AO$6:$AO$30,MATCH(5,Scorecard!$AP$6:$AP$30,0)) -> 36.570333 | F17: =INDEX(Scorecard!$AQ$6:$AQ$30,MATCH(5,Scorecard!$AP$6:$AP$30,0)) -> High | G17: =INDEX(Scorecard!$AX$6:$AX$30,MATCH(5,Scorecard!$AP$6:$AP$30,0)) -> Low | H17: =INDEX(Scorecard!$AY$6:$AY$30,MATCH(5,Scorecard!$AP$6:$AP$30,0)) -> VERIFY first – urgent sub-tier fact-find | I17: =INDEX(Scorecard!$AK$6:$AK$30,MATCH(5,Scorecard!$AP$6:$AP$30,0)) -> 240
A18: 6 | B18: =INDEX(Scorecard!$B$6:$B$30,MATCH(6,Scorecard!$AP$6:$AP$30,0)) -> Orion Ceramics Ltd. | C18: =INDEX(Scorecard!$C$6:$C$30,MATCH(6,Scorecard!$AP$6:$AP$30,0)) -> 2 | D18: =INDEX(Scorecard!$F$6:$F$30,MATCH(6,Scorecard!$AP$6:$AP$30,0)) -> Z01 | E18: =INDEX(Scorecard!$AO$6:$AO$30,MATCH(6,Scorecard!$AP$6:$AP$30,0)) -> 33.006667 | F18: =INDEX(Scorecard!$AQ$6:$AQ$30,MATCH(6,Scorecard!$AP$6:$AP$30,0)) -> High | G18: =INDEX(Scorecard!$AX$6:$AX$30,MATCH(6,Scorecard!$AP$6:$AP$30,0)) -> Medium | H18: =INDEX(Scorecard!$AY$6:$AY$30,MATCH(6,Scorecard!$AP$6:$AP$30,0)) -> CONFIRM sole-source status, then qualify alternate | I18: =INDEX(Scorecard!$AK$6:$AK$30,MATCH(6,Scorecard!$AP$6:$AP$30,0)) -> 600
A19: 7 | B19: =INDEX(Scorecard!$B$6:$B$30,MATCH(7,Scorecard!$AP$6:$AP$30,0)) -> Lumen Magnetics Ltd. | C19: =INDEX(Scorecard!$C$6:$C$30,MATCH(7,Scorecard!$AP$6:$AP$30,0)) -> 2 | D19: =INDEX(Scorecard!$F$6:$F$30,MATCH(7,Scorecard!$AP$6:$AP$30,0)) -> Z04 | E19: =INDEX(Scorecard!$AO$6:$AO$30,MATCH(7,Scorecard!$AP$6:$AP$30,0)) -> 31.636056 | F19: =INDEX(Scorecard!$AQ$6:$AQ$30,MATCH(7,Scorecard!$AP$6:$AP$30,0)) -> High | G19: =INDEX(Scorecard!$AX$6:$AX$30,MATCH(7,Scorecard!$AP$6:$AP$30,0)) -> Medium | H19: =INDEX(Scorecard!$AY$6:$AY$30,MATCH(7,Scorecard!$AP$6:$AP$30,0)) -> CONFIRM sole-source status, then qualify alternate | I19: =INDEX(Scorecard!$AK$6:$AK$30,MATCH(7,Scorecard!$AP$6:$AP$30,0)) -> 300
A20: 8 | B20: =INDEX(Scorecard!$B$6:$B$30,MATCH(8,Scorecard!$AP$6:$AP$30,0)) -> Warden Copper Foil Ltd. | C20: =INDEX(Scorecard!$C$6:$C$30,MATCH(8,Scorecard!$AP$6:$AP$30,0)) -> 3 | D20: =INDEX(Scorecard!$F$6:$F$30,MATCH(8,Scorecard!$AP$6:$AP$30,0)) -> Z06 | E20: =INDEX(Scorecard!$AO$6:$AO$30,MATCH(8,Scorecard!$AP$6:$AP$30,0)) -> 30.913917 | F20: =INDEX(Scorecard!$AQ$6:$AQ$30,MATCH(8,Scorecard!$AP$6:$AP$30,0)) -> High | G20: =INDEX(Scorecard!$AX$6:$AX$30,MATCH(8,Scorecard!$AP$6:$AP$30,0)) -> Low | H20: =INDEX(Scorecard!$AY$6:$AY$30,MATCH(8,Scorecard!$AP$6:$AP$30,0)) -> VERIFY first – urgent sub-tier fact-find | I20: =INDEX(Scorecard!$AK$6:$AK$30,MATCH(8,Scorecard!$AP$6:$AP$30,0)) -> 240
A21: 9 | B21: =INDEX(Scorecard!$B$6:$B$30,MATCH(9,Scorecard!$AP$6:$AP$30,0)) -> Cobalt Control Electronics Ltd. | C21: =INDEX(Scorecard!$C$6:$C$30,MATCH(9,Scorecard!$AP$6:$AP$30,0)) -> 1 | D21: =INDEX(Scorecard!$F$6:$F$30,MATCH(9,Scorecard!$AP$6:$AP$30,0)) -> Z04 | E21: =INDEX(Scorecard!$AO$6:$AO$30,MATCH(9,Scorecard!$AP$6:$AP$30,0)) -> 30.785556 | F21: =INDEX(Scorecard!$AQ$6:$AQ$30,MATCH(9,Scorecard!$AP$6:$AP$30,0)) -> High | G21: =INDEX(Scorecard!$AX$6:$AX$30,MATCH(9,Scorecard!$AP$6:$AP$30,0)) -> High | H21: =INDEX(Scorecard!$AY$6:$AY$30,MATCH(9,Scorecard!$AP$6:$AP$30,0)) -> ACT – mitigate now | I21: =INDEX(Scorecard!$AK$6:$AK$30,MATCH(9,Scorecard!$AP$6:$AP$30,0)) -> 360
A22: 10 | B22: =INDEX(Scorecard!$B$6:$B$30,MATCH(10,Scorecard!$AP$6:$AP$30,0)) -> Xenon Resin Ltd. | C22: =INDEX(Scorecard!$C$6:$C$30,MATCH(10,Scorecard!$AP$6:$AP$30,0)) -> 3 | D22: =INDEX(Scorecard!$F$6:$F$30,MATCH(10,Scorecard!$AP$6:$AP$30,0)) -> Z04 | E22: =INDEX(Scorecard!$AO$6:$AO$30,MATCH(10,Scorecard!$AP$6:$AP$30,0)) -> 30.460306 | F22: =INDEX(Scorecard!$AQ$6:$AQ$30,MATCH(10,Scorecard!$AP$6:$AP$30,0)) -> High | G22: =INDEX(Scorecard!$AX$6:$AX$30,MATCH(10,Scorecard!$AP$6:$AP$30,0)) -> Low | H22: =INDEX(Scorecard!$AY$6:$AY$30,MATCH(10,Scorecard!$AP$6:$AP$30,0)) -> VERIFY first – urgent sub-tier fact-find | I22: =INDEX(Scorecard!$AK$6:$AK$30,MATCH(10,Scorecard!$AP$6:$AP$30,0)) -> 240
A24: 2. HOW CONFIDENT ARE WE?
A25: ="Network links: "&COUNTIF(Network!S5:S36,"A")&" grade A (≥2 independent source families), "&COUNTIF(Network!S5:S36,"B")&" grade B (one primary disclosure), "&COUNTIF(Network!S5:S36,"C")&" grade C (inferred), plus "&COUNTIF(Network!R37:R45,"Hypothesis")&" hypotheses and "&COUNTIF(Network!R37:R45,"Rejected")&" rejected traps. Every Tier-1 link is grade A." -> Network links: 15 grade A (≥2 independent source families), 16 grade B (one primary disclosure), 1 grade C (inferred), plus 2 hypotheses and 3 rejected traps. Every Tier-1 link is grade A.
A26: ="Scored nodes: "&COUNTIF(Scorecard!AX6:AX30,"High")&" High, "&COUNTIF(Scorecard!AX6:AX30,"Medium")&" Medium, "&COUNTIF(Scorecard!AX6:AX30,"Low")&" Low confidence. Confidence is kept separate from risk: it decides whether we ACT or VERIFY." -> Scored nodes: 11 High, 8 Medium, 6 Low confidence. Confidence is kept separate from risk: it decides whether we ACT or VERIFY.
A27: ="Robustness: IonPeak, Jade, Umber and Verdant stay top-5 under all 5 weighting scenarios; Meridian under "&Sensitivity!U28&" of 5 (Sensitivity tab). Our headline conclusions do not hinge on the weights." -> Robustness: IonPeak, Jade, Umber and Verdant stay top-5 under all 5 weighting scenarios; Meridian under 4 of 5 (Sensitivity tab). Our headline conclusions do not hinge on the weights.
A28: Biggest unknowns: whether Meridian is Delta's only film source; whether NovaDrive dies are SiC (Umber relevance); inventory at every tier; the zones of NovaDrive's own plants; which lanes use Gulf Arc (Unknowns tab).
A30: 3. WHAT ARE OUR PRACTICAL SOURCING OPTIONS?
A31: Capacitors (fastest hedge, 8-week qualification): TDK B25696H (Jun-2026) and Vishay MKP1848e (Sep-2025) as a second Tier-1 C20; Toray / Tervakoski as second film for Delta. Steinerfilm US EXCLUDED – plant closed June 2026.
A32: Power dies / modules: Infineon (bare dies + modules), Mitsubishi 8th-gen NX (May-2026), Fuji X-Series for M10; Vincotech / Infineon SiC for M20. Wolfspeed RESERVE only (fitment 72, Amber risk: emerged from Chapter 11 on 30-Sep-2025). Independent assembler: Semikron Danfoss power stacks (must not use IonPeak dies or Orion ceramics).
A33: Control boards: second EMS (Sanmina, Celestica, Kitron) – only real once NovaDrive owns the C10 data pack. Substrates outside Z01: Schweizer (small; profitable again in 2025) or TTM Penang.
A34: Cooling: Boyd (now Eaton, Mar-2026 – watch capacity diverted to data centres) or Wieland Microcool. Full scoring on Alternates tab: fitment and risk screened SEPARATELY.
A36: 4. WHAT WE WOULD DO ON MONDAY
A37: ① Z01 census + pull-forward through the Tier-1s (EV-001).
A38: ② Delta film-source disclosure + C20 buffer ≥ 8 weeks; launch second C20 qualification (EV-003).
A39: ③ N-tier disclosure request for all presumed-sole links.
A40: ④ Secure the C10 data pack from Cobalt; brief two EMS candidates.
A41: ⑤ Open the second power-module platform programme – the only structural fix for the CommonSpan/IonPeak concentration.
... A51: HOW TO READ THIS WORKBOOK: Answer → Scorecard (priority) → Network & Evidence (why we believe each link) → Concentration → Alerts → Alternates → ActionPlan → Unknowns. Blue = input/judgement, black = formula, green = cross-tab link, yellow = key assumption. Change any weight on Assumptions and everything recalculates.

Sheet Scorecard
A1: Supplier risk scorecard – Impact × Vulnerability, with Confidence kept separate
A2: Priority = Impact × Vulnerability / 100. Confidence (evidence quality + data completeness + dependency certainty) does NOT change the score – it changes the ACTION (act vs verify).
A4: IDENTITY & NETWORK ROLE | K4: RAW INDICATORS (from case data, via Data tab) | S4: VULNERABILITY / LIKELIHOOD (0-100) | AE4: IMPACT, PRIORITY & RANK | AS4: CONFIDENCE (kept separate) & RECOMMENDED ACTION
A5: Node ID | B5: Supplier | C5: Tier | D5: Network role | E5: Facility | F5: Zone | G5: Dependency status | H5: Downstream Tier-1s | I5: TTR (weeks) | J5: TTR basis | K5: Current ratio | L5: Net debt/EBITDA | M5: OTD 3m % | N5: OTD Δ pp | O5: Assurance gap | P5: Physical hazard | Q5: Logistics friction | R5: Infrastructure | S5: Leverage score | T5: Liquidity score | U5: OTD score | V5: OTD trend score | W5: Leverage used | X5: Liquidity used | Y5: Assurance used | Z5: Financial | AA5: Operational | AB5: Geographic | AC5: Event overlay (1=yes) | AD5: VULNERABILITY | AE5: Exposure P1 | AF5: Exposure P2 | AG5: Exposure P3 | AH5: Revenue exposed ($m/yr) | AI5: Share of revenue | AJ5: Weekly revenue exposed ($m) | AK5: Revenue-at-risk over TTR ($m) | AL5: Recovery score | AM5: Centrality score | AN5: IMPACT | AO5: PRIORITY | AP5: Rank | AQ5: Band | AR5: Quadrant | AS5: Link grade pts | AT5: Indicators available (of 8) | AU5: Data pts | AV5: Dependency pts | AW5: Confidence pts | AX5: CONFIDENCE | AY5: Recommended action | AZ5: Missing data (imputed)
A6: ORG-247 | B6: =INDEX(Data!$B$5:$B$34,MATCH($A6,Data!$A$5:$A$34,0)) -> Aster Power Assemblies Ltd. | C6: 1 | D6: Tier-1: M10 (60%) & M20 (70%) | E6: =INDEX(Data!$G$38:$G$67,MATCH($A6,Data!$A$38:$A$67,0)) -> SITE-018 | F6: =INDEX(Data!$I$38:$I$67,MATCH($A6,Data!$A$38:$A$67,0)) -> Z02 | G6: Partial (60/70%) – shares owner with Boreal | H6: 1 | I6: 16 | J6: Case: M10/M20 qualification lead time 16 wks | K6: =IF(INDEX(Data!$C$5:$C$34,MATCH($A6,Data!$A$5:$A$34,0))="","",INDEX(Data!$C$5:$C$34,MATCH($A6,Data!$A$5:$A$34,0))) -> 2.13 | L6: =IF(INDEX(Data!$D$5:$D$34,MATCH($A6,Data!$A$5:$A$34,0))="","",INDEX(Data!$D$5:$D$34,MATCH($A6,Data!$A$5:$A$34,0))) -> 2 | M6: =IF(INDEX(Data!$E$5:$E$34,MATCH($A6,Data!$A$5:$A$34,0))="","",INDEX(Data!$E$5:$E$34,MATCH($A6,Data!$A$5:$A$34,0))) -> 80.9 | N6: =IF(INDEX(Data!$F$5:$F$34,MATCH($A6,Data!$A$5:$A$34,0))="","",INDEX(Data!$F$5:$F$34,MATCH($A6,Data!$A$5:$A$34,0))) -> 2.3 | O6: =IF(INDEX(Data!$G$5:$G$34,MATCH($A6,Data!$A$5:$A$34,0))="","",INDEX(Data!$G$5:$G$34,MATCH($A6,Data!$A$5:$A$34,0))) -> 24 | P6: =IF(INDEX(Data!$H$5:$H$34,MATCH($A6,Data!$A$5:$A$34,0))="","",INDEX(Data!$H$5:$H$34,MATCH($A6,Data!$A$5:$A$34,0))) -> 27 | Q6: =IF(INDEX(Data!$I$5:$I$34,MATCH($A6,Data!$A$5:$A$34,0))="","",INDEX(Data!$I$5:$I$34,MATCH($A6,Data!$A$5:$A$34,0))) -> 30 | R6: =IF(INDEX(Data!$J$5:$J$34,MATCH($A6,Data!$A$5:$A$34,0))="","",INDEX(Data!$J$5:$J$34,MATCH($A6,Data!$A$5:$A$34,0))) -> 24 | S6: =IF(L6="","",IF(L6<=Assumptions!$B$31,Assumptions!$H$31,IF(L6<=Assumptions!$C$31,Assumptions!$H$31+(L6-Assumptions!$B$31)/(Assumptions!$C$31-Assumptions!$B$31)*(Assumptions!$I$31-Assumptions!$H$31),IF(L6<=Assumptions!$D$31,Assumptions!$I$31+(L6-Assumptions!$C$31)/(Assumptions!$D$31-Assumptions!$C$31)*(Assumptions!$J$31-Assumptions!$I$31),IF(L6<=Assumptions!$E$31,Assumptions!$J$31+(L6-Assumptions!$D$31)/(Assumptions!$E$31-Assumptions!$D$31)*(Assumptions!$K$31-Assumptions!$J$31),IF(L6<=Assumptions!$F$31,Assumptions!$K$31+(L6-Assumptions!$E$31)/(Assumptions!$F$31-Assumptions!$E$31)*(Assumptions!$L$31-Assumptions!$K$31),IF(L6<=Assumptions!$G$31,Assumptions!$L$31+(L6-Assumptions!$F$31)/(Assumptions!$G$31-Assumptions!$F$31)*(Assumptions!$M$31-Assumptions!$L$31),Assumptions!$M$31))))))) -> 24 | T6: =IF(K6="","",IF(K6<=Assumptions!$B$32,Assumptions!$H$32,IF(K6<=Assumptions!$C$32,Assumptions!$H$32+(K6-Assumptions!$B$32)/(Assumptions!$C$32-Assumptions!$B$32)*(Assumptions!$I$32-Assumptions!$H$32),IF(K6<=Assumptions!$D$32,Assumptions!$I$32+(K6-Assumptions!$C$32)/(Assumptions!$D$32-Assumptions!$C$32)*(Assumptions!$J$32-Assumptions!$I$32),IF(K6<=Assumptions!$E$32,Assumptions!$J$32+(K6-Assumptions!$D$32)/(Assumptions!$E$32-Assumptions!$D$32)*(Assumptions!$K$32-Assumptions!$J$32),IF(K6<=Assumptions!$F$32,Assumptions!$K$32+(K6-Assumptions!$E$32)/(Assumptions!$F$32-Assumptions!$E$32)*(Assumptions!$L$32-Assumptions!$K$32),IF(K6<=Assumptions!$G$32,Assumptions!$L$32+(K6-Assumptions!$F$32)/(Assumptions!$G$32-Assumptions!$F$32)*(Assumptions!$M$32-Assumptions!$L$32),Assumptions!$M$32))))))) -> 11.1 | U6: =IF(M6<=Assumptions!$B$33,Assumptions!$H$33,IF(M6<=Assumptions!$C$33,Assumptions!$H$33+(M6-Assumptions!$B$33)/(Assumptions!$C$33-Assumptions!$B$33)*(Assumptions!$I$33-Assumptions!$H$33),IF(M6<=Assumptions!$D$33,Assumptions!$I$33+(M6-Assumptions!$C$33)/(Assumptions!$D$33-Assumptions!$C$33)*(Assumptions!$J$33-Assumptions!$I$33),IF(M6<=Assumptions!$E$33,Assumptions!$J$33+(M6-Assumptions!$D$33)/(Assumptions!$E$33-Assumptions!$D$33)*(Assumptions!$K$33-Assumptions!$J$33),IF(M6<=Assumptions!$F$33,Assumptions!$K$33+(M6-Assumptions!$E$33)/(Assumptions!$F$33-Assumptions!$E$33)*(Assumptions!$L$33-Assumptions!$K$33),IF(M6<=Assumptions!$G$33,Assumptions!$L$33+(M6-Assumptions!$F$33)/(Assumptions!$G$33-Assumptions!$F$33)*(Assumptions!$M$33-Assumptions!$L$33),Assumptions!$M$33)))))) -> 70.5 | V6: =IF(N6<=Assumptions!$B$34,Assumptions!$H$34,IF(N6<=Assumptions!$C$34,Assumptions!$H$34+(N6-Assumptions!$B$34)/(Assumptions!$C$34-Assumptions!$B$34)*(Assumptions!$I$34-Assumptions!$H$34),IF(N6<=Assumptions!$D$34,Assumptions!$I$34+(N6-Assumptions!$C$34)/(Assumptions!$D$34-Assumptions!$C$34)*(Assumptions!$J$34-Assumptions!$I$34),IF(N6<=Assumptions!$E$34,Assumptions!$J$34+(N6-Assumptions!$D$34)/(Assumptions!$E$34-Assumptions!$D$34)*(Assumptions!$K$34-Assumptions!$J$34),IF(N6<=Assumptions!$F$34,Assumptions!$K$34+(N6-Assumptions!$E$34)/(Assumptions!$F$34-Assumptions!$E$34)*(Assumptions!$L$34-Assumptions!$K$34),IF(N6<=Assumptions!$G$34,Assumptions!$L$34+(N6-Assumptions!$F$34)/(Assumptions!$G$34-Assumptions!$F$34)*(Assumptions!$M$34-Assumptions!$L$34),Assumptions!$M$34)))))) -> 0 | W6: =IF(S6="",PERCENTILE($S$6:$S$30,Assumptions!$B$36),S6) -> 24 | X6: =IF(T6="",PERCENTILE($T$6:$T$30,Assumptions!$B$36),T6) -> 11.1 | Y6: =IF(O6="",PERCENTILE($O$6:$O$30,Assumptions!$B$36),O6) -> 24 | Z6: =W6*Assumptions!$B$16+X6*Assumptions!$B$17 -> 17.55 | AA6: =U6*Assumptions!$B$18+V6*Assumptions!$B$19 -> 35.25 | AB6: =AVERAGE(P6:R6) -> 27 | AC6: 0 | AD6: =MIN(100,Z6*Assumptions!$B$11+AA6*Assumptions!$B$12+Y6*Assumptions!$B$13+AB6*Assumptions!$B$14+AC6*Assumptions!$B$20) -> 26.19 | AE6: =MIN(1,SUMIFS(Network!$V$5:$V$14,Network!$D$5:$D$14,$A6,Network!$U$5:$U$14,1)) -> 0.6 | AF6: =MIN(1,SUMIFS(Network!$W$5:$W$14,Network!$D$5:$D$14,$A6,Network!$U$5:$U$14,1)) -> 0.7 | AG6: =MIN(1,SUMIFS(Network!$X$5:$X$14,Network!$D$5:$D$14,$A6,Network!$U$5:$U$14,1)) -> 0.6 | AH6: =AE6*Assumptions!$B$5+AF6*Assumptions!$B$6+AG6*Assumptions!$B$7 -> 988 | AI6: =AH6/Assumptions!$B$8 -> 0.63333333 | AJ6: =AH6/52 -> 19 | AK6: =AJ6*I6 -> 304 | AL6: =MIN(100,I6/Assumptions!$B$26*100) -> 44.444444 | AM6: =MIN(100,H6/Assumptions!$B$27*100) -> 33.333333 | AN6: =AI6*100*Assumptions!$B$23+AL6*Assumptions!$B$24+AM6*Assumptions!$B$25 -> 51.666667 | AO6: =AN6*AD6/100 -> 13.5315 | AP6: =RANK(AO6,$AO$6:$AO$30)+COUNTIF($AO$6:AO6,AO6)-1 -> 19 | AQ6: =IF(AO6>=Assumptions!$B$39,"Critical",IF(AO6>=Assumptions!$B$40,"High",IF(AO6>=Assumptions!$B$41,"Elevated","Watch"))) -> Watch | AR6: =IF(AND(AN6>=Assumptions!$B$42,AD6>=Assumptions!$B$43),"Act now",IF(AN6>=Assumptions!$B$42,"Protect (structural)",IF(AD6>=Assumptions!$B$43,"Remediate supplier","Routine"))) -> Routine | AS6: =_xlfn.MAXIFS(Network!$T$5:$T$36,Network!$D$5:$D$36,$A6) -> 3 | AT6: =COUNT(K6:R6) -> 8 | AU6: =IF(AT6>=8,2,IF(AT6>=6,1,0)) -> 2 | AV6: =IF(OR(C6=1,LEFT(G6,9)="Confirmed"),1,0) -> 1 | AW6: =AS6+AU6+AV6 -> 6 | AX6: =IF(AW6>=Assumptions!$B$44,"High",IF(AW6>=Assumptions!$B$45,"Medium","Low")) -> High | AY6: =IF(OR(AQ6="Critical",AQ6="High"),IF(AX6="Low","VERIFY first – urgent sub-tier fact-find",IF(OR(AQ6="Critical",AV6=1),"ACT – mitigate now","CONFIRM sole-source status, then qualify alternate")),IF(AQ6="Elevated",IF(AX6="Low","VERIFY – add to N-tier survey","PLAN – qualify alternate in 90 days"),"MONITOR – quarterly review")) -> MONITOR – quarterly review | AZ6: =IF(K6&L6&O6<>"",IF(OR(K6="",L6="",O6=""),TRIM(IF(K6="","Current ratio; ","")&IF(L6="","Net debt/EBITDA; ","")&IF(O6="","Assurance gap","")),"—"),"Current ratio; Net debt/EBITDA; Assurance gap") -> —
A7: ORG-725 | B7: =INDEX(Data!$B$5:$B$34,MATCH($A7,Data!$A$5:$A$34,0)) -> Boreal Power Systems Ltd. | C7: 1 | D7: Tier-1: M10 (40%) & M20 (30%) | E7: =INDEX(Data!$G$38:$G$67,MATCH($A7,Data!$A$38:$A$67,0)) -> SITE-025 | F7: =INDEX(Data!$I$38:$I$67,MATCH($A7,Data!$A$38:$A$67,0)) -> Z05 | G7: Partial (40/30%) – shares owner with Aster | H7: 1 | I7: 16 | J7: Case: M10/M20 qualification lead time 16 wks | K7: =IF(INDEX(Data!$C$5:$C$34,MATCH($A7,Data!$A$5:$A$34,0))="","",INDEX(Data!$C$5:$C$34,MATCH($A7,Data!$A$5:$A$34,0))) -> 1.54 | L7: =IF(INDEX(Data!$D$5:$D$34,MATCH($A7,Data!$A$5:$A$34,0))="","",INDEX(Data!$D$5:$D$34,MATCH($A7,Data!$A$5:$A$34,0))) -> 3 | M7: =IF(INDEX(Data!$E$5:$E$34,MATCH($A7,Data!$A$5:$A$34,0))="","",INDEX(Data!$E$5:$E$34,MATCH($A7,Data!$A$5:$A$34,0))) -> 83.1 | N7: =IF(INDEX(Data!$F$5:$F$34,MATCH($A7,Data!$A$5:$A$34,0))="","",INDEX(Data!$F$5:$F$34,MATCH($A7,Data!$A$5:$A$34,0))) -> 2.2 | O7: =IF(INDEX(Data!$G$5:$G$34,MATCH($A7,Data!$A$5:$A$34,0))="","",INDEX(Data!$G$5:$G$34,MATCH($A7,Data!$A$5:$A$34,0))) -> 33 | P7: =IF(INDEX(Data!$H$5:$H$34,MATCH($A7,Data!$A$5:$A$34,0))="","",INDEX(Data!$H$5:$H$34,MATCH($A7,Data!$A$5:$A$34,0))) -> 31 | Q7: =IF(INDEX(Data!$I$5:$I$34,MATCH($A7,Data!$A$5:$A$34,0))="","",INDEX(Data!$I$5:$I$34,MATCH($A7,Data!$A$5:$A$34,0))) -> 23 | R7: =IF(INDEX(Data!$J$5:$J$34,MATCH($A7,Data!$A$5:$A$34,0))="","",INDEX(Data!$J$5:$J$34,MATCH($A7,Data!$A$5:$A$34,0))) -> 19 | S7: =IF(L7="","",IF(L7<=Assumptions!$B$31,Assumptions!$H$31,IF(L7<=Assumptions!$C$31,Assumptions!$H$31+(L7-Assumptions!$B$31)/(Assumptions!$C$31-Assumptions!$B$31)*(Assumptions!$I$31-Assumptions!$H$31),IF(L7<=Assumptions!$D$31,Assumptions!$I$31+(L7-Assumptions!$C$31)/(Assumptions!$D$31-Assumptions!$C$31)*(Assumptions!$J$31-Assumptions!$I$31),IF(L7<=Assumptions!$E$31,Assumptions!$J$31+(L7-Assumptions!$D$31)/(Assumptions!$E$31-Assumptions!$D$31)*(Assumptions!$K$31-Assumptions!$J$31),IF(L7<=Assumptions!$F$31,Assumptions!$K$31+(L7-Assumptions!$E$31)/(Assumptions!$F$31-Assumptions!$E$31)*(Assumptions!$L$31-Assumptions!$K$31),IF(L7<=Assumptions!$G$31,Assumptions!$L$31+(L7-Assumptions!$F$31)/(Assumptions!$G$31-Assumptions!$F$31)*(Assumptions!$M$31-Assumptions!$L$31),Assumptions!$M$31))))))) -> 43.333333 | T7: =IF(K7="","",IF(K7<=Assumptions!$B$32,Assumptions!$H$32,IF(K7<=Assumptions!$C$32,Assumptions!$H$32+(K7-Assumptions!$B$32)/(Assumptions!$C$32-Assumptions!$B$32)*(Assumptions!$I$32-Assumptions!$H$32),IF(K7<=Assumptions!$D$32,Assumptions!$I$32+(K7-Assumptions!$C$32)/(Assumptions!$D$32-Assumptions!$C$32)*(Assumptions!$J$32-Assumptions!$I$32),IF(K7<=Assumptions!$E$32,Assumptions!$J$32+(K7-Assumptions!$D$32)/(Assumptions!$E$32-Assumptions!$D$32)*(Assumptions!$K$32-Assumptions!$J$32),IF(K7<=Assumptions!$F$32,Assumptions!$K$32+(K7-Assumptions!$E$32)/(Assumptions!$F$32-Assumptions!$E$32)*(Assumptions!$L$32-Assumptions!$K$32),IF(K7<=Assumptions!$G$32,Assumptions!$L$32+(K7-Assumptions!$F$32)/(Assumptions!$G$32-Assumptions!$F$32)*(Assumptions!$M$32-Assumptions!$L$32),Assumptions!$M$32))))))) -> 28.8 | U7: =IF(M7<=Assumptions!$B$33,Assumptions!$H$33,IF(M7<=Assumptions!$C$33,Assumptions!$H$33+(M7-Assumptions!$B$33)/(Assumptions!$C$33-Assumptions!$B$33)*(Assumptions!$I$33-Assumptions!$H$33),IF(M7<=Assumptions!$D$33,Assumptions!$I$33+(M7-Assumptions!$C$33)/(Assumptions!$D$33-Assumptions!$C$33)*(Assumptions!$J$33-Assumptions!$I$33),IF(M7<=Assumptions!$E$33,Assumptions!$J$33+(M7-Assumptions!$D$33)/(Assumptions!$E$33-Assumptions!$D$33)*(Assumptions!$K$33-Assumptions!$J$33),IF(M7<=Assumptions!$F$33,Assumptions!$K$33+(M7-Assumptions!$E$33)/(Assumptions!$F$33-Assumptions!$E$33)*(Assumptions!$L$33-Assumptions!$K$33),IF(M7<=Assumptions!$G$33,Assumptions!$L$33+(M7-Assumptions!$F$33)/(Assumptions!$G$33-Assumptions!$F$33)*(Assumptions!$M$33-Assumptions!$L$33),Assumptions!$M$33)))))) -> 59.5 | V7: =IF(N7<=Assumptions!$B$34,Assumptions!$H$34,IF(N7<=Assumptions!$C$34,Assumptions!$H$34+(N7-Assumptions!$B$34)/(Assumptions!$C$34-Assumptions!$B$34)*(Assumptions!$I$34-Assumptions!$H$34),IF(N7<=Assumptions!$D$34,Assumptions!$I$34+(N7-Assumptions!$C$34)/(Assumptions!$D$34-Assumptions!$C$34)*(Assumptions!$J$34-Assumptions!$I$34),IF(N7<=Assumptions!$E$34,Assumptions!$J$34+(N7-Assumptions!$D$34)/(Assumptions!$E$34-Assumptions!$D$34)*(Assumptions!$K$34-Assumptions!$J$34),IF(N7<=Assumptions!$F$34,Assumptions!$K$34+(N7-Assumptions!$E$34)/(Assumptions!$F$34-Assumptions!$E$34)*(Assumptions!$L$34-Assumptions!$K$34),IF(N7<=Assumptions!$G$34,Assumptions!$L$34+(N7-Assumptions!$F$34)/(Assumptions!$G$34-Assumptions!$F$34)*(Assumptions!$M$34-Assumptions!$L$34),Assumptions!$M$34)))))) -> 0 | W7: =IF(S7="",PERCENTILE($S$6:$S$30,Assumptions!$B$36),S7) -> 43.333333 | X7: =IF(T7="",PERCENTILE($T$6:$T$30,Assumptions!$B$36),T7) -> 28.8 | Y7: =IF(O7="",PERCENTILE($O$6:$O$30,Assumptions!$B$36),O7) -> 33 | Z7: =W7*Assumptions!$B$16+X7*Assumptions!$B$17 -> 36.066667 | AA7: =U7*Assumptions!$B$18+V7*Assumptions!$B$19 -> 29.75 | AB7: =AVERAGE(P7:R7) -> 24.333333 | AC7: 0 | AD7: =MIN(100,Z7*Assumptions!$B$11+AA7*Assumptions!$B$12+Y7*Assumptions!$B$13+AB7*Assumptions!$B$14+AC7*Assumptions!$B$20) -> 30.778333 | AE7: =MIN(1,SUMIFS(Network!$V$5:$V$14,Network!$D$5:$D$14,$A7,Network!$U$5:$U$14,1)) -> 0.4 | AF7: =MIN(1,SUMIFS(Network!$W$5:$W$14,Network!$D$5:$D$14,$A7,Network!$U$5:$U$14,1)) -> 0.3 | AG7: =MIN(1,SUMIFS(Network!$X$5:$X$14,Network!$D$5:$D$14,$A7,Network!$U$5:$U$14,1)) -> 0.4 | AH7: =AE7*Assumptions!$B$5+AF7*Assumptions!$B$6+AG7*Assumptions!$B$7 -> 572 | AI7: =AH7/Assumptions!$B$8 -> 0.36666667 | AJ7: =AH7/52 -> 11 | AK7: =AJ7*I7 -> 176 | AL7: =MIN(100,I7/Assumptions!$B$26*100) -> 44.444444 | AM7: =MIN(100,H7/Assumptions!$B$27*100) -> 33.333333 | AN7: =AI7*100*Assumptions!$B$23+AL7*Assumptions!$B$24+AM7*Assumptions!$B$25 -> 38.333333 | AO7: =AN7*AD7/100 -> 11.798361 | AP7: =RANK(AO7,$AO$6:$AO$30)+COUNTIF($AO$6:AO7,AO7)-1 -> 21 | AQ7: =IF(AO7>=Assumptions!$B$39,"Critical",IF(AO7>=Assumptions!$B$40,"High",IF(AO7>=Assumptions!$B$41,"Elevated","Watch"))) -> Watch | AR7: =IF(AND(AN7>=Assumptions!$B$42,AD7>=Assumptions!$B$43),"Act now",IF(AN7>=Assumptions!$B$42,"Protect (structural)",IF(AD7>=Assumptions!$B$43,"Remediate supplier","Routine"))) -> Routine | AS7: =_xlfn.MAXIFS(Network!$T$5:$T$36,Network!$D$5:$D$36,$A7) -> 3 | AT7: =COUNT(K7:R7) -> 8 | AU7: =IF(AT7>=8,2,IF(AT7>=6,1,0)) -> 2 | AV7: =IF(OR(C7=1,LEFT(G7,9)="Confirmed"),1,0) -> 1 | AW7: =AS7+AU7+AV7 -> 6 | AX7: =IF(AW7>=Assumptions!$B$44,"High",IF(AW7>=Assumptions!$B$45,"Medium","Low")) -> High | AY7: =IF(OR(AQ7="Critical",AQ7="High"),IF(AX7="Low","VERIFY first – urgent sub-tier fact-find",IF(OR(AQ7="Critical",AV7=1),"ACT – mitigate now","CONFIRM sole-source status, then qualify alternate")),IF(AQ7="Elevated",IF(AX7="Low","VERIFY – add to N-tier survey","PLAN – qualify alternate in 90 days"),"MONITOR – quarterly review")) -> MONITOR – quarterly review | AZ7: =IF(K7&L7&O7<>"",IF(OR(K7="",L7="",O7=""),TRIM(IF(K7="","Current ratio; ","")&IF(L7="","Net debt/EBITDA; ","")&IF(O7="","Assurance gap","")),"—"),"Current ratio; Net debt/EBITDA; Assurance gap") -> —
A8: ORG-119 | B8: =INDEX(Data!$B$5:$B$34,MATCH($A8,Data!$A$5:$A$34,0)) -> Cobalt Control Electronics Ltd. | C8: 1 | D8: Tier-1: C10 control board, all products | E8: =INDEX(Data!$G$38:$G$67,MATCH($A8,Data!$A$38:$A$67,0)) -> SITE-032 | F8: =INDEX(Data!$I$38:$I$67,MATCH($A8,Data!$A$38:$A$67,0)) -> Z04 | G8: Confirmed sole (100% allocation) | H8: 1 | I8: 12 | J8: Case: C10 qualification 12 wks | K8: =IF(INDEX(Data!$C$5:$C$34,MATCH($A8,Data!$A$5:$A$34,0))="","",INDEX(Data!$C$5:$C$34,MATCH($A8,Data!$A$5:$A$34,0))) -> 2.34 | L8: =IF(INDEX(Data!$D$5:$D$34,MATCH($A8,Data!$A$5:$A$34,0))="","",INDEX(Data!$D$5:$D$34,MATCH($A8,Data!$A$5:$A$34,0))) -> 4 | M8: =IF(INDEX(Data!$E$5:$E$34,MATCH($A8,Data!$A$5:$A$34,0))="","",INDEX(Data!$E$5:$E$34,MATCH($A8,Data!$A$5:$A$34,0))) -> 83.3 | N8: =IF(INDEX(Data!$F$5:$F$34,MATCH($A8,Data!$A$5:$A$34,0))="","",INDEX(Data!$F$5:$F$34,MATCH($A8,Data!$A$5:$A$34,0))) -> -2.3 | O8: =IF(INDEX(Data!$G$5:$G$34,MATCH($A8,Data!$A$5:$A$34,0))="","",INDEX(Data!$G$5:$G$34,MATCH($A8,Data!$A$5:$A$34,0))) -> 42 | P8: =IF(INDEX(Data!$H$5:$H$34,MATCH($A8,Data!$A$5:$A$34,0))="","",INDEX(Data!$H$5:$H$34,MATCH($A8,Data!$A$5:$A$34,0))) -> 58 | Q8: =IF(INDEX(Data!$I$5:$I$34,MATCH($A8,Data!$A$5:$A$34,0))="","",INDEX(Data!$I$5:$I$34,MATCH($A8,Data!$A$5:$A$34,0))) -> 62 | R8: =IF(INDEX(Data!$J$5:$J$34,MATCH($A8,Data!$A$5:$A$34,0))="","",INDEX(Data!$J$5:$J$34,MATCH($A8,Data!$A$5:$A$34,0))) -> 52 | S8: =IF(L8="","",IF(L8<=Assumptions!$B$31,Assumptions!$H$31,IF(L8<=Assumptions!$C$31,Assumptions!$H$31+(L8-Assumptions!$B$31)/(Assumptions!$C$31-Assumptions!$B$31)*(Assumptions!$I$31-Assumptions!$H$31),IF(L8<=Assumptions!$D$31,Assumptions!$I$31+(L8-Assumptions!$C$31)/(Assumptions!$D$31-Assumptions!$C$31)*(Assumptions!$J$31-Assumptions!$I$31),IF(L8<=Assumptions!$E$31,Assumptions!$J$31+(L8-Assumptions!$D$31)/(Assumptions!$E$31-Assumptions!$D$31)*(Assumptions!$K$31-Assumptions!$J$31),IF(L8<=Assumptions!$F$31,Assumptions!$K$31+(L8-Assumptions!$E$31)/(Assumptions!$F$31-Assumptions!$E$31)*(Assumptions!$L$31-Assumptions!$K$31),IF(L8<=Assumptions!$G$31,Assumptions!$L$31+(L8-Assumptions!$F$31)/(Assumptions!$G$31-Assumptions!$F$31)*(Assumptions!$M$31-Assumptions!$L$31),Assumptions!$M$31))))))) -> 70 | T8: =IF(K8="","",IF(K8<=Assumptions!$B$32,Assumptions!$H$32,IF(K8<=Assumptions!$C$32,Assumptions!$H$32+(K8-Assumptions!$B$32)/(Assumptions!$C$32-Assumptions!$B$32)*(Assumptions!$I$32-Assumptions!$H$32),IF(K8<=Assumptions!$D$32,Assumptions!$I$32+(K8-Assumptions!$C$32)/(Assumptions!$D$32-Assumptions!$C$32)*(Assumptions!$J$32-Assumptions!$I$32),IF(K8<=Assumptions!$E$32,Assumptions!$J$32+(K8-Assumptions!$D$32)/(Assumptions!$E$32-Assumptions!$D$32)*(Assumptions!$K$32-Assumptions!$J$32),IF(K8<=Assumptions!$F$32,Assumptions!$K$32+(K8-Assumptions!$E$32)/(Assumptions!$F$32-Assumptions!$E$32)*(Assumptions!$L$32-Assumptions!$K$32),IF(K8<=Assumptions!$G$32,Assumptions!$L$32+(K8-Assumptions!$F$32)/(Assumptions!$G$32-Assumptions!$F$32)*(Assumptions!$M$32-Assumptions!$L$32),Assumptions!$M$32))))))) -> 4.8 | U8: =IF(M8<=Assumptions!$B$33,Assumptions!$H$33,IF(M8<=Assumptions!$C$33,Assumptions!$H$33+(M8-Assumptions!$B$33)/(Assumptions!$C$33-Assumptions!$B$33)*(Assumptions!$I$33-Assumptions!$H$33),IF(M8<=Assumptions!$D$33,Assumptions!$I$33+(M8-Assumptions!$C$33)/(Assumptions!$D$33-Assumptions!$C$33)*(Assumptions!$J$33-Assumptions!$I$33),IF(M8<=Assumptions!$E$33,Assumptions!$J$33+(M8-Assumptions!$D$33)/(Assumptions!$E$33-Assumptions!$D$33)*(Assumptions!$K$33-Assumptions!$J$33),IF(M8<=Assumptions!$F$33,Assumptions!$K$33+(M8-Assumptions!$E$33)/(Assumptions!$F$33-Assumptions!$E$33)*(Assumptions!$L$33-Assumptions!$K$33),IF(M8<=Assumptions!$G$33,Assumptions!$L$33+(M8-Assumptions!$F$33)/(Assumptions!$G$33-Assumptions!$F$33)*(Assumptions!$M$33-Assumptions!$L$33),Assumptions!$M$33)))))) -> 58.5 | V8: =IF(N8<=Assumptions!$B$34,Assumptions!$H$34,IF(N8<=Assumptions!$C$34,Assumptions!$H$34+(N8-Assumptions!$B$34)/(Assumptions!$C$34-Assumptions!$B$34)*(Assumptions!$I$34-Assumptions!$H$34),IF(N8<=Assumptions!$D$34,Assumptions!$I$34+(N8-Assumptions!$C$34)/(Assumptions!$D$34-Assumptions!$C$34)*(Assumptions!$J$34-Assumptions!$I$34),IF(N8<=Assumptions!$E$34,Assumptions!$J$34+(N8-Assumptions!$D$34)/(Assumptions!$E$34-Assumptions!$D$34)*(Assumptions!$K$34-Assumptions!$J$34),IF(N8<=Assumptions!$F$34,Assumptions!$K$34+(N8-Assumptions!$E$34)/(Assumptions!$F$34-Assumptions!$E$34)*(Assumptions!$L$34-Assumptions!$K$34),IF(N8<=Assumptions!$G$34,Assumptions!$L$34+(N8-Assumptions!$F$34)/(Assumptions!$G$34-Assumptions!$F$34)*(Assumptions!$M$34-Assumptions!$L$34),Assumptions!$M$34)))))) -> 37 | W8: =IF(S8="",PERCENTILE($S$6:$S$30,Assumptions!$B$36),S8) -> 70 | X8: =IF(T8="",PERCENTILE($T$6:$T$30,Assumptions!$B$36),T8) -> 4.8 | Y8: =IF(O8="",PERCENTILE($O$6:$O$30,Assumptions!$B$36),O8) -> 42 | Z8: =W8*Assumptions!$B$16+X8*Assumptions!$B$17 -> 37.4 | AA8: =U8*Assumptions!$B$18+V8*Assumptions!$B$19 -> 47.75 | AB8: =AVERAGE(P8:R8) -> 57.333333 | AC8: 0 | AD8: =MIN(100,Z8*Assumptions!$B$11+AA8*Assumptions!$B$12+Y8*Assumptions!$B$13+AB8*Assumptions!$B$14+AC8*Assumptions!$B$20) -> 46.178333 | AE8: =MIN(1,SUMIFS(Network!$V$5:$V$14,Network!$D$5:$D$14,$A8,Network!$U$5:$U$14,1)) -> 1 | AF8: =MIN(1,SUMIFS(Network!$W$5:$W$14,Network!$D$5:$D$14,$A8,Network!$U$5:$U$14,1)) -> 1 | AG8: =MIN(1,SUMIFS(Network!$X$5:$X$14,Network!$D$5:$D$14,$A8,Network!$U$5:$U$14,1)) -> 1 | AH8: =AE8*Assumptions!$B$5+AF8*Assumptions!$B$6+AG8*Assumptions!$B$7 -> 1560 | AI8: =AH8/Assumptions!$B$8 -> 1 | AJ8: =AH8/52 -> 30 | AK8: =AJ8*I8 -> 360 | AL8: =MIN(100,I8/Assumptions!$B$26*100) -> 33.333333 | AM8: =MIN(100,H8/Assumptions!$B$27*100) -> 33.333333 | AN8: =AI8*100*Assumptions!$B$23+AL8*Assumptions!$B$24+AM8*Assumptions!$B$25 -> 66.666667 | AO8: =AN8*AD8/100 -> 30.785556 | AP8: =RANK(AO8,$AO$6:$AO$30)+COUNTIF($AO$6:AO8,AO8)-1 -> 9 | AQ8: =IF(AO8>=Assumptions!$B$39,"Critical",IF(AO8>=Assumptions!$B$40,"High",IF(AO8>=Assumptions!$B$41,"Elevated","Watch"))) -> High | AR8: =IF(AND(AN8>=Assumptions!$B$42,AD8>=Assumptions!$B$43),"Act now",IF(AN8>=Assumptions!$B$42,"Protect (structural)",IF(AD8>=Assumptions!$B$43,"Remediate supplier","Routine"))) -> Act now | AS8: =_xlfn.MAXIFS(Network!$T$5:$T$36,Network!$D$5:$D$36,$A8) -> 3 | AT8: =COUNT(K8:R8) -> 8 | AU8: =IF(AT8>=8,2,IF(AT8>=6,1,0)) -> 2 | AV8: =IF(OR(C8=1,LEFT(G8,9)="Confirmed"),1,0) -> 1 | AW8: =AS8+AU8+AV8 -> 6 | AX8: =IF(AW8>=Assumptions!$B$44,"High",IF(AW8>=Assumptions!$B$45,"Medium","Low")) -> High | AY8: =IF(OR(AQ8="Critical",AQ8="High"),IF(AX8="Low","VERIFY first – urgent sub-tier fact-find",IF(OR(AQ8="Critical",AV8=1),"ACT – mitigate now","CONFIRM sole-source status, then qualify alternate")),IF(AQ8="Elevated",IF(AX8="Low","VERIFY – add to N-tier survey","PLAN – qualify alternate in 90 days"),"MONITOR – quarterly review")) -> ACT – mitigate now | AZ8: =IF(K8&L8&O8<>"",IF(OR(K8="",L8="",O8=""),TRIM(IF(K8="","Current ratio; ","")&IF(L8="","Net debt/EBITDA; ","")&IF(O8="","Assurance gap","")),"—"),"Current ratio; Net debt/EBITDA; Assurance gap") -> —
A9: ORG-922 | B9: =INDEX(Data!$B$5:$B$34,MATCH($A9,Data!$A$5:$A$34,0)) -> Delta Capacitor Works Ltd. | C9: 1 | D9: Tier-1: C20 DC-link capacitor (P1,P2) | E9: =INDEX(Data!$G$38:$G$67,MATCH($A9,Data!$A$38:$A$67,0)) -> SITE-039 | F9: =INDEX(Data!$I$38:$I$67,MATCH($A9,Data!$A$38:$A$67,0)) -> Z03 | G9: Confirmed sole (100% allocation) | H9: 1 | I9: 8 | J9: Case: C20 qualification 8 wks | K9: =IF(INDEX(Data!$C$5:$C$34,MATCH($A9,Data!$A$5:$A$34,0))="","",INDEX(Data!$C$5:$C$34,MATCH($A9,Data!$A$5:$A$34,0))) -> 1.82 | L9: =IF(INDEX(Data!$D$5:$D$34,MATCH($A9,Data!$A$5:$A$34,0))="","",INDEX(Data!$D$5:$D$34,MATCH($A9,Data!$A$5:$A$34,0))) -> 1.67 | M9: =IF(INDEX(Data!$E$5:$E$34,MATCH($A9,Data!$A$5:$A$34,0))="","",INDEX(Data!$E$5:$E$34,MATCH($A9,Data!$A$5:$A$34,0))) -> 86.9 | N9: =IF(INDEX(Data!$F$5:$F$34,MATCH($A9,Data!$A$5:$A$34,0))="","",INDEX(Data!$F$5:$F$34,MATCH($A9,Data!$A$5:$A$34,0))) -> 2.2 | O9: =IF(INDEX(Data!$G$5:$G$34,MATCH($A9,Data!$A$5:$A$34,0))="","",INDEX(Data!$G$5:$G$34,MATCH($A9,Data!$A$5:$A$34,0))) -> 51 | P9: =IF(INDEX(Data!$H$5:$H$34,MATCH($A9,Data!$A$5:$A$34,0))="","",INDEX(Data!$H$5:$H$34,MATCH($A9,Data!$A$5:$A$34,0))) -> 19 | Q9: =IF(INDEX(Data!$I$5:$I$34,MATCH($A9,Data!$A$5:$A$34,0))="","",INDEX(Data!$I$5:$I$34,MATCH($A9,Data!$A$5:$A$34,0))) -> 26 | R9: =IF(INDEX(Data!$J$5:$J$34,MATCH($A9,Data!$A$5:$A$34,0))="","",INDEX(Data!$J$5:$J$34,MATCH($A9,Data!$A$5:$A$34,0))) -> 25 | S9: =IF(L9="","",IF(L9<=Assumptions!$B$31,Assumptions!$H$31,IF(L9<=Assumptions!$C$31,Assumptions!$H$31+(L9-Assumptions!$B$31)/(Assumptions!$C$31-Assumptions!$B$31)*(Assumptions!$I$31-Assumptions!$H$31),IF(L9<=Assumptions!$D$31,Assumptions!$I$31+(L9-Assumptions!$C$31)/(Assumptions!$D$31-Assumptions!$C$31)*(Assumptions!$J$31-Assumptions!$I$31),IF(L9<=Assumptions!$E$31,Assumptions!$J$31+(L9-Assumptions!$D$31)/(Assumptions!$E$31-Assumptions!$D$31)*(Assumptions!$K$31-Assumptions!$J$31),IF(L9<=Assumptions!$F$31,Assumptions!$K$31+(L9-Assumptions!$E$31)/(Assumptions!$F$31-Assumptions!$E$31)*(Assumptions!$L$31-Assumptions!$K$31),IF(L9<=Assumptions!$G$31,Assumptions!$L$31+(L9-Assumptions!$F$31)/(Assumptions!$G$31-Assumptions!$F$31)*(Assumptions!$M$31-Assumptions!$L$31),Assumptions!$M$31))))))) -> 20.04 | T9: =IF(K9="","",IF(K9<=Assumptions!$B$32,Assumptions!$H$32,IF(K9<=Assumptions!$C$32,Assumptions!$H$32+(K9-Assumptions!$B$32)/(Assumptions!$C$32-Assumptions!$B$32)*(Assumptions!$I$32-Assumptions!$H$32),IF(K9<=Assumptions!$D$32,Assumptions!$I$32+(K9-Assumptions!$C$32)/(Assumptions!$D$32-Assumptions!$C$32)*(Assumptions!$J$32-Assumptions!$I$32),IF(K9<=Assumptions!$E$32,Assumptions!$J$32+(K9-Assumptions!$D$32)/(Assumptions!$E$32-Assumptions!$D$32)*(Assumptions!$K$32-Assumptions!$J$32),IF(K9<=Assumptions!$F$32,Assumptions!$K$32+(K9-Assumptions!$E$32)/(Assumptions!$F$32-Assumptions!$E$32)*(Assumptions!$L$32-Assumptions!$K$32),IF(K9<=Assumptions!$G$32,Assumptions!$L$32+(K9-Assumptions!$F$32)/(Assumptions!$G$32-Assumptions!$F$32)*(Assumptions!$M$32-Assumptions!$L$32),Assumptions!$M$32))))))) -> 20.4 | U9: =IF(M9<=Assumptions!$B$33,Assumptions!$H$33,IF(M9<=Assumptions!$C$33,Assumptions!$H$33+(M9-Assumptions!$B$33)/(Assumptions!$C$33-Assumptions!$B$33)*(Assumptions!$I$33-Assumptions!$H$33),IF(M9<=Assumptions!$D$33,Assumptions!$I$33+(M9-Assumptions!$C$33)/(Assumptions!$D$33-Assumptions!$C$33)*(Assumptions!$J$33-Assumptions!$I$33),IF(M9<=Assumptions!$E$33,Assumptions!$J$33+(M9-Assumptions!$D$33)/(Assumptions!$E$33-Assumptions!$D$33)*(Assumptions!$K$33-Assumptions!$J$33),IF(M9<=Assumptions!$F$33,Assumptions!$K$33+(M9-Assumptions!$E$33)/(Assumptions!$F$33-Assumptions!$E$33)*(Assumptions!$L$33-Assumptions!$K$33),IF(M9<=Assumptions!$G$33,Assumptions!$L$33+(M9-Assumptions!$F$33)/(Assumptions!$G$33-Assumptions!$F$33)*(Assumptions!$M$33-Assumptions!$L$33),Assumptions!$M$33)))))) -> 40.5 | V9: =IF(N9<=Assumptions!$B$34,Assumptions!$H$34,IF(N9<=Assumptions!$C$34,Assumptions!$H$34+(N9-Assumptions!$B$34)/(Assumptions!$C$34-Assumptions!$B$34)*(Assumptions!$I$34-Assumptions!$H$34),IF(N9<=Assumptions!$D$34,Assumptions!$I$34+(N9-Assumptions!$C$34)/(Assumptions!$D$34-Assumptions!$C$34)*(Assumptions!$J$34-Assumptions!$I$34),IF(N9<=Assumptions!$E$34,Assumptions!$J$34+(N9-Assumptions!$D$34)/(Assumptions!$E$34-Assumptions!$D$34)*(Assumptions!$K$34-Assumptions!$J$34),IF(N9<=Assumptions!$F$34,Assumptions!$K$34+(N9-Assumptions!$E$34)/(Assumptions!$F$34-Assumptions!$E$34)*(Assumptions!$L$34-Assumptions!$K$34),IF(N9<=Assumptions!$G$34,Assumptions!$L$34+(N9-Assumptions!$F$34)/(Assumptions!$G$34-Assumptions!$F$34)*(Assumptions!$M$34-Assumptions!$L$34),Assumptions!$M$34)))))) -> 0 | W9: =IF(S9="",PERCENTILE($S$6:$S$30,Assumptions!$B$36),S9) -> 20.04 | X9: =IF(T9="",PERCENTILE($T$6:$T$30,Assumptions!$B$36),T9) -> 20.4 | Y9: =IF(O9="",PERCENTILE($O$6:$O$30,Assumptions!$B$36),O9) -> 51 | Z9: =W9*Assumptions!$B$16+X9*Assumptions!$B$17 -> 20.22 | AA9: =U9*Assumptions!$B$18+V9*Assumptions!$B$19 -> 20.25 | AB9: =AVERAGE(P9:R9) -> 23.333333 | AC9: 0 | AD9: =MIN(100,Z9*Assumptions!$B$11+AA9*Assumptions!$B$12+Y9*Assumptions!$B$13+AB9*Assumptions!$B$14+AC9*Assumptions!$B$20) -> 25.624333 | AE9: =MIN(1,SUMIFS(Network!$V$5:$V$14,Network!$D$5:$D$14,$A9,Network!$U$5:$U$14,1)) -> 1 | AF9: =MIN(1,SUMIFS(Network!$W$5:$W$14,Network!$D$5:$D$14,$A9,Network!$U$5:$U$14,1)) -> 1 | AG9: =MIN(1,SUMIFS(Network!$X$5:$X$14,Network!$D$5:$D$14,$A9,Network!$U$5:$U$14,1)) -> 0 | AH9: =AE9*Assumptions!$B$5+AF9*Assumptions!$B$6+AG9*Assumptions!$B$7 -> 1144 | AI9: =AH9/Assumptions!$B$8 -> 0.73333333 | AJ9: =AH9/52 -> 22 | AK9: =AJ9*I9 -> 176 | AL9: =MIN(100,I9/Assumptions!$B$26*100) -> 22.222222 | AM9: =MIN(100,H9/Assumptions!$B$27*100) -> 33.333333 | AN9: =AI9*100*Assumptions!$B$23+AL9*Assumptions!$B$24+AM9*Assumptions!$B$25 -> 50 | AO9: =AN9*AD9/100 -> 12.812167 | AP9: =RANK(AO9,$AO$6:$AO$30)+COUNTIF($AO$6:AO9,AO9)-1 -> 20 | AQ9: =IF(AO9>=Assumptions!$B$39,"Critical",IF(AO9>=Assumptions!$B$40,"High",IF(AO9>=Assumptions!$B$41,"Elevated","Watch"))) -> Watch | AR9: =IF(AND(AN9>=Assumptions!$B$42,AD9>=Assumptions!$B$43),"Act now",IF(AN9>=Assumptions!$B$42,"Protect (structural)",IF(AD9>=Assumptions!$B$43,"Remediate supplier","Routine"))) -> Routine | AS9: =_xlfn.MAXIFS(Network!$T$5:$T$36,Network!$D$5:$D$36,$A9) -> 3 | AT9: =COUNT(K9:R9) -> 8 | AU9: =IF(AT9>=8,2,IF(AT9>=6,1,0)) -> 2 | AV9: =IF(OR(C9=1,LEFT(G9,9)="Confirmed"),1,0) -> 1 | AW9: =AS9+AU9+AV9 -> 6 | AX9: =IF(AW9>=Assumptions!$B$44,"High",IF(AW9>=Assumptions!$B$45,"Medium","Low")) -> High | AY9: =IF(OR(AQ9="Critical",AQ9="High"),IF(AX9="Low","VERIFY first – urgent sub-tier fact-find",IF(OR(AQ9="Critical",AV9=1),"ACT – mitigate now","CONFIRM sole-source status, then qualify alternate")),IF(AQ9="Elevated",IF(AX9="Low","VERIFY – add to N-tier survey","PLAN – qualify alternate in 90 days"),"MONITOR – quarterly review")) -> MONITOR – quarterly review | AZ9: =IF(K9&L9&O9<>"",IF(OR(K9="",L9="",O9=""),TRIM(IF(K9="","Current ratio; ","")&IF(L9="","Net debt/EBITDA; ","")&IF(O9="","Assurance gap","")),"—"),"Current ratio; Net debt/EBITDA; Assurance gap") -> —
A10: ORG-786 | B10: =INDEX(Data!$B$5:$B$34,MATCH($A10,Data!$A$5:$A$34,0)) -> Estuary Thermal Systems Ltd. | C10: 1 | D10: Tier-1: H20 cooling (P2,P3) | E10: =INDEX(Data!$G$38:$G$67,MATCH($A10,Data!$A$38:$A$67,0)) -> SITE-046 | F10: =INDEX(Data!$I$38:$I$67,MATCH($A10,Data!$A$38:$A$67,0)) -> Z06 | G10: Confirmed sole (100% allocation) | H10: 1 | I10: 6 | J10: Case: H20 qualification 6 wks | K10: =IF(INDEX(Data!$C$5:$C$34,MATCH($A10,Data!$A$5:$A$34,0))="","",INDEX(Data!$C$5:$C$34,MATCH($A10,Data!$A$5:$A$34,0))) -> 2.53 | L10: =IF(INDEX(Data!$D$5:$D$34,MATCH($A10,Data!$A$5:$A$34,0))="","",INDEX(Data!$D$5:$D$34,MATCH($A10,Data!$A$5:$A$34,0))) -> 2.67 | M10: =IF(INDEX(Data!$E$5:$E$34,MATCH($A10,Data!$A$5:$A$34,0))="","",INDEX(Data!$E$5:$E$34,MATCH($A10,Data!$A$5:$A$34,0))) -> 89.7 | N10: =IF(INDEX(Data!$F$5:$F$34,MATCH($A10,Data!$A$5:$A$34,0))="","",INDEX(Data!$F$5:$F$34,MATCH($A10,Data!$A$5:$A$34,0))) -> 1.8 | O10: =IF(INDEX(Data!$G$5:$G$34,MATCH($A10,Data!$A$5:$A$34,0))="","",INDEX(Data!$G$5:$G$34,MATCH($A10,Data!$A$5:$A$34,0))) -> 60 | P10: =IF(INDEX(Data!$H$5:$H$34,MATCH($A10,Data!$A$5:$A$34,0))="","",INDEX(Data!$H$5:$H$34,MATCH($A10,Data!$A$5:$A$34,0))) -> 67 | Q10: =IF(INDEX(Data!$I$5:$I$34,MATCH($A10,Data!$A$5:$A$34,0))="","",INDEX(Data!$I$5:$I$34,MATCH($A10,Data!$A$5:$A$34,0))) -> 59 | R10: =IF(INDEX(Data!$J$5:$J$34,MATCH($A10,Data!$A$5:$A$34,0))="","",INDEX(Data!$J$5:$J$34,MATCH($A10,Data!$A$5:$A$34,0))) -> 54 | S10: =IF(L10="","",IF(L10<=Assumptions!$B$31,Assumptions!$H$31,IF(L10<=Assumptions!$C$31,Assumptions!$H$31+(L10-Assumptions!$B$31)/(Assumptions!$C$31-Assumptions!$B$31)*(Assumptions!$I$31-Assumptions!$H$31),IF(L10<=Assumptions!$D$31,Assumptions!$I$31+(L10-Assumptions!$C$31)/(Assumptions!$D$31-Assumptions!$C$31)*(Assumptions!$J$31-Assumptions!$I$31),IF(L10<=Assumptions!$E$31,Assumptions!$J$31+(L10-Assumptions!$D$31)/(Assumptions!$E$31-Assumptions!$D$31)*(Assumptions!$K$31-Assumptions!$J$31),IF(L10<=Assumptions!$F$31,Assumptions!$K$31+(L10-Assumptions!$E$31)/(Assumptions!$F$31-Assumptions!$E$31)*(Assumptions!$L$31-Assumptions!$K$31),IF(L10<=Assumptions!$G$31,Assumptions!$L$31+(L10-Assumptions!$F$31)/(Assumptions!$G$31-Assumptions!$F$31)*(Assumptions!$M$31-Assumptions!$L$31),Assumptions!$M$31))))))) -> 34.533333 | T10: =IF(K10="","",IF(K10<=Assumptions!$B$32,Assumptions!$H$32,IF(K10<=Assumptions!$C$32,Assumptions!$H$32+(K10-Assumptions!$B$32)/(Assumptions!$C$32-Assumptions!$B$32)*(Assumptions!$I$32-Assumptions!$H$32),IF(K10<=Assumptions!$D$32,Assumptions!$I$32+(K10-Assumptions!$C$32)/(Assumptions!$D$32-Assumptions!$C$32)*(Assumptions!$J$32-Assumptions!$I$32),IF(K10<=Assumptions!$E$32,Assumptions!$J$32+(K10-Assumptions!$D$32)/(Assumptions!$E$32-Assumptions!$D$32)*(Assumptions!$K$32-Assumptions!$J$32),IF(K10<=Assumptions!$F$32,Assumptions!$K$32+(K10-Assumptions!$E$32)/(Assumptions!$F$32-Assumptions!$E$32)*(Assumptions!$L$32-Assumptions!$K$32),IF(K10<=Assumptions!$G$32,Assumptions!$L$32+(K10-Assumptions!$F$32)/(Assumptions!$G$32-Assumptions!$F$32)*(Assumptions!$M$32-Assumptions!$L$32),Assumptions!$M$32))))))) -> 0 | U10: =IF(M10<=Assumptions!$B$33,Assumptions!$H$33,IF(M10<=Assumptions!$C$33,Assumptions!$H$33+(M10-Assumptions!$B$33)/(Assumptions!$C$33-Assumptions!$B$33)*(Assumptions!$I$33-Assumptions!$H$33),IF(M10<=Assumptions!$D$33,Assumptions!$I$33+(M10-Assumptions!$C$33)/(Assumptions!$D$33-Assumptions!$C$33)*(Assumptions!$J$33-Assumptions!$I$33),IF(M10<=Assumptions!$E$33,Assumptions!$J$33+(M10-Assumptions!$D$33)/(Assumptions!$E$33-Assumptions!$D$33)*(Assumptions!$K$33-Assumptions!$J$33),IF(M10<=Assumptions!$F$33,Assumptions!$K$33+(M10-Assumptions!$E$33)/(Assumptions!$F$33-Assumptions!$E$33)*(Assumptions!$L$33-Assumptions!$K$33),IF(M10<=Assumptions!$G$33,Assumptions!$L$33+(M10-Assumptions!$F$33)/(Assumptions!$G$33-Assumptions!$F$33)*(Assumptions!$M$33-Assumptions!$L$33),Assumptions!$M$33)))))) -> 26.5 | V10: =IF(N10<=Assumptions!$B$34,Assumptions!$H$34,IF(N10<=Assumptions!$C$34,Assumptions!$H$34+(N10-Assumptions!$B$34)/(Assumptions!$C$34-Assumptions!$B$34)*(Assumptions!$I$34-Assumptions!$H$34),IF(N10<=Assumptions!$D$34,Assumptions!$I$34+(N10-Assumptions!$C$34)/(Assumptions!$D$34-Assumptions!$C$34)*(Assumptions!$J$34-Assumptions!$I$34),IF(N10<=Assumptions!$E$34,Assumptions!$J$34+(N10-Assumptions!$D$34)/(Assumptions!$E$34-Assumptions!$D$34)*(Assumptions!$K$34-Assumptions!$J$34),IF(N10<=Assumptions!$F$34,Assumptions!$K$34+(N10-Assumptions!$E$34)/(Assumptions!$F$34-Assumptions!$E$34)*(Assumptions!$L$34-Assumptions!$K$34),IF(N10<=Assumptions!$G$34,Assumptions!$L$34+(N10-Assumptions!$F$34)/(Assumptions!$G$34-Assumptions!$F$34)*(Assumptions!$M$34-Assumptions!$L$34),Assumptions!$M$34)))))) -> 2 | W10: =IF(S10="",PERCENTILE($S$6:$S$30,Assumptions!$B$36),S10) -> 34.533333 | X10: =IF(T10="",PERCENTILE($T$6:$T$30,Assumptions!$B$36),T10) -> 0 | Y10: =IF(O10="",PERCENTILE($O$6:$O$30,Assumptions!$B$36),O10) -> 60 | Z10: =W10*Assumptions!$B$16+X10*Assumptions!$B$17 -> 17.266667 | AA10: =U10*Assumptions!$B$18+V10*Assumptions!$B$19 -> 14.25 | AB10: =AVERAGE(P10:R10) -> 60 | AC10: 0 | AD10: =MIN(100,Z10*Assumptions!$B$11+AA10*Assumptions!$B$12+Y10*Assumptions!$B$13+AB10*Assumptions!$B$14+AC10*Assumptions!$B$20) -> 33.455 | AE10: =MIN(1,SUMIFS(Network!$V$5:$V$14,Network!$D$5:$D$14,$A10,Network!$U$5:$U$14,1)) -> 0 | AF10: =MIN(1,SUMIFS(Network!$W$5:$W$14,Network!$D$5:$D$14,$A10,Network!$U$5:$U$14,1)) -> 1 | AG10: =MIN(1,SUMIFS(Network!$X$5:$X$14,Network!$D$5:$D$14,$A10,Network!$U$5:$U$14,1)) -> 1 | AH10: =AE10*Assumptions!$B$5+AF10*Assumptions!$B$6+AG10*Assumptions!$B$7 -> 936 | AI10: =AH10/Assumptions!$B$8 -> 0.6 | AJ10: =AH10/52 -> 18 | AK10: =AJ10*I10 -> 108 | AL10: =MIN(100,I10/Assumptions!$B$26*100) -> 16.666667 | AM10: =MIN(100,H10/Assumptions!$B$27*100) -> 33.333333 | AN10: =AI10*100*Assumptions!$B$23+AL10*Assumptions!$B$24+AM10*Assumptions!$B$25 -> 41.666667 | AO10: =AN10*AD10/100 -> 13.939583 | AP10: =RANK(AO10,$AO$6:$AO$30)+COUNTIF($AO$6:AO10,AO10)-1 -> 18 | AQ10: =IF(AO10>=Assumptions!$B$39,"Critical",IF(AO10>=Assumptions!$B$40,"High",IF(AO10>=Assumptions!$B$41,"Elevated","Watch"))) -> Watch | AR10: =IF(AND(AN10>=Assumptions!$B$42,AD10>=Assumptions!$B$43),"Act now",IF(AN10>=Assumptions!$B$42,"Protect (structural)",IF(AD10>=Assumptions!$B$43,"Remediate supplier","Routine"))) -> Routine | AS10: =_xlfn.MAXIFS(Network!$T$5:$T$36,Network!$D$5:$D$36,$A10) -> 3 | AT10: =COUNT(K10:R10) -> 8 | AU10: =IF(AT10>=8,2,IF(AT10>=6,1,0)) -> 2 | AV10: =IF(OR(C10=1,LEFT(G10,9)="Confirmed"),1,0) -> 1 | AW10: =AS10+AU10+AV10 -> 6 | AX10: =IF(AW10>=Assumptions!$B$44,"High",IF(AW10>=Assumptions!$B$45,"Medium","Low")) -> High | AY10: =IF(OR(AQ10="Critical",AQ10="High"),IF(AX10="Low","VERIFY first – urgent sub-tier fact-find",IF(OR(AQ10="Critical",AV10=1),"ACT – mitigate now","CONFIRM sole-source status, then qualify alternate")),IF(AQ10="Elevated",IF(AX10="Low","VERIFY – add to N-tier survey","PLAN – qualify alternate in 90 days"),"MONITOR – quarterly review")) -> MONITOR – quarterly review | AZ10: =IF(K10&L10&O10<>"",IF(OR(K10="",L10="",O10=""),TRIM(IF(K10="","Current ratio; ","")&IF(L10="","Net debt/EBITDA; ","")&IF(O10="","Assurance gap","")),"—"),"Current ratio; Net debt/EBITDA; Assurance gap") -> —
A11: ORG-287 | B11: =INDEX(Data!$B$5:$B$34,MATCH($A11,Data!$A$5:$A$34,0)) -> ForgeLine Enclosures Ltd. | C11: 1 | D11: Tier-1: H10 housing (P1) | E11: =INDEX(Data!$G$38:$G$67,MATCH($A11,Data!$A$38:$A$67,0)) -> SITE-053 | F11: =INDEX(Data!$I$38:$I$67,MATCH($A11,Data!$A$38:$A$67,0)) -> Z02 | G11: Confirmed sole (100% allocation) | H11: 1 | I11: 4 | J11: Case: H10 qualification 4 wks | K11: =IF(INDEX(Data!$C$5:$C$34,MATCH($A11,Data!$A$5:$A$34,0))="","",INDEX(Data!$C$5:$C$34,MATCH($A11,Data!$A$5:$A$34,0))) -> 1.94 | L11: =IF(INDEX(Data!$D$5:$D$34,MATCH($A11,Data!$A$5:$A$34,0))="","",INDEX(Data!$D$5:$D$34,MATCH($A11,Data!$A$5:$A$34,0))) -> 3.67 | M11: =IF(INDEX(Data!$E$5:$E$34,MATCH($A11,Data!$A$5:$A$34,0))="","",INDEX(Data!$E$5:$E$34,MATCH($A11,Data!$A$5:$A$34,0))) -> 89.8 | N11: =IF(INDEX(Data!$F$5:$F$34,MATCH($A11,Data!$A$5:$A$34,0))="","",INDEX(Data!$F$5:$F$34,MATCH($A11,Data!$A$5:$A$34,0))) -> -0.3 | O11: =IF(INDEX(Data!$G$5:$G$34,MATCH($A11,Data!$A$5:$A$34,0))="","",INDEX(Data!$G$5:$G$34,MATCH($A11,Data!$A$5:$A$34,0))) -> 69 | P11: =IF(INDEX(Data!$H$5:$H$34,MATCH($A11,Data!$A$5:$A$34,0))="","",INDEX(Data!$H$5:$H$34,MATCH($A11,Data!$A$5:$A$34,0))) -> 27 | Q11: =IF(INDEX(Data!$I$5:$I$34,MATCH($A11,Data!$A$5:$A$34,0))="","",INDEX(Data!$I$5:$I$34,MATCH($A11,Data!$A$5:$A$34,0))) -> 30 | R11: =IF(INDEX(Data!$J$5:$J$34,MATCH($A11,Data!$A$5:$A$34,0))="","",INDEX(Data!$J$5:$J$34,MATCH($A11,Data!$A$5:$A$34,0))) -> 24 | S11: =IF(L11="","",IF(L11<=Assumptions!$B$31,Assumptions!$H$31,IF(L11<=Assumptions!$C$31,Assumptions!$H$31+(L11-Assumptions!$B$31)/(Assumptions!$C$31-Assumptions!$B$31)*(Assumptions!$I$31-Assumptions!$H$31),IF(L11<=Assumptions!$D$31,Assumptions!$I$31+(L11-Assumptions!$C$31)/(Assumptions!$D$31-Assumptions!$C$31)*(Assumptions!$J$31-Assumptions!$I$31),IF(L11<=Assumptions!$E$31,Assumptions!$J$31+(L11-Assumptions!$D$31)/(Assumptions!$E$31-Assumptions!$D$31)*(Assumptions!$K$31-Assumptions!$J$31),IF(L11<=Assumptions!$F$31,Assumptions!$K$31+(L11-Assumptions!$E$31)/(Assumptions!$F$31-Assumptions!$E$31)*(Assumptions!$L$31-Assumptions!$K$31),IF(L11<=Assumptions!$G$31,Assumptions!$L$31+(L11-Assumptions!$F$31)/(Assumptions!$G$31-Assumptions!$F$31)*(Assumptions!$M$31-Assumptions!$L$31),Assumptions!$M$31))))))) -> 61.2 | T11: =IF(K11="","",IF(K11<=Assumptions!$B$32,Assumptions!$H$32,IF(K11<=Assumptions!$C$32,Assumptions!$H$32+(K11-Assumptions!$B$32)/(Assumptions!$C$32-Assumptions!$B$32)*(Assumptions!$I$32-Assumptions!$H$32),IF(K11<=Assumptions!$D$32,Assumptions!$I$32+(K11-Assumptions!$C$32)/(Assumptions!$D$32-Assumptions!$C$32)*(Assumptions!$J$32-Assumptions!$I$32),IF(K11<=Assumptions!$E$32,Assumptions!$J$32+(K11-Assumptions!$D$32)/(Assumptions!$E$32-Assumptions!$D$32)*(Assumptions!$K$32-Assumptions!$J$32),IF(K11<=Assumptions!$F$32,Assumptions!$K$32+(K11-Assumptions!$E$32)/(Assumptions!$F$32-Assumptions!$E$32)*(Assumptions!$L$32-Assumptions!$K$32),IF(K11<=Assumptions!$G$32,Assumptions!$L$32+(K11-Assumptions!$F$32)/(Assumptions!$G$32-Assumptions!$F$32)*(Assumptions!$M$32-Assumptions!$L$32),Assumptions!$M$32))))))) -> 16.8 | U11: =IF(M11<=Assumptions!$B$33,Assumptions!$H$33,IF(M11<=Assumptions!$C$33,Assumptions!$H$33+(M11-Assumptions!$B$33)/(Assumptions!$C$33-Assumptions!$B$33)*(Assumptions!$I$33-Assumptions!$H$33),IF(M11<=Assumptions!$D$33,Assumptions!$I$33+(M11-Assumptions!$C$33)/(Assumptions!$D$33-Assumptions!$C$33)*(Assumptions!$J$33-Assumptions!$I$33),IF(M11<=Assumptions!$E$33,Assumptions!$J$33+(M11-Assumptions!$D$33)/(Assumptions!$E$33-Assumptions!$D$33)*(Assumptions!$K$33-Assumptions!$J$33),IF(M11<=Assumptions!$F$33,Assumptions!$K$33+(M11-Assumptions!$E$33)/(Assumptions!$F$33-Assumptions!$E$33)*(Assumptions!$L$33-Assumptions!$K$33),IF(M11<=Assumptions!$G$33,Assumptions!$L$33+(M11-Assumptions!$F$33)/(Assumptions!$G$33-Assumptions!$F$33)*(Assumptions!$M$33-Assumptions!$L$33),Assumptions!$M$33)))))) -> 26 | V11: =IF(N11<=Assumptions!$B$34,Assumptions!$H$34,IF(N11<=Assumptions!$C$34,Assumptions!$H$34+(N11-Assumptions!$B$34)/(Assumptions!$C$34-Assumptions!$B$34)*(Assumptions!$I$34-Assumptions!$H$34),IF(N11<=Assumptions!$D$34,Assumptions!$I$34+(N11-Assumptions!$C$34)/(Assumptions!$D$34-Assumptions!$C$34)*(Assumptions!$J$34-Assumptions!$I$34),IF(N11<=Assumptions!$E$34,Assumptions!$J$34+(N11-Assumptions!$D$34)/(Assumptions!$E$34-Assumptions!$D$34)*(Assumptions!$K$34-Assumptions!$J$34),IF(N11<=Assumptions!$F$34,Assumptions!$K$34+(N11-Assumptions!$E$34)/(Assumptions!$F$34-Assumptions!$E$34)*(Assumptions!$L$34-Assumptions!$K$34),IF(N11<=Assumptions!$G$34,Assumptions!$L$34+(N11-Assumptions!$F$34)/(Assumptions!$G$34-Assumptions!$F$34)*(Assumptions!$M$34-Assumptions!$L$34),Assumptions!$M$34)))))) -> 22.25 | W11: =IF(S11="",PERCENTILE($S$6:$S$30,Assumptions!$B$36),S11) -> 61.2 | X11: =IF(T11="",PERCENTILE($T$6:$T$30,Assumptions!$B$36),T11) -> 16.8 | Y11: =IF(O11="",PERCENTILE($O$6:$O$30,Assumptions!$B$36),O11) -> 69 | Z11: =W11*Assumptions!$B$16+X11*Assumptions!$B$17 -> 39 | AA11: =U11*Assumptions!$B$18+V11*Assumptions!$B$19 -> 24.125 | AB11: =AVERAGE(P11:R11) -> 27 | AC11: 0 | AD11: =MIN(100,Z11*Assumptions!$B$11+AA11*Assumptions!$B$12+Y11*Assumptions!$B$13+AB11*Assumptions!$B$14+AC11*Assumptions!$B$20) -> 36.0375 | AE11: =MIN(1,SUMIFS(Network!$V$5:$V$14,Network!$D$5:$D$14,$A11,Network!$U$5:$U$14,1)) -> 1 | AF11: =MIN(1,SUMIFS(Network!$W$5:$W$14,Network!$D$5:$D$14,$A11,Network!$U$5:$U$14,1)) -> 0 | AG11: =MIN(1,SUMIFS(Network!$X$5:$X$14,Network!$D$5:$D$14,$A11,Network!$U$5:$U$14,1)) -> 0 | AH11: =AE11*Assumptions!$B$5+AF11*Assumptions!$B$6+AG11*Assumptions!$B$7 -> 624 | AI11: =AH11/Assumptions!$B$8 -> 0.4 | AJ11: =AH11/52 -> 12 | AK11: =AJ11*I11 -> 48 | AL11: =MIN(100,I11/Assumptions!$B$26*100) -> 11.111111 | AM11: =MIN(100,H11/Assumptions!$B$27*100) -> 33.333333 | AN11: =AI11*100*Assumptions!$B$23+AL11*Assumptions!$B$24+AM11*Assumptions!$B$25 -> 30 | AO11: =AN11*AD11/100 -> 10.81125 | AP11: =RANK(AO11,$AO$6:$AO$30)+COUNTIF($AO$6:AO11,AO11)-1 -> 23 | AQ11: =IF(AO11>=Assumptions!$B$39,"Critical",IF(AO11>=Assumptions!$B$40,"High",IF(AO11>=Assumptions!$B$41,"Elevated","Watch"))) -> Watch | AR11: =IF(AND(AN11>=Assumptions!$B$42,AD11>=Assumptions!$B$43),"Act now",IF(AN11>=Assumptions!$B$42,"Protect (structural)",IF(AD11>=Assumptions!$B$43,"Remediate supplier","Routine"))) -> Routine | AS11: =_xlfn.MAXIFS(Network!$T$5:$T$36,Network!$D$5:$D$36,$A11) -> 3 | AT11: =COUNT(K11:R11) -> 8 | AU11: =IF(AT11>=8,2,IF(AT11>=6,1,0)) -> 2 | AV11: =IF(OR(C11=1,LEFT(G11,9)="Confirmed"),1,0) -> 1 | AW11: =AS11+AU11+AV11 -> 6 | AX11: =IF(AW11>=Assumptions!$B$44,"High",IF(AW11>=Assumptions!$B$45,"Medium","Low")) -> High | AY11: =IF(OR(AQ11="Critical",AQ11="High"),IF(AX11="Low","VERIFY first – urgent sub-tier fact-find",IF(OR(AQ11="Critical",AV11=1),"ACT – mitigate now","CONFIRM sole-source status, then qualify alternate")),IF(AQ11="Elevated",IF(AX11="Low","VERIFY – add to N-tier survey","PLAN – qualify alternate in 90 days"),"MONITOR – quarterly review")) -> MONITOR – quarterly review | AZ11: =IF(K11&L11&O11<>"",IF(OR(K11="",L11="",O11=""),TRIM(IF(K11="","Current ratio; ","")&IF(L11="","Net debt/EBITDA; ","")&IF(O11="","Assurance gap","")),"—"),"Current ratio; Net debt/EBITDA; Assurance gap") -> —
A12: ORG-103 | B12: =INDEX(Data!$B$5:$B$34,MATCH($A12,Data!$A$5:$A$34,0)) -> Grove Battery Controls Ltd. | C12: 1 | D12: Tier-1: B10 battery board (80%) | E12: =INDEX(Data!$G$38:$G$67,MATCH($A12,Data!$A$38:$A$67,0)) -> SITE-060 | F12: =INDEX(Data!$I$38:$I$67,MATCH($A12,Data!$A$38:$A$67,0)) -> Z04 | G12: Majority (80%) | H12: 1 | I12: 12 | J12: Case: B10 qualification 12 wks | K12: =IF(INDEX(Data!$C$5:$C$34,MATCH($A12,Data!$A$5:$A$34,0))="","",INDEX(Data!$C$5:$C$34,MATCH($A12,Data!$A$5:$A$34,0))) -> 1.51 | L12: =IF(INDEX(Data!$D$5:$D$34,MATCH($A12,Data!$A$5:$A$34,0))="","",INDEX(Data!$D$5:$D$34,MATCH($A12,Data!$A$5:$A$34,0))) -> 1.33 | M12: =IF(INDEX(Data!$E$5:$E$34,MATCH($A12,Data!$A$5:$A$34,0))="","",INDEX(Data!$E$5:$E$34,MATCH($A12,Data!$A$5:$A$34,0))) -> 78.8 | N12: =IF(INDEX(Data!$F$5:$F$34,MATCH($A12,Data!$A$5:$A$34,0))="","",INDEX(Data!$F$5:$F$34,MATCH($A12,Data!$A$5:$A$34,0))) -> -0.9 | O12: =IF(INDEX(Data!$G$5:$G$34,MATCH($A12,Data!$A$5:$A$34,0))="","",INDEX(Data!$G$5:$G$34,MATCH($A12,Data!$A$5:$A$34,0))) -> 18 | P12: =IF(INDEX(Data!$H$5:$H$34,MATCH($A12,Data!$A$5:$A$34,0))="","",INDEX(Data!$H$5:$H$34,MATCH($A12,Data!$A$5:$A$34,0))) -> 58 | Q12: =IF(INDEX(Data!$I$5:$I$34,MATCH($A12,Data!$A$5:$A$34,0))="","",INDEX(Data!$I$5:$I$34,MATCH($A12,Data!$A$5:$A$34,0))) -> 62 | R12: =IF(INDEX(Data!$J$5:$J$34,MATCH($A12,Data!$A$5:$A$34,0))="","",INDEX(Data!$J$5:$J$34,MATCH($A12,Data!$A$5:$A$34,0))) -> 52 | S12: =IF(L12="","",IF(L12<=Assumptions!$B$31,Assumptions!$H$31,IF(L12<=Assumptions!$C$31,Assumptions!$H$31+(L12-Assumptions!$B$31)/(Assumptions!$C$31-Assumptions!$B$31)*(Assumptions!$I$31-Assumptions!$H$31),IF(L12<=Assumptions!$D$31,Assumptions!$I$31+(L12-Assumptions!$C$31)/(Assumptions!$D$31-Assumptions!$C$31)*(Assumptions!$J$31-Assumptions!$I$31),IF(L12<=Assumptions!$E$31,Assumptions!$J$31+(L12-Assumptions!$D$31)/(Assumptions!$E$31-Assumptions!$D$31)*(Assumptions!$K$31-Assumptions!$J$31),IF(L12<=Assumptions!$F$31,Assumptions!$K$31+(L12-Assumptions!$E$31)/(Assumptions!$F$31-Assumptions!$E$31)*(Assumptions!$L$31-Assumptions!$K$31),IF(L12<=Assumptions!$G$31,Assumptions!$L$31+(L12-Assumptions!$F$31)/(Assumptions!$G$31-Assumptions!$F$31)*(Assumptions!$M$31-Assumptions!$L$31),Assumptions!$M$31))))))) -> 15.96 | T12: =IF(K12="","",IF(K12<=Assumptions!$B$32,Assumptions!$H$32,IF(K12<=Assumptions!$C$32,Assumptions!$H$32+(K12-Assumptions!$B$32)/(Assumptions!$C$32-Assumptions!$B$32)*(Assumptions!$I$32-Assumptions!$H$32),IF(K12<=Assumptions!$D$32,Assumptions!$I$32+(K12-Assumptions!$C$32)/(Assumptions!$D$32-Assumptions!$C$32)*(Assumptions!$J$32-Assumptions!$I$32),IF(K12<=Assumptions!$E$32,Assumptions!$J$32+(K12-Assumptions!$D$32)/(Assumptions!$E$32-Assumptions!$D$32)*(Assumptions!$K$32-Assumptions!$J$32),IF(K12<=Assumptions!$F$32,Assumptions!$K$32+(K12-Assumptions!$E$32)/(Assumptions!$F$32-Assumptions!$E$32)*(Assumptions!$L$32-Assumptions!$K$32),IF(K12<=Assumptions!$G$32,Assumptions!$L$32+(K12-Assumptions!$F$32)/(Assumptions!$G$32-Assumptions!$F$32)*(Assumptions!$M$32-Assumptions!$L$32),Assumptions!$M$32))))))) -> 29.7 | U12: =IF(M12<=Assumptions!$B$33,Assumptions!$H$33,IF(M12<=Assumptions!$C$33,Assumptions!$H$33+(M12-Assumptions!$B$33)/(Assumptions!$C$33-Assumptions!$B$33)*(Assumptions!$I$33-Assumptions!$H$33),IF(M12<=Assumptions!$D$33,Assumptions!$I$33+(M12-Assumptions!$C$33)/(Assumptions!$D$33-Assumptions!$C$33)*(Assumptions!$J$33-Assumptions!$I$33),IF(M12<=Assumptions!$E$33,Assumptions!$J$33+(M12-Assumptions!$D$33)/(Assumptions!$E$33-Assumptions!$D$33)*(Assumptions!$K$33-Assumptions!$J$33),IF(M12<=Assumptions!$F$33,Assumptions!$K$33+(M12-Assumptions!$E$33)/(Assumptions!$F$33-Assumptions!$E$33)*(Assumptions!$L$33-Assumptions!$K$33),IF(M12<=Assumptions!$G$33,Assumptions!$L$33+(M12-Assumptions!$F$33)/(Assumptions!$G$33-Assumptions!$F$33)*(Assumptions!$M$33-Assumptions!$L$33),Assumptions!$M$33)))))) -> 81 | V12: =IF(N12<=Assumptions!$B$34,Assumptions!$H$34,IF(N12<=Assumptions!$C$34,Assumptions!$H$34+(N12-Assumptions!$B$34)/(Assumptions!$C$34-Assumptions!$B$34)*(Assumptions!$I$34-Assumptions!$H$34),IF(N12<=Assumptions!$D$34,Assumptions!$I$34+(N12-Assumptions!$C$34)/(Assumptions!$D$34-Assumptions!$C$34)*(Assumptions!$J$34-Assumptions!$I$34),IF(N12<=Assumptions!$E$34,Assumptions!$J$34+(N12-Assumptions!$D$34)/(Assumptions!$E$34-Assumptions!$D$34)*(Assumptions!$K$34-Assumptions!$J$34),IF(N12<=Assumptions!$F$34,Assumptions!$K$34+(N12-Assumptions!$E$34)/(Assumptions!$F$34-Assumptions!$E$34)*(Assumptions!$L$34-Assumptions!$K$34),IF(N12<=Assumptions!$G$34,Assumptions!$L$34+(N12-Assumptions!$F$34)/(Assumptions!$G$34-Assumptions!$F$34)*(Assumptions!$M$34-Assumptions!$L$34),Assumptions!$M$34)))))) -> 26.75 | W12: =IF(S12="",PERCENTILE($S$6:$S$30,Assumptions!$B$36),S12) -> 15.96 | X12: =IF(T12="",PERCENTILE($T$6:$T$30,Assumptions!$B$36),T12) -> 29.7 | Y12: =IF(O12="",PERCENTILE($O$6:$O$30,Assumptions!$B$36),O12) -> 18 | Z12: =W12*Assumptions!$B$16+X12*Assumptions!$B$17 -> 22.83 | AA12: =U12*Assumptions!$B$18+V12*Assumptions!$B$19 -> 53.875 | AB12: =AVERAGE(P12:R12) -> 57.333333 | AC12: 0 | AD12: =MIN(100,Z12*Assumptions!$B$11+AA12*Assumptions!$B$12+Y12*Assumptions!$B$13+AB12*Assumptions!$B$14+AC12*Assumptions!$B$20) -> 40.044833 | AE12: =MIN(1,SUMIFS(Network!$V$5:$V$14,Network!$D$5:$D$14,$A12,Network!$U$5:$U$14,1)) -> 0 | AF12: =MIN(1,SUMIFS(Network!$W$5:$W$14,Network!$D$5:$D$14,$A12,Network!$U$5:$U$14,1)) -> 0 | AG12: =MIN(1,SUMIFS(Network!$X$5:$X$14,Network!$D$5:$D$14,$A12,Network!$U$5:$U$14,1)) -> 0.8 | AH12: =AE12*Assumptions!$B$5+AF12*Assumptions!$B$6+AG12*Assumptions!$B$7 -> 332.8 | AI12: =AH12/Assumptions!$B$8 -> 0.21333333 | AJ12: =AH12/52 -> 6.4 | AK12: =AJ12*I12 -> 76.8 | AL12: =MIN(100,I12/Assumptions!$B$26*100) -> 33.333333 | AM12: =MIN(100,H12/Assumptions!$B$27*100) -> 33.333333 | AN12: =AI12*100*Assumptions!$B$23+AL12*Assumptions!$B$24+AM12*Assumptions!$B$25 -> 27.333333 | AO12: =AN12*AD12/100 -> 10.945588 | AP12: =RANK(AO12,$AO$6:$AO$30)+COUNTIF($AO$6:AO12,AO12)-1 -> 22 | AQ12: =IF(AO12>=Assumptions!$B$39,"Critical",IF(AO12>=Assumptions!$B$40,"High",IF(AO12>=Assumptions!$B$41,"Elevated","Watch"))) -> Watch | AR12: =IF(AND(AN12>=Assumptions!$B$42,AD12>=Assumptions!$B$43),"Act now",IF(AN12>=Assumptions!$B$42,"Protect (structural)",IF(AD12>=Assumptions!$B$43,"Remediate supplier","Routine"))) -> Routine | AS12: =_xlfn.MAXIFS(Network!$T$5:$T$36,Network!$D$5:$D$36,$A12) -> 3 | AT12: =COUNT(K12:R12) -> 8 | AU12: =IF(AT12>=8,2,IF(AT12>=6,1,0)) -> 2 | AV12: =IF(OR(C12=1,LEFT(G12,9)="Confirmed"),1,0) -> 1 | AW12: =AS12+AU12+AV12 -> 6 | AX12: =IF(AW12>=Assumptions!$B$44,"High",IF(AW12>=Assumptions!$B$45,"Medium","Low")) -> High | AY12: =IF(OR(AQ12="Critical",AQ12="High"),IF(AX12="Low","VERIFY first – urgent sub-tier fact-find",IF(OR(AQ12="Critical",AV12=1),"ACT – mitigate now","CONFIRM sole-source status, then qualify alternate")),IF(AQ12="Elevated",IF(AX12="Low","VERIFY – add to N-tier survey","PLAN – qualify alternate in 90 days"),"MONITOR – quarterly review")) -> MONITOR – quarterly review | AZ12: =IF(K12&L12&O12<>"",IF(OR(K12="",L12="",O12=""),TRIM(IF(K12="","Current ratio; ","")&IF(L12="","Net debt/EBITDA; ","")&IF(O12="","Assurance gap","")),"—"),"Current ratio; Net debt/EBITDA; Assurance gap") -> —
A13: ORG-176 | B13: =INDEX(Data!$B$5:$B$34,MATCH($A13,Data!$A$5:$A$34,0)) -> HarborSense Electronics Ltd. | C13: 1 | D13: Tier-1: B10 battery board (20%) | E13: =INDEX(Data!$G$38:$G$67,MATCH($A13,Data!$A$38:$A$67,0)) -> SITE-067 | F13: =INDEX(Data!$I$38:$I$67,MATCH($A13,Data!$A$38:$A$67,0)) -> Z05 | G13: Minority (20%) | H13: 1 | I13: 12 | J13: Case: B10 qualification 12 wks | K13: =IF(INDEX(Data!$C$5:$C$34,MATCH($A13,Data!$A$5:$A$34,0))="","",INDEX(Data!$C$5:$C$34,MATCH($A13,Data!$A$5:$A$34,0))) -> 2.24 | L13: =IF(INDEX(Data!$D$5:$D$34,MATCH($A13,Data!$A$5:$A$34,0))="","",INDEX(Data!$D$5:$D$34,MATCH($A13,Data!$A$5:$A$34,0))) -> 2.33 | M13: =IF(INDEX(Data!$E$5:$E$34,MATCH($A13,Data!$A$5:$A$34,0))="","",INDEX(Data!$E$5:$E$34,MATCH($A13,Data!$A$5:$A$34,0))) -> 81.9 | N13: =IF(INDEX(Data!$F$5:$F$34,MATCH($A13,Data!$A$5:$A$34,0))="","",INDEX(Data!$F$5:$F$34,MATCH($A13,Data!$A$5:$A$34,0))) -> -0.9 | O13: =IF(INDEX(Data!$G$5:$G$34,MATCH($A13,Data!$A$5:$A$34,0))="","",INDEX(Data!$G$5:$G$34,MATCH($A13,Data!$A$5:$A$34,0))) -> 27 | P13: =IF(INDEX(Data!$H$5:$H$34,MATCH($A13,Data!$A$5:$A$34,0))="","",INDEX(Data!$H$5:$H$34,MATCH($A13,Data!$A$5:$A$34,0))) -> 31 | Q13: =IF(INDEX(Data!$I$5:$I$34,MATCH($A13,Data!$A$5:$A$34,0))="","",INDEX(Data!$I$5:$I$34,MATCH($A13,Data!$A$5:$A$34,0))) -> 23 | R13: =IF(INDEX(Data!$J$5:$J$34,MATCH($A13,Data!$A$5:$A$34,0))="","",INDEX(Data!$J$5:$J$34,MATCH($A13,Data!$A$5:$A$34,0))) -> 19 | S13: =IF(L13="","",IF(L13<=Assumptions!$B$31,Assumptions!$H$31,IF(L13<=Assumptions!$C$31,Assumptions!$H$31+(L13-Assumptions!$B$31)/(Assumptions!$C$31-Assumptions!$B$31)*(Assumptions!$I$31-Assumptions!$H$31),IF(L13<=Assumptions!$D$31,Assumptions!$I$31+(L13-Assumptions!$C$31)/(Assumptions!$D$31-Assumptions!$C$31)*(Assumptions!$J$31-Assumptions!$I$31),IF(L13<=Assumptions!$E$31,Assumptions!$J$31+(L13-Assumptions!$D$31)/(Assumptions!$E$31-Assumptions!$D$31)*(Assumptions!$K$31-Assumptions!$J$31),IF(L13<=Assumptions!$F$31,Assumptions!$K$31+(L13-Assumptions!$E$31)/(Assumptions!$F$31-Assumptions!$E$31)*(Assumptions!$L$31-Assumptions!$K$31),IF(L13<=Assumptions!$G$31,Assumptions!$L$31+(L13-Assumptions!$F$31)/(Assumptions!$G$31-Assumptions!$F$31)*(Assumptions!$M$31-Assumptions!$L$31),Assumptions!$M$31))))))) -> 27.96 | T13: =IF(K13="","",IF(K13<=Assumptions!$B$32,Assumptions!$H$32,IF(K13<=Assumptions!$C$32,Assumptions!$H$32+(K13-Assumptions!$B$32)/(Assumptions!$C$32-Assumptions!$B$32)*(Assumptions!$I$32-Assumptions!$H$32),IF(K13<=Assumptions!$D$32,Assumptions!$I$32+(K13-Assumptions!$C$32)/(Assumptions!$D$32-Assumptions!$C$32)*(Assumptions!$J$32-Assumptions!$I$32),IF(K13<=Assumptions!$E$32,Assumptions!$J$32+(K13-Assumptions!$D$32)/(Assumptions!$E$32-Assumptions!$D$32)*(Assumptions!$K$32-Assumptions!$J$32),IF(K13<=Assumptions!$F$32,Assumptions!$K$32+(K13-Assumptions!$E$32)/(Assumptions!$F$32-Assumptions!$E$32)*(Assumptions!$L$32-Assumptions!$K$32),IF(K13<=Assumptions!$G$32,Assumptions!$L$32+(K13-Assumptions!$F$32)/(Assumptions!$G$32-Assumptions!$F$32)*(Assumptions!$M$32-Assumptions!$L$32),Assumptions!$M$32))))))) -> 7.8 | U13: =IF(M13<=Assumptions!$B$33,Assumptions!$H$33,IF(M13<=Assumptions!$C$33,Assumptions!$H$33+(M13-Assumptions!$B$33)/(Assumptions!$C$33-Assumptions!$B$33)*(Assumptions!$I$33-Assumptions!$H$33),IF(M13<=Assumptions!$D$33,Assumptions!$I$33+(M13-Assumptions!$C$33)/(Assumptions!$D$33-Assumptions!$C$33)*(Assumptions!$J$33-Assumptions!$I$33),IF(M13<=Assumptions!$E$33,Assumptions!$J$33+(M13-Assumptions!$D$33)/(Assumptions!$E$33-Assumptions!$D$33)*(Assumptions!$K$33-Assumptions!$J$33),IF(M13<=Assumptions!$F$33,Assumptions!$K$33+(M13-Assumptions!$E$33)/(Assumptions!$F$33-Assumptions!$E$33)*(Assumptions!$L$33-Assumptions!$K$33),IF(M13<=Assumptions!$G$33,Assumptions!$L$33+(M13-Assumptions!$F$33)/(Assumptions!$G$33-Assumptions!$F$33)*(Assumptions!$M$33-Assumptions!$L$33),Assumptions!$M$33)))))) -> 65.5 | V13: =IF(N13<=Assumptions!$B$34,Assumptions!$H$34,IF(N13<=Assumptions!$C$34,Assumptions!$H$34+(N13-Assumptions!$B$34)/(Assumptions!$C$34-Assumptions!$B$34)*(Assumptions!$I$34-Assumptions!$H$34),IF(N13<=Assumptions!$D$34,Assumptions!$I$34+(N13-Assumptions!$C$34)/(Assumptions!$D$34-Assumptions!$C$34)*(Assumptions!$J$34-Assumptions!$I$34),IF(N13<=Assumptions!$E$34,Assumptions!$J$34+(N13-Assumptions!$D$34)/(Assumptions!$E$34-Assumptions!$D$34)*(Assumptions!$K$34-Assumptions!$J$34),IF(N13<=Assumptions!$F$34,Assumptions!$K$34+(N13-Assumptions!$E$34)/(Assumptions!$F$34-Assumptions!$E$34)*(Assumptions!$L$34-Assumptions!$K$34),IF(N13<=Assumptions!$G$34,Assumptions!$L$34+(N13-Assumptions!$F$34)/(Assumptions!$G$34-Assumptions!$F$34)*(Assumptions!$M$34-Assumptions!$L$34),Assumptions!$M$34)))))) -> 26.75 | W13: =IF(S13="",PERCENTILE($S$6:$S$30,Assumptions!$B$36),S13) -> 27.96 | X13: =IF(T13="",PERCENTILE($T$6:$T$30,Assumptions!$B$36),T13) -> 7.8 | Y13: =IF(O13="",PERCENTILE($O$6:$O$30,Assumptions!$B$36),O13) -> 27 | Z13: =W13*Assumptions!$B$16+X13*Assumptions!$B$17 -> 17.88 | AA13: =U13*Assumptions!$B$18+V13*Assumptions!$B$19 -> 46.125 | AB13: =AVERAGE(P13:R13) -> 24.333333 | AC13: 0 | AD13: =MIN(100,Z13*Assumptions!$B$11+AA13*Assumptions!$B$12+Y13*Assumptions!$B$13+AB13*Assumptions!$B$14+AC13*Assumptions!$B$20) -> 29.334833 | AE13: =MIN(1,SUMIFS(Network!$V$5:$V$14,Network!$D$5:$D$14,$A13,Network!$U$5:$U$14,1)) -> 0 | AF13: =MIN(1,SUMIFS(Network!$W$5:$W$14,Network!$D$5:$D$14,$A13,Network!$U$5:$U$14,1)) -> 0 | AG13: =MIN(1,SUMIFS(Network!$X$5:$X$14,Network!$D$5:$D$14,$A13,Network!$U$5:$U$14,1)) -> 0.2 | AH13: =AE13*Assumptions!$B$5+AF13*Assumptions!$B$6+AG13*Assumptions!$B$7 -> 83.2 | AI13: =AH13/Assumptions!$B$8 -> 0.053333333 | AJ13: =AH13/52 -> 1.6 | AK13: =AJ13*I13 -> 19.2 | AL13: =MIN(100,I13/Assumptions!$B$26*100) -> 33.333333 | AM13: =MIN(100,H13/Assumptions!$B$27*100) -> 33.333333 | AN13: =AI13*100*Assumptions!$B$23+AL13*Assumptions!$B$24+AM13*Assumptions!$B$25 -> 19.333333 | AO13: =AN13*AD13/100 -> 5.6714011 | AP13: =RANK(AO13,$AO$6:$AO$30)+COUNTIF($AO$6:AO13,AO13)-1 -> 25 | AQ13: =IF(AO13>=Assumptions!$B$39,"Critical",IF(AO13>=Assumptions!$B$40,"High",IF(AO13>=Assumptions!$B$41,"Elevated","Watch"))) -> Watch | AR13: =IF(AND(AN13>=Assumptions!$B$42,AD13>=Assumptions!$B$43),"Act now",IF(AN13>=Assumptions!$B$42,"Protect (structural)",IF(AD13>=Assumptions!$B$43,"Remediate supplier","Routine"))) -> Routine | AS13: =_xlfn.MAXIFS(Network!$T$5:$T$36,Network!$D$5:$D$36,$A13) -> 3 | AT13: =COUNT(K13:R13) -> 8 | AU13: =IF(AT13>=8,2,IF(AT13>=6,1,0)) -> 2 | AV13: =IF(OR(C13=1,LEFT(G13,9)="Confirmed"),1,0) -> 1 | AW13: =AS13+AU13+AV13 -> 6 | AX13: =IF(AW13>=Assumptions!$B$44,"High",IF(AW13>=Assumptions!$B$45,"Medium","Low")) -> High | AY13: =IF(OR(AQ13="Critical",AQ13="High"),IF(AX13="Low","VERIFY first – urgent sub-tier fact-find",IF(OR(AQ13="Critical",AV13=1),"ACT – mitigate now","CONFIRM sole-source status, then qualify alternate")),IF(AQ13="Elevated",IF(AX13="Low","VERIFY – add to N-tier survey","PLAN – qualify alternate in 90 days"),"MONITOR – quarterly review")) -> MONITOR – quarterly review | AZ13: =IF(K13&L13&O13<>"",IF(OR(K13="",L13="",O13=""),TRIM(IF(K13="","Current ratio; ","")&IF(L13="","Net debt/EBITDA; ","")&IF(O13="","Assurance gap","")),"—"),"Current ratio; Net debt/EBITDA; Assurance gap") -> —
A14: ORG-268 | B14: =INDEX(Data!$B$5:$B$34,MATCH($A14,Data!$A$5:$A$34,0)) -> CommonSpan Holdings Ltd. | C14: 1 | D14: GROUP NODE: CommonSpan = owner of Aster + Boreal (100% of M10/M20) | E14: SITE-018 + SITE-025 | F14: Z02/Z05 | G14: Confirmed – common owner (DOC-075) | H14: 2 | I14: 16 | J14: Replacing both assemblers = full new M10/M20 qualification (16 wks minimum). Scored on parent's own indicators. | K14: =IF(INDEX(Data!$C$5:$C$34,MATCH($A14,Data!$A$5:$A$34,0))="","",INDEX(Data!$C$5:$C$34,MATCH($A14,Data!$A$5:$A$34,0))) -> 2.04 | L14: =IF(INDEX(Data!$D$5:$D$34,MATCH($A14,Data!$A$5:$A$34,0))="","",INDEX(Data!$D$5:$D$34,MATCH($A14,Data!$A$5:$A$34,0))) -> 1 | M14: =IF(INDEX(Data!$E$5:$E$34,MATCH($A14,Data!$A$5:$A$34,0))="","",INDEX(Data!$E$5:$E$34,MATCH($A14,Data!$A$5:$A$34,0))) -> 87.6 | N14: =IF(INDEX(Data!$F$5:$F$34,MATCH($A14,Data!$A$5:$A$34,0))="","",INDEX(Data!$F$5:$F$34,MATCH($A14,Data!$A$5:$A$34,0))) -> -1.1 | O14: =IF(INDEX(Data!$G$5:$G$34,MATCH($A14,Data!$A$5:$A$34,0))="","",INDEX(Data!$G$5:$G$34,MATCH($A14,Data!$A$5:$A$34,0))) -> 45 | P14: =IF(INDEX(Data!$H$5:$H$34,MATCH($A14,Data!$A$5:$A$34,0))="","",INDEX(Data!$H$5:$H$34,MATCH($A14,Data!$A$5:$A$34,0))) -> 31 | Q14: =IF(INDEX(Data!$I$5:$I$34,MATCH($A14,Data!$A$5:$A$34,0))="","",INDEX(Data!$I$5:$I$34,MATCH($A14,Data!$A$5:$A$34,0))) -> 23 | R14: =IF(INDEX(Data!$J$5:$J$34,MATCH($A14,Data!$A$5:$A$34,0))="","",INDEX(Data!$J$5:$J$34,MATCH($A14,Data!$A$5:$A$34,0))) -> 19 | S14: =IF(L14="","",IF(L14<=Assumptions!$B$31,Assumptions!$H$31,IF(L14<=Assumptions!$C$31,Assumptions!$H$31+(L14-Assumptions!$B$31)/(Assumptions!$C$31-Assumptions!$B$31)*(Assumptions!$I$31-Assumptions!$H$31),IF(L14<=Assumptions!$D$31,Assumptions!$I$31+(L14-Assumptions!$C$31)/(Assumptions!$D$31-Assumptions!$C$31)*(Assumptions!$J$31-Assumptions!$I$31),IF(L14<=Assumptions!$E$31,Assumptions!$J$31+(L14-Assumptions!$D$31)/(Assumptions!$E$31-Assumptions!$D$31)*(Assumptions!$K$31-Assumptions!$J$31),IF(L14<=Assumptions!$F$31,Assumptions!$K$31+(L14-Assumptions!$E$31)/(Assumptions!$F$31-Assumptions!$E$31)*(Assumptions!$L$31-Assumptions!$K$31),IF(L14<=Assumptions!$G$31,Assumptions!$L$31+(L14-Assumptions!$F$31)/(Assumptions!$G$31-Assumptions!$F$31)*(Assumptions!$M$31-Assumptions!$L$31),Assumptions!$M$31))))))) -> 12 | T14: =IF(K14="","",IF(K14<=Assumptions!$B$32,Assumptions!$H$32,IF(K14<=Assumptions!$C$32,Assumptions!$H$32+(K14-Assumptions!$B$32)/(Assumptions!$C$32-Assumptions!$B$32)*(Assumptions!$I$32-Assumptions!$H$32),IF(K14<=Assumptions!$D$32,Assumptions!$I$32+(K14-Assumptions!$C$32)/(Assumptions!$D$32-Assumptions!$C$32)*(Assumptions!$J$32-Assumptions!$I$32),IF(K14<=Assumptions!$E$32,Assumptions!$J$32+(K14-Assumptions!$D$32)/(Assumptions!$E$32-Assumptions!$D$32)*(Assumptions!$K$32-Assumptions!$J$32),IF(K14<=Assumptions!$F$32,Assumptions!$K$32+(K14-Assumptions!$E$32)/(Assumptions!$F$32-Assumptions!$E$32)*(Assumptions!$L$32-Assumptions!$K$32),IF(K14<=Assumptions!$G$32,Assumptions!$L$32+(K14-Assumptions!$F$32)/(Assumptions!$G$32-Assumptions!$F$32)*(Assumptions!$M$32-Assumptions!$L$32),Assumptions!$M$32))))))) -> 13.8 | U14: =IF(M14<=Assumptions!$B$33,Assumptions!$H$33,IF(M14<=Assumptions!$C$33,Assumptions!$H$33+(M14-Assumptions!$B$33)/(Assumptions!$C$33-Assumptions!$B$33)*(Assumptions!$I$33-Assumptions!$H$33),IF(M14<=Assumptions!$D$33,Assumptions!$I$33+(M14-Assumptions!$C$33)/(Assumptions!$D$33-Assumptions!$C$33)*(Assumptions!$J$33-Assumptions!$I$33),IF(M14<=Assumptions!$E$33,Assumptions!$J$33+(M14-Assumptions!$D$33)/(Assumptions!$E$33-Assumptions!$D$33)*(Assumptions!$K$33-Assumptions!$J$33),IF(M14<=Assumptions!$F$33,Assumptions!$K$33+(M14-Assumptions!$E$33)/(Assumptions!$F$33-Assumptions!$E$33)*(Assumptions!$L$33-Assumptions!$K$33),IF(M14<=Assumptions!$G$33,Assumptions!$L$33+(M14-Assumptions!$F$33)/(Assumptions!$G$33-Assumptions!$F$33)*(Assumptions!$M$33-Assumptions!$L$33),Assumptions!$M$33)))))) -> 37 | V14: =IF(N14<=Assumptions!$B$34,Assumptions!$H$34,IF(N14<=Assumptions!$C$34,Assumptions!$H$34+(N14-Assumptions!$B$34)/(Assumptions!$C$34-Assumptions!$B$34)*(Assumptions!$I$34-Assumptions!$H$34),IF(N14<=Assumptions!$D$34,Assumptions!$I$34+(N14-Assumptions!$C$34)/(Assumptions!$D$34-Assumptions!$C$34)*(Assumptions!$J$34-Assumptions!$I$34),IF(N14<=Assumptions!$E$34,Assumptions!$J$34+(N14-Assumptions!$D$34)/(Assumptions!$E$34-Assumptions!$D$34)*(Assumptions!$K$34-Assumptions!$J$34),IF(N14<=Assumptions!$F$34,Assumptions!$K$34+(N14-Assumptions!$E$34)/(Assumptions!$F$34-Assumptions!$E$34)*(Assumptions!$L$34-Assumptions!$K$34),IF(N14<=Assumptions!$G$34,Assumptions!$L$34+(N14-Assumptions!$F$34)/(Assumptions!$G$34-Assumptions!$F$34)*(Assumptions!$M$34-Assumptions!$L$34),Assumptions!$M$34)))))) -> 28.25 | W14: =IF(S14="",PERCENTILE($S$6:$S$30,Assumptions!$B$36),S14) -> 12 | X14: =IF(T14="",PERCENTILE($T$6:$T$30,Assumptions!$B$36),T14) -> 13.8 | Y14: =IF(O14="",PERCENTILE($O$6:$O$30,Assumptions!$B$36),O14) -> 45 | Z14: =W14*Assumptions!$B$16+X14*Assumptions!$B$17 -> 12.9 | AA14: =U14*Assumptions!$B$18+V14*Assumptions!$B$19 -> 32.625 | AB14: =AVERAGE(P14:R14) -> 24.333333 | AC14: 0 | AD14: =MIN(100,Z14*Assumptions!$B$11+AA14*Assumptions!$B$12+Y14*Assumptions!$B$13+AB14*Assumptions!$B$14+AC14*Assumptions!$B$20) -> 26.490833 | AE14: =MIN(1,AE6+AE7) -> 1 | AF14: =MIN(1,AF6+AF7) -> 1 | AG14: =MIN(1,AG6+AG7) -> 1 | AH14: =AE14*Assumptions!$B$5+AF14*Assumptions!$B$6+AG14*Assumptions!$B$7 -> 1560 | AI14: =AH14/Assumptions!$B$8 -> 1 | AJ14: =AH14/52 -> 30 | AK14: =AJ14*I14 -> 480 | AL14: =MIN(100,I14/Assumptions!$B$26*100) -> 44.444444 | AM14: =MIN(100,H14/Assumptions!$B$27*100) -> 66.666667 | AN14: =AI14*100*Assumptions!$B$23+AL14*Assumptions!$B$24+AM14*Assumptions!$B$25 -> 76.666667 | AO14: =AN14*AD14/100 -> 20.309639 | AP14: =RANK(AO14,$AO$6:$AO$30)+COUNTIF($AO$6:AO14,AO14)-1 -> 15 | AQ14: =IF(AO14>=Assumptions!$B$39,"Critical",IF(AO14>=Assumptions!$B$40,"High",IF(AO14>=Assumptions!$B$41,"Elevated","Watch"))) -> Elevated | AR14: =IF(AND(AN14>=Assumptions!$B$42,AD14>=Assumptions!$B$43),"Act now",IF(AN14>=Assumptions!$B$42,"Protect (structural)",IF(AD14>=Assumptions!$B$43,"Remediate supplier","Routine"))) -> Protect (structural) | AS14: 3 | AT14: =COUNT(K14:R14) -> 8 | AU14: =IF(AT14>=8,2,IF(AT14>=6,1,0)) -> 2 | AV14: =IF(OR(C14=1,LEFT(G14,9)="Confirmed"),1,0) -> 1 | AW14: =AS14+AU14+AV14 -> 6 | AX14: =IF(AW14>=Assumptions!$B$44,"High",IF(AW14>=Assumptions!$B$45,"Medium","Low")) -> High | AY14: =IF(OR(AQ14="Critical",AQ14="High"),IF(AX14="Low","VERIFY first – urgent sub-tier fact-find",IF(OR(AQ14="Critical",AV14=1),"ACT – mitigate now","CONFIRM sole-source status, then qualify alternate")),IF(AQ14="Elevated",IF(AX14="Low","VERIFY – add to N-tier survey","PLAN – qualify alternate in 90 days"),"MONITOR – quarterly review")) -> PLAN – qualify alternate in 90 days | AZ14: =IF(K14&L14&O14<>"",IF(OR(K14="",L14="",O14=""),TRIM(IF(K14="","Current ratio; ","")&IF(L14="","Net debt/EBITDA; ","")&IF(O14="","Assurance gap","")),"—"),"Current ratio; Net debt/EBITDA; Assurance gap") -> —
A15: ORG-439 | B15: =INDEX(Data!$B$5:$B$34,MATCH($A15,Data!$A$5:$A$34,0)) -> IonPeak Semiconductor Ltd. | C15: 2 | D15: Tier-2: power dies → Aster & Boreal | E15: =INDEX(Data!$G$38:$G$67,MATCH($A15,Data!$A$38:$A$67,0)) -> SITE-074 | F15: =INDEX(Data!$I$38:$I$67,MATCH($A15,Data!$A$38:$A$67,0)) -> Z01 | G15: Confirmed sole (DOC-078) | H15: 2 | I15: 36 | J15: No second die qualified (DOC-078). Alternate die/module requal 26-52 wks (team research) – mid-point | K15: =IF(INDEX(Data!$C$5:$C$34,MATCH($A15,Data!$A$5:$A$34,0))="","",INDEX(Data!$C$5:$C$34,MATCH($A15,Data!$A$5:$A$34,0))) -> 1.8 | L15: =IF(INDEX(Data!$D$5:$D$34,MATCH($A15,Data!$A$5:$A$34,0))="","",INDEX(Data!$D$5:$D$34,MATCH($A15,Data!$A$5:$A$34,0))) -> 2.4 | M15: =IF(INDEX(Data!$E$5:$E$34,MATCH($A15,Data!$A$5:$A$34,0))="","",INDEX(Data!$E$5:$E$34,MATCH($A15,Data!$A$5:$A$34,0))) -> 85.2 | N15: =IF(INDEX(Data!$F$5:$F$34,MATCH($A15,Data!$A$5:$A$34,0))="","",INDEX(Data!$F$5:$F$34,MATCH($A15,Data!$A$5:$A$34,0))) -> -8.8 | O15: =IF(INDEX(Data!$G$5:$G$34,MATCH($A15,Data!$A$5:$A$34,0))="","",INDEX(Data!$G$5:$G$34,MATCH($A15,Data!$A$5:$A$34,0))) -> 36 | P15: =IF(INDEX(Data!$H$5:$H$34,MATCH($A15,Data!$A$5:$A$34,0))="","",INDEX(Data!$H$5:$H$34,MATCH($A15,Data!$A$5:$A$34,0))) -> 82 | Q15: =IF(INDEX(Data!$I$5:$I$34,MATCH($A15,Data!$A$5:$A$34,0))="","",INDEX(Data!$I$5:$I$34,MATCH($A15,Data!$A$5:$A$34,0))) -> 76 | R15: =IF(INDEX(Data!$J$5:$J$34,MATCH($A15,Data!$A$5:$A$34,0))="","",INDEX(Data!$J$5:$J$34,MATCH($A15,Data!$A$5:$A$34,0))) -> 71 | S15: =IF(L15="","",IF(L15<=Assumptions!$B$31,Assumptions!$H$31,IF(L15<=Assumptions!$C$31,Assumptions!$H$31+(L15-Assumptions!$B$31)/(Assumptions!$C$31-Assumptions!$B$31)*(Assumptions!$I$31-Assumptions!$H$31),IF(L15<=Assumptions!$D$31,Assumptions!$I$31+(L15-Assumptions!$C$31)/(Assumptions!$D$31-Assumptions!$C$31)*(Assumptions!$J$31-Assumptions!$I$31),IF(L15<=Assumptions!$E$31,Assumptions!$J$31+(L15-Assumptions!$D$31)/(Assumptions!$E$31-Assumptions!$D$31)*(Assumptions!$K$31-Assumptions!$J$31),IF(L15<=Assumptions!$F$31,Assumptions!$K$31+(L15-Assumptions!$E$31)/(Assumptions!$F$31-Assumptions!$E$31)*(Assumptions!$L$31-Assumptions!$K$31),IF(L15<=Assumptions!$G$31,Assumptions!$L$31+(L15-Assumptions!$F$31)/(Assumptions!$G$31-Assumptions!$F$31)*(Assumptions!$M$31-Assumptions!$L$31),Assumptions!$M$31))))))) -> 28.8 | T15: =IF(K15="","",IF(K15<=Assumptions!$B$32,Assumptions!$H$32,IF(K15<=Assumptions!$C$32,Assumptions!$H$32+(K15-Assumptions!$B$32)/(Assumptions!$C$32-Assumptions!$B$32)*(Assumptions!$I$32-Assumptions!$H$32),IF(K15<=Assumptions!$D$32,Assumptions!$I$32+(K15-Assumptions!$C$32)/(Assumptions!$D$32-Assumptions!$C$32)*(Assumptions!$J$32-Assumptions!$I$32),IF(K15<=Assumptions!$E$32,Assumptions!$J$32+(K15-Assumptions!$D$32)/(Assumptions!$E$32-Assumptions!$D$32)*(Assumptions!$K$32-Assumptions!$J$32),IF(K15<=Assumptions!$F$32,Assumptions!$K$32+(K15-Assumptions!$E$32)/(Assumptions!$F$32-Assumptions!$E$32)*(Assumptions!$L$32-Assumptions!$K$32),IF(K15<=Assumptions!$G$32,Assumptions!$L$32+(K15-Assumptions!$F$32)/(Assumptions!$G$32-Assumptions!$F$32)*(Assumptions!$M$32-Assumptions!$L$32),Assumptions!$M$32))))))) -> 21 | U15: =IF(M15<=Assumptions!$B$33,Assumptions!$H$33,IF(M15<=Assumptions!$C$33,Assumptions!$H$33+(M15-Assumptions!$B$33)/(Assumptions!$C$33-Assumptions!$B$33)*(Assumptions!$I$33-Assumptions!$H$33),IF(M15<=Assumptions!$D$33,Assumptions!$I$33+(M15-Assumptions!$C$33)/(Assumptions!$D$33-Assumptions!$C$33)*(Assumptions!$J$33-Assumptions!$I$33),IF(M15<=Assumptions!$E$33,Assumptions!$J$33+(M15-Assumptions!$D$33)/(Assumptions!$E$33-Assumptions!$D$33)*(Assumptions!$K$33-Assumptions!$J$33),IF(M15<=Assumptions!$F$33,Assumptions!$K$33+(M15-Assumptions!$E$33)/(Assumptions!$F$33-Assumptions!$E$33)*(Assumptions!$L$33-Assumptions!$K$33),IF(M15<=Assumptions!$G$33,Assumptions!$L$33+(M15-Assumptions!$F$33)/(Assumptions!$G$33-Assumptions!$F$33)*(Assumptions!$M$33-Assumptions!$L$33),Assumptions!$M$33)))))) -> 49 | V15: =IF(N15<=Assumptions!$B$34,Assumptions!$H$34,IF(N15<=Assumptions!$C$34,Assumptions!$H$34+(N15-Assumptions!$B$34)/(Assumptions!$C$34-Assumptions!$B$34)*(Assumptions!$I$34-Assumptions!$H$34),IF(N15<=Assumptions!$D$34,Assumptions!$I$34+(N15-Assumptions!$C$34)/(Assumptions!$D$34-Assumptions!$C$34)*(Assumptions!$J$34-Assumptions!$I$34),IF(N15<=Assumptions!$E$34,Assumptions!$J$34+(N15-Assumptions!$D$34)/(Assumptions!$E$34-Assumptions!$D$34)*(Assumptions!$K$34-Assumptions!$J$34),IF(N15<=Assumptions!$F$34,Assumptions!$K$34+(N15-Assumptions!$E$34)/(Assumptions!$F$34-Assumptions!$E$34)*(Assumptions!$L$34-Assumptions!$K$34),IF(N15<=Assumptions!$G$34,Assumptions!$L$34+(N15-Assumptions!$F$34)/(Assumptions!$G$34-Assumptions!$F$34)*(Assumptions!$M$34-Assumptions!$L$34),Assumptions!$M$34)))))) -> 74 | W15: =IF(S15="",PERCENTILE($S$6:$S$30,Assumptions!$B$36),S15) -> 28.8 | X15: =IF(T15="",PERCENTILE($T$6:$T$30,Assumptions!$B$36),T15) -> 21 | Y15: =IF(O15="",PERCENTILE($O$6:$O$30,Assumptions!$B$36),O15) -> 36 | Z15: =W15*Assumptions!$B$16+X15*Assumptions!$B$17 -> 24.9 | AA15: =U15*Assumptions!$B$18+V15*Assumptions!$B$19 -> 61.5 | AB15: =AVERAGE(P15:R15) -> 76.333333 | AC15: 0 | AD15: =MIN(100,Z15*Assumptions!$B$11+AA15*Assumptions!$B$12+Y15*Assumptions!$B$13+AB15*Assumptions!$B$14+AC15*Assumptions!$B$20) -> 50.403333 | AE15: =MIN(1,SUMIFS(Network!$V$15:$V$30,Network!$D$15:$D$30,$A15,Network!$U$15:$U$30,1)) -> 1 | AF15: =MIN(1,SUMIFS(Network!$W$15:$W$30,Network!$D$15:$D$30,$A15,Network!$U$15:$U$30,1)) -> 1 | AG15: =MIN(1,SUMIFS(Network!$X$15:$X$30,Network!$D$15:$D$30,$A15,Network!$U$15:$U$30,1)) -> 1 | AH15: =AE15*Assumptions!$B$5+AF15*Assumptions!$B$6+AG15*Assumptions!$B$7 -> 1560 | AI15: =AH15/Assumptions!$B$8 -> 1 | AJ15: =AH15/52 -> 30 | AK15: =AJ15*I15 -> 1080 | AL15: =MIN(100,I15/Assumptions!$B$26*100) -> 100 | AM15: =MIN(100,H15/Assumptions!$B$27*100) -> 66.666667 | AN15: =AI15*100*Assumptions!$B$23+AL15*Assumptions!$B$24+AM15*Assumptions!$B$25 -> 93.333333 | AO15: =AN15*AD15/100 -> 47.043111 | AP15: =RANK(AO15,$AO$6:$AO$30)+COUNTIF($AO$6:AO15,AO15)-1 -> 2 | AQ15: =IF(AO15>=Assumptions!$B$39,"Critical",IF(AO15>=Assumptions!$B$40,"High",IF(AO15>=Assumptions!$B$41,"Elevated","Watch"))) -> Critical | AR15: =IF(AND(AN15>=Assumptions!$B$42,AD15>=Assumptions!$B$43),"Act now",IF(AN15>=Assumptions!$B$42,"Protect (structural)",IF(AD15>=Assumptions!$B$43,"Remediate supplier","Routine"))) -> Act now | AS15: =_xlfn.MAXIFS(Network!$T$5:$T$36,Network!$D$5:$D$36,$A15) -> 3 | AT15: =COUNT(K15:R15) -> 8 | AU15: =IF(AT15>=8,2,IF(AT15>=6,1,0)) -> 2 | AV15: =IF(OR(C15=1,LEFT(G15,9)="Confirmed"),1,0) -> 1 | AW15: =AS15+AU15+AV15 -> 6 | AX15: =IF(AW15>=Assumptions!$B$44,"High",IF(AW15>=Assumptions!$B$45,"Medium","Low")) -> High | AY15: =IF(OR(AQ15="Critical",AQ15="High"),IF(AX15="Low","VERIFY first – urgent sub-tier fact-find",IF(OR(AQ15="Critical",AV15=1),"ACT – mitigate now","CONFIRM sole-source status, then qualify alternate")),IF(AQ15="Elevated",IF(AX15="Low","VERIFY – add to N-tier survey","PLAN – qualify alternate in 90 days"),"MONITOR – quarterly review")) -> ACT – mitigate now | AZ15: =IF(K15&L15&O15<>"",IF(OR(K15="",L15="",O15=""),TRIM(IF(K15="","Current ratio; ","")&IF(L15="","Net debt/EBITDA; ","")&IF(O15="","Assurance gap","")),"—"),"Current ratio; Net debt/EBITDA; Assurance gap") -> —
A16: ORG-453 | B16: =INDEX(Data!$B$5:$B$34,MATCH($A16,Data!$A$5:$A$34,0)) -> Jade Printed Circuits Ltd. | C16: 2 | D16: Tier-2: PCB substrates → Cobalt, Grove, HarborSense | E16: =INDEX(Data!$G$38:$G$67,MATCH($A16,Data!$A$38:$A$67,0)) -> SITE-081 | F16: =INDEX(Data!$I$38:$I$67,MATCH($A16,Data!$A$38:$A$67,0)) -> Z01 | G16: Confirmed sole (DOC-079) | H16: 3 | I16: 12 | J16: Assumption: requalifying a PCB fab ≈ board qualification (12 wks) | K16: =IF(INDEX(Data!$C$5:$C$34,MATCH($A16,Data!$A$5:$A$34,0))="","",INDEX(Data!$C$5:$C$34,MATCH($A16,Data!$A$5:$A$34,0))) -> 1.55 | L16: =IF(INDEX(Data!$D$5:$D$34,MATCH($A16,Data!$A$5:$A$34,0))="","",INDEX(Data!$D$5:$D$34,MATCH($A16,Data!$A$5:$A$34,0))) -> 3.1 | M16: =IF(INDEX(Data!$E$5:$E$34,MATCH($A16,Data!$A$5:$A$34,0))="","",INDEX(Data!$E$5:$E$34,MATCH($A16,Data!$A$5:$A$34,0))) -> 86.6 | N16: =IF(INDEX(Data!$F$5:$F$34,MATCH($A16,Data!$A$5:$A$34,0))="","",INDEX(Data!$F$5:$F$34,MATCH($A16,Data!$A$5:$A$34,0))) -> -6.4 | O16: =IF(INDEX(Data!$G$5:$G$34,MATCH($A16,Data!$A$5:$A$34,0))="","",INDEX(Data!$G$5:$G$34,MATCH($A16,Data!$A$5:$A$34,0))) -> 45 | P16: =IF(INDEX(Data!$H$5:$H$34,MATCH($A16,Data!$A$5:$A$34,0))="","",INDEX(Data!$H$5:$H$34,MATCH($A16,Data!$A$5:$A$34,0))) -> 82 | Q16: =IF(INDEX(Data!$I$5:$I$34,MATCH($A16,Data!$A$5:$A$34,0))="","",INDEX(Data!$I$5:$I$34,MATCH($A16,Data!$A$5:$A$34,0))) -> 76 | R16: =IF(INDEX(Data!$J$5:$J$34,MATCH($A16,Data!$A$5:$A$34,0))="","",INDEX(Data!$J$5:$J$34,MATCH($A16,Data!$A$5:$A$34,0))) -> 71 | S16: =IF(L16="","",IF(L16<=Assumptions!$B$31,Assumptions!$H$31,IF(L16<=Assumptions!$C$31,Assumptions!$H$31+(L16-Assumptions!$B$31)/(Assumptions!$C$31-Assumptions!$B$31)*(Assumptions!$I$31-Assumptions!$H$31),IF(L16<=Assumptions!$D$31,Assumptions!$I$31+(L16-Assumptions!$C$31)/(Assumptions!$D$31-Assumptions!$C$31)*(Assumptions!$J$31-Assumptions!$I$31),IF(L16<=Assumptions!$E$31,Assumptions!$J$31+(L16-Assumptions!$D$31)/(Assumptions!$E$31-Assumptions!$D$31)*(Assumptions!$K$31-Assumptions!$J$31),IF(L16<=Assumptions!$F$31,Assumptions!$K$31+(L16-Assumptions!$E$31)/(Assumptions!$F$31-Assumptions!$E$31)*(Assumptions!$L$31-Assumptions!$K$31),IF(L16<=Assumptions!$G$31,Assumptions!$L$31+(L16-Assumptions!$F$31)/(Assumptions!$G$31-Assumptions!$F$31)*(Assumptions!$M$31-Assumptions!$L$31),Assumptions!$M$31))))))) -> 46 | T16: =IF(K16="","",IF(K16<=Assumptions!$B$32,Assumptions!$H$32,IF(K16<=Assumptions!$C$32,Assumptions!$H$32+(K16-Assumptions!$B$32)/(Assumptions!$C$32-Assumptions!$B$32)*(Assumptions!$I$32-Assumptions!$H$32),IF(K16<=Assumptions!$D$32,Assumptions!$I$32+(K16-Assumptions!$C$32)/(Assumptions!$D$32-Assumptions!$C$32)*(Assumptions!$J$32-Assumptions!$I$32),IF(K16<=Assumptions!$E$32,Assumptions!$J$32+(K16-Assumptions!$D$32)/(Assumptions!$E$32-Assumptions!$D$32)*(Assumptions!$K$32-Assumptions!$J$32),IF(K16<=Assumptions!$F$32,Assumptions!$K$32+(K16-Assumptions!$E$32)/(Assumptions!$F$32-Assumptions!$E$32)*(Assumptions!$L$32-Assumptions!$K$32),IF(K16<=Assumptions!$G$32,Assumptions!$L$32+(K16-Assumptions!$F$32)/(Assumptions!$G$32-Assumptions!$F$32)*(Assumptions!$M$32-Assumptions!$L$32),Assumptions!$M$32))))))) -> 28.5 | U16: =IF(M16<=Assumptions!$B$33,Assumptions!$H$33,IF(M16<=Assumptions!$C$33,Assumptions!$H$33+(M16-Assumptions!$B$33)/(Assumptions!$C$33-Assumptions!$B$33)*(Assumptions!$I$33-Assumptions!$H$33),IF(M16<=Assumptions!$D$33,Assumptions!$I$33+(M16-Assumptions!$C$33)/(Assumptions!$D$33-Assumptions!$C$33)*(Assumptions!$J$33-Assumptions!$I$33),IF(M16<=Assumptions!$E$33,Assumptions!$J$33+(M16-Assumptions!$D$33)/(Assumptions!$E$33-Assumptions!$D$33)*(Assumptions!$K$33-Assumptions!$J$33),IF(M16<=Assumptions!$F$33,Assumptions!$K$33+(M16-Assumptions!$E$33)/(Assumptions!$F$33-Assumptions!$E$33)*(Assumptions!$L$33-Assumptions!$K$33),IF(M16<=Assumptions!$G$33,Assumptions!$L$33+(M16-Assumptions!$F$33)/(Assumptions!$G$33-Assumptions!$F$33)*(Assumptions!$M$33-Assumptions!$L$33),Assumptions!$M$33)))))) -> 42 | V16: =IF(N16<=Assumptions!$B$34,Assumptions!$H$34,IF(N16<=Assumptions!$C$34,Assumptions!$H$34+(N16-Assumptions!$B$34)/(Assumptions!$C$34-Assumptions!$B$34)*(Assumptions!$I$34-Assumptions!$H$34),IF(N16<=Assumptions!$D$34,Assumptions!$I$34+(N16-Assumptions!$C$34)/(Assumptions!$D$34-Assumptions!$C$34)*(Assumptions!$J$34-Assumptions!$I$34),IF(N16<=Assumptions!$E$34,Assumptions!$J$34+(N16-Assumptions!$D$34)/(Assumptions!$E$34-Assumptions!$D$34)*(Assumptions!$K$34-Assumptions!$J$34),IF(N16<=Assumptions!$F$34,Assumptions!$K$34+(N16-Assumptions!$E$34)/(Assumptions!$F$34-Assumptions!$E$34)*(Assumptions!$L$34-Assumptions!$K$34),IF(N16<=Assumptions!$G$34,Assumptions!$L$34+(N16-Assumptions!$F$34)/(Assumptions!$G$34-Assumptions!$F$34)*(Assumptions!$M$34-Assumptions!$L$34),Assumptions!$M$34)))))) -> 62 | W16: =IF(S16="",PERCENTILE($S$6:$S$30,Assumptions!$B$36),S16) -> 46 | X16: =IF(T16="",PERCENTILE($T$6:$T$30,Assumptions!$B$36),T16) -> 28.5 | Y16: =IF(O16="",PERCENTILE($O$6:$O$30,Assumptions!$B$36),O16) -> 45 | Z16: =W16*Assumptions!$B$16+X16*Assumptions!$B$17 -> 37.25 | AA16: =U16*Assumptions!$B$18+V16*Assumptions!$B$19 -> 52 | AB16: =AVERAGE(P16:R16) -> 76.333333 | AC16: 0 | AD16: =MIN(100,Z16*Assumptions!$B$11+AA16*Assumptions!$B$12+Y16*Assumptions!$B$13+AB16*Assumptions!$B$14+AC16*Assumptions!$B$20) -> 52.608333 | AE16: =MIN(1,SUMIFS(Network!$V$15:$V$30,Network!$D$15:$D$30,$A16,Network!$U$15:$U$30,1)) -> 1 | AF16: =MIN(1,SUMIFS(Network!$W$15:$W$30,Network!$D$15:$D$30,$A16,Network!$U$15:$U$30,1)) -> 1 | AG16: =MIN(1,SUMIFS(Network!$X$15:$X$30,Network!$D$15:$D$30,$A16,Network!$U$15:$U$30,1)) -> 1 | AH16: =AE16*Assumptions!$B$5+AF16*Assumptions!$B$6+AG16*Assumptions!$B$7 -> 1560 | AI16: =AH16/Assumptions!$B$8 -> 1 | AJ16: =AH16/52 -> 30 | AK16: =AJ16*I16 -> 360 | AL16: =MIN(100,I16/Assumptions!$B$26*100) -> 33.333333 | AM16: =MIN(100,H16/Assumptions!$B$27*100) -> 100 | AN16: =AI16*100*Assumptions!$B$23+AL16*Assumptions!$B$24+AM16*Assumptions!$B$25 -> 80 | AO16: =AN16*AD16/100 -> 42.086667 | AP16: =RANK(AO16,$AO$6:$AO$30)+COUNTIF($AO$6:AO16,AO16)-1 -> 4 | AQ16: =IF(AO16>=Assumptions!$B$39,"Critical",IF(AO16>=Assumptions!$B$40,"High",IF(AO16>=Assumptions!$B$41,"Elevated","Watch"))) -> High | AR16: =IF(AND(AN16>=Assumptions!$B$42,AD16>=Assumptions!$B$43),"Act now",IF(AN16>=Assumptions!$B$42,"Protect (structural)",IF(AD16>=Assumptions!$B$43,"Remediate supplier","Routine"))) -> Act now | AS16: =_xlfn.MAXIFS(Network!$T$5:$T$36,Network!$D$5:$D$36,$A16) -> 3 | AT16: =COUNT(K16:R16) -> 8 | AU16: =IF(AT16>=8,2,IF(AT16>=6,1,0)) -> 2 | AV16: =IF(OR(C16=1,LEFT(G16,9)="Confirmed"),1,0) -> 1 | AW16: =AS16+AU16+AV16 -> 6 | AX16: =IF(AW16>=Assumptions!$B$44,"High",IF(AW16>=Assumptions!$B$45,"Medium","Low")) -> High | AY16: =IF(OR(AQ16="Critical",AQ16="High"),IF(AX16="Low","VERIFY first – urgent sub-tier fact-find",IF(OR(AQ16="Critical",AV16=1),"ACT – mitigate now","CONFIRM sole-source status, then qualify alternate")),IF(AQ16="Elevated",IF(AX16="Low","VERIFY – add to N-tier survey","PLAN – qualify alternate in 90 days"),"MONITOR – quarterly review")) -> ACT – mitigate now | AZ16: =IF(K16&L16&O16<>"",IF(OR(K16="",L16="",O16=""),TRIM(IF(K16="","Current ratio; ","")&IF(L16="","Net debt/EBITDA; ","")&IF(O16="","Assurance gap","")),"—"),"Current ratio; Net debt/EBITDA; Assurance gap") -> —
A17: ORG-728 | B17: =INDEX(Data!$B$5:$B$34,MATCH($A17,Data!$A$5:$A$34,0)) -> Kestrel Microdevices Ltd. | C17: 2 | D17: Tier-2: MCUs → Cobalt, Grove | E17: =INDEX(Data!$G$38:$G$67,MATCH($A17,Data!$A$38:$A$67,0)) -> SITE-088 | F17: =INDEX(Data!$I$38:$I$67,MATCH($A17,Data!$A$38:$A$67,0)) -> Z05 | G17: Presumed sole – not disclosed | H17: 2 | I17: 26 | J17: Assumption: MCU change = firmware port + revalidation (~6 months) | K17: =IF(INDEX(Data!$C$5:$C$34,MATCH($A17,Data!$A$5:$A$34,0))="","",INDEX(Data!$C$5:$C$34,MATCH($A17,Data!$A$5:$A$34,0))) -> 1.86 | L17: =IF(INDEX(Data!$D$5:$D$34,MATCH($A17,Data!$A$5:$A$34,0))="","",INDEX(Data!$D$5:$D$34,MATCH($A17,Data!$A$5:$A$34,0))) -> 2 | M17: =IF(INDEX(Data!$E$5:$E$34,MATCH($A17,Data!$A$5:$A$34,0))="","",INDEX(Data!$E$5:$E$34,MATCH($A17,Data!$A$5:$A$34,0))) -> 87.3 | N17: =IF(INDEX(Data!$F$5:$F$34,MATCH($A17,Data!$A$5:$A$34,0))="","",INDEX(Data!$F$5:$F$34,MATCH($A17,Data!$A$5:$A$34,0))) -> 1.6 | O17: =IF(INDEX(Data!$G$5:$G$34,MATCH($A17,Data!$A$5:$A$34,0))="","",INDEX(Data!$G$5:$G$34,MATCH($A17,Data!$A$5:$A$34,0))) -> 54 | P17: =IF(INDEX(Data!$H$5:$H$34,MATCH($A17,Data!$A$5:$A$34,0))="","",INDEX(Data!$H$5:$H$34,MATCH($A17,Data!$A$5:$A$34,0))) -> 31 | Q17: =IF(INDEX(Data!$I$5:$I$34,MATCH($A17,Data!$A$5:$A$34,0))="","",INDEX(Data!$I$5:$I$34,MATCH($A17,Data!$A$5:$A$34,0))) -> 23 | R17: =IF(INDEX(Data!$J$5:$J$34,MATCH($A17,Data!$A$5:$A$34,0))="","",INDEX(Data!$J$5:$J$34,MATCH($A17,Data!$A$5:$A$34,0))) -> 19 | S17: =IF(L17="","",IF(L17<=Assumptions!$B$31,Assumptions!$H$31,IF(L17<=Assumptions!$C$31,Assumptions!$H$31+(L17-Assumptions!$B$31)/(Assumptions!$C$31-Assumptions!$B$31)*(Assumptions!$I$31-Assumptions!$H$31),IF(L17<=Assumptions!$D$31,Assumptions!$I$31+(L17-Assumptions!$C$31)/(Assumptions!$D$31-Assumptions!$C$31)*(Assumptions!$J$31-Assumptions!$I$31),IF(L17<=Assumptions!$E$31,Assumptions!$J$31+(L17-Assumptions!$D$31)/(Assumptions!$E$31-Assumptions!$D$31)*(Assumptions!$K$31-Assumptions!$J$31),IF(L17<=Assumptions!$F$31,Assumptions!$K$31+(L17-Assumptions!$E$31)/(Assumptions!$F$31-Assumptions!$E$31)*(Assumptions!$L$31-Assumptions!$K$31),IF(L17<=Assumptions!$G$31,Assumptions!$L$31+(L17-Assumptions!$F$31)/(Assumptions!$G$31-Assumptions!$F$31)*(Assumptions!$M$31-Assumptions!$L$31),Assumptions!$M$31))))))) -> 24 | T17: =IF(K17="","",IF(K17<=Assumptions!$B$32,Assumptions!$H$32,IF(K17<=Assumptions!$C$32,Assumptions!$H$32+(K17-Assumptions!$B$32)/(Assumptions!$C$32-Assumptions!$B$32)*(Assumptions!$I$32-Assumptions!$H$32),IF(K17<=Assumptions!$D$32,Assumptions!$I$32+(K17-Assumptions!$C$32)/(Assumptions!$D$32-Assumptions!$C$32)*(Assumptions!$J$32-Assumptions!$I$32),IF(K17<=Assumptions!$E$32,Assumptions!$J$32+(K17-Assumptions!$D$32)/(Assumptions!$E$32-Assumptions!$D$32)*(Assumptions!$K$32-Assumptions!$J$32),IF(K17<=Assumptions!$F$32,Assumptions!$K$32+(K17-Assumptions!$E$32)/(Assumptions!$F$32-Assumptions!$E$32)*(Assumptions!$L$32-Assumptions!$K$32),IF(K17<=Assumptions!$G$32,Assumptions!$L$32+(K17-Assumptions!$F$32)/(Assumptions!$G$32-Assumptions!$F$32)*(Assumptions!$M$32-Assumptions!$L$32),Assumptions!$M$32))))))) -> 19.2 | U17: =IF(M17<=Assumptions!$B$33,Assumptions!$H$33,IF(M17<=Assumptions!$C$33,Assumptions!$H$33+(M17-Assumptions!$B$33)/(Assumptions!$C$33-Assumptions!$B$33)*(Assumptions!$I$33-Assumptions!$H$33),IF(M17<=Assumptions!$D$33,Assumptions!$I$33+(M17-Assumptions!$C$33)/(Assumptions!$D$33-Assumptions!$C$33)*(Assumptions!$J$33-Assumptions!$I$33),IF(M17<=Assumptions!$E$33,Assumptions!$J$33+(M17-Assumptions!$D$33)/(Assumptions!$E$33-Assumptions!$D$33)*(Assumptions!$K$33-Assumptions!$J$33),IF(M17<=Assumptions!$F$33,Assumptions!$K$33+(M17-Assumptions!$E$33)/(Assumptions!$F$33-Assumptions!$E$33)*(Assumptions!$L$33-Assumptions!$K$33),IF(M17<=Assumptions!$G$33,Assumptions!$L$33+(M17-Assumptions!$F$33)/(Assumptions!$G$33-Assumptions!$F$33)*(Assumptions!$M$33-Assumptions!$L$33),Assumptions!$M$33)))))) -> 38.5 | V17: =IF(N17<=Assumptions!$B$34,Assumptions!$H$34,IF(N17<=Assumptions!$C$34,Assumptions!$H$34+(N17-Assumptions!$B$34)/(Assumptions!$C$34-Assumptions!$B$34)*(Assumptions!$I$34-Assumptions!$H$34),IF(N17<=Assumptions!$D$34,Assumptions!$I$34+(N17-Assumptions!$C$34)/(Assumptions!$D$34-Assumptions!$C$34)*(Assumptions!$J$34-Assumptions!$I$34),IF(N17<=Assumptions!$E$34,Assumptions!$J$34+(N17-Assumptions!$D$34)/(Assumptions!$E$34-Assumptions!$D$34)*(Assumptions!$K$34-Assumptions!$J$34),IF(N17<=Assumptions!$F$34,Assumptions!$K$34+(N17-Assumptions!$E$34)/(Assumptions!$F$34-Assumptions!$E$34)*(Assumptions!$L$34-Assumptions!$K$34),IF(N17<=Assumptions!$G$34,Assumptions!$L$34+(N17-Assumptions!$F$34)/(Assumptions!$G$34-Assumptions!$F$34)*(Assumptions!$M$34-Assumptions!$L$34),Assumptions!$M$34)))))) -> 4 | W17: =IF(S17="",PERCENTILE($S$6:$S$30,Assumptions!$B$36),S17) -> 24 | X17: =IF(T17="",PERCENTILE($T$6:$T$30,Assumptions!$B$36),T17) -> 19.2 | Y17: =IF(O17="",PERCENTILE($O$6:$O$30,Assumptions!$B$36),O17) -> 54 | Z17: =W17*Assumptions!$B$16+X17*Assumptions!$B$17 -> 21.6 | AA17: =U17*Assumptions!$B$18+V17*Assumptions!$B$19 -> 21.25 | AB17: =AVERAGE(P17:R17) -> 24.333333 | AC17: 0 | AD17: =MIN(100,Z17*Assumptions!$B$11+AA17*Assumptions!$B$12+Y17*Assumptions!$B$13+AB17*Assumptions!$B$14+AC17*Assumptions!$B$20) -> 27.038333 | AE17: =MIN(1,SUMIFS(Network!$V$15:$V$30,Network!$D$15:$D$30,$A17,Network!$U$15:$U$30,1)) -> 1 | AF17: =MIN(1,SUMIFS(Network!$W$15:$W$30,Network!$D$15:$D$30,$A17,Network!$U$15:$U$30,1)) -> 1 | AG17: =MIN(1,SUMIFS(Network!$X$15:$X$30,Network!$D$15:$D$30,$A17,Network!$U$15:$U$30,1)) -> 1 | AH17: =AE17*Assumptions!$B$5+AF17*Assumptions!$B$6+AG17*Assumptions!$B$7 -> 1560 | AI17: =AH17/Assumptions!$B$8 -> 1 | AJ17: =AH17/52 -> 30 | AK17: =AJ17*I17 -> 780 | AL17: =MIN(100,I17/Assumptions!$B$26*100) -> 72.222222 | AM17: =MIN(100,H17/Assumptions!$B$27*100) -> 66.666667 | AN17: =AI17*100*Assumptions!$B$23+AL17*Assumptions!$B$24+AM17*Assumptions!$B$25 -> 85 | AO17: =AN17*AD17/100 -> 22.982583 | AP17: =RANK(AO17,$AO$6:$AO$30)+COUNTIF($AO$6:AO17,AO17)-1 -> 12 | AQ17: =IF(AO17>=Assumptions!$B$39,"Critical",IF(AO17>=Assumptions!$B$40,"High",IF(AO17>=Assumptions!$B$41,"Elevated","Watch"))) -> Elevated | AR17: =IF(AND(AN17>=Assumptions!$B$42,AD17>=Assumptions!$B$43),"Act now",IF(AN17>=Assumptions!$B$42,"Protect (structural)",IF(AD17>=Assumptions!$B$43,"Remediate supplier","Routine"))) -> Protect (structural) | AS17: =_xlfn.MAXIFS(Network!$T$5:$T$36,Network!$D$5:$D$36,$A17) -> 2 | AT17: =COUNT(K17:R17) -> 8 | AU17: =IF(AT17>=8,2,IF(AT17>=6,1,0)) -> 2 | AV17: =IF(OR(C17=1,LEFT(G17,9)="Confirmed"),1,0) -> 0 | AW17: =AS17+AU17+AV17 -> 4 | AX17: =IF(AW17>=Assumptions!$B$44,"High",IF(AW17>=Assumptions!$B$45,"Medium","Low")) -> Medium | AY17: =IF(OR(AQ17="Critical",AQ17="High"),IF(AX17="Low","VERIFY first – urgent sub-tier fact-find",IF(OR(AQ17="Critical",AV17=1),"ACT – mitigate now","CONFIRM sole-source status, then qualify alternate")),IF(AQ17="Elevated",IF(AX17="Low","VERIFY – add to N-tier survey","PLAN – qualify alternate in 90 days"),"MONITOR – quarterly review")) -> PLAN – qualify alternate in 90 days | AZ17: =IF(K17&L17&O17<>"",IF(OR(K17="",L17="",O17=""),TRIM(IF(K17="","Current ratio; ","")&IF(L17="","Net debt/EBITDA; ","")&IF(O17="","Assurance gap","")),"—"),"Current ratio; Net debt/EBITDA; Assurance gap") -> —
A18: ORG-942 | B18: =INDEX(Data!$B$5:$B$34,MATCH($A18,Data!$A$5:$A$34,0)) -> Lumen Magnetics Ltd. | C18: 2 | D18: Tier-2: magnetic cores → Aster & Boreal | E18: =INDEX(Data!$G$38:$G$67,MATCH($A18,Data!$A$38:$A$67,0)) -> SITE-095 | F18: =INDEX(Data!$I$38:$I$67,MATCH($A18,Data!$A$38:$A$67,0)) -> Z04 | G18: Presumed sole – not disclosed | H18: 2 | I18: 10 | J18: Assumption: core change revalidated inside assembly | K18: =IF(INDEX(Data!$C$5:$C$34,MATCH($A18,Data!$A$5:$A$34,0))="","",INDEX(Data!$C$5:$C$34,MATCH($A18,Data!$A$5:$A$34,0))) -> 1.37 | L18: =IF(INDEX(Data!$D$5:$D$34,MATCH($A18,Data!$A$5:$A$34,0))="","",INDEX(Data!$D$5:$D$34,MATCH($A18,Data!$A$5:$A$34,0))) -> 3 | M18: =IF(INDEX(Data!$E$5:$E$34,MATCH($A18,Data!$A$5:$A$34,0))="","",INDEX(Data!$E$5:$E$34,MATCH($A18,Data!$A$5:$A$34,0))) -> 89.5 | N18: =IF(INDEX(Data!$F$5:$F$34,MATCH($A18,Data!$A$5:$A$34,0))="","",INDEX(Data!$F$5:$F$34,MATCH($A18,Data!$A$5:$A$34,0))) -> -0.6 | O18: =IF(INDEX(Data!$G$5:$G$34,MATCH($A18,Data!$A$5:$A$34,0))="","",INDEX(Data!$G$5:$G$34,MATCH($A18,Data!$A$5:$A$34,0))) -> 63 | P18: =IF(INDEX(Data!$H$5:$H$34,MATCH($A18,Data!$A$5:$A$34,0))="","",INDEX(Data!$H$5:$H$34,MATCH($A18,Data!$A$5:$A$34,0))) -> 58 | Q18: =IF(INDEX(Data!$I$5:$I$34,MATCH($A18,Data!$A$5:$A$34,0))="","",INDEX(Data!$I$5:$I$34,MATCH($A18,Data!$A$5:$A$34,0))) -> 62 | R18: =IF(INDEX(Data!$J$5:$J$34,MATCH($A18,Data!$A$5:$A$34,0))="","",INDEX(Data!$J$5:$J$34,MATCH($A18,Data!$A$5:$A$34,0))) -> 52 | S18: =IF(L18="","",IF(L18<=Assumptions!$B$31,Assumptions!$H$31,IF(L18<=Assumptions!$C$31,Assumptions!$H$31+(L18-Assumptions!$B$31)/(Assumptions!$C$31-Assumptions!$B$31)*(Assumptions!$I$31-Assumptions!$H$31),IF(L18<=Assumptions!$D$31,Assumptions!$I$31+(L18-Assumptions!$C$31)/(Assumptions!$D$31-Assumptions!$C$31)*(Assumptions!$J$31-Assumptions!$I$31),IF(L18<=Assumptions!$E$31,Assumptions!$J$31+(L18-Assumptions!$D$31)/(Assumptions!$E$31-Assumptions!$D$31)*(Assumptions!$K$31-Assumptions!$J$31),IF(L18<=Assumptions!$F$31,Assumptions!$K$31+(L18-Assumptions!$E$31)/(Assumptions!$F$31-Assumptions!$E$31)*(Assumptions!$L$31-Assumptions!$K$31),IF(L18<=Assumptions!$G$31,Assumptions!$L$31+(L18-Assumptions!$F$31)/(Assumptions!$G$31-Assumptions!$F$31)*(Assumptions!$M$31-Assumptions!$L$31),Assumptions!$M$31))))))) -> 43.333333 | T18: =IF(K18="","",IF(K18<=Assumptions!$B$32,Assumptions!$H$32,IF(K18<=Assumptions!$C$32,Assumptions!$H$32+(K18-Assumptions!$B$32)/(Assumptions!$C$32-Assumptions!$B$32)*(Assumptions!$I$32-Assumptions!$H$32),IF(K18<=Assumptions!$D$32,Assumptions!$I$32+(K18-Assumptions!$C$32)/(Assumptions!$D$32-Assumptions!$C$32)*(Assumptions!$J$32-Assumptions!$I$32),IF(K18<=Assumptions!$E$32,Assumptions!$J$32+(K18-Assumptions!$D$32)/(Assumptions!$E$32-Assumptions!$D$32)*(Assumptions!$K$32-Assumptions!$J$32),IF(K18<=Assumptions!$F$32,Assumptions!$K$32+(K18-Assumptions!$E$32)/(Assumptions!$F$32-Assumptions!$E$32)*(Assumptions!$L$32-Assumptions!$K$32),IF(K18<=Assumptions!$G$32,Assumptions!$L$32+(K18-Assumptions!$F$32)/(Assumptions!$G$32-Assumptions!$F$32)*(Assumptions!$M$32-Assumptions!$L$32),Assumptions!$M$32))))))) -> 40.4 | U18: =IF(M18<=Assumptions!$B$33,Assumptions!$H$33,IF(M18<=Assumptions!$C$33,Assumptions!$H$33+(M18-Assumptions!$B$33)/(Assumptions!$C$33-Assumptions!$B$33)*(Assumptions!$I$33-Assumptions!$H$33),IF(M18<=Assumptions!$D$33,Assumptions!$I$33+(M18-Assumptions!$C$33)/(Assumptions!$D$33-Assumptions!$C$33)*(Assumptions!$J$33-Assumptions!$I$33),IF(M18<=Assumptions!$E$33,Assumptions!$J$33+(M18-Assumptions!$D$33)/(Assumptions!$E$33-Assumptions!$D$33)*(Assumptions!$K$33-Assumptions!$J$33),IF(M18<=Assumptions!$F$33,Assumptions!$K$33+(M18-Assumptions!$E$33)/(Assumptions!$F$33-Assumptions!$E$33)*(Assumptions!$L$33-Assumptions!$K$33),IF(M18<=Assumptions!$G$33,Assumptions!$L$33+(M18-Assumptions!$F$33)/(Assumptions!$G$33-Assumptions!$F$33)*(Assumptions!$M$33-Assumptions!$L$33),Assumptions!$M$33)))))) -> 27.5 | V18: =IF(N18<=Assumptions!$B$34,Assumptions!$H$34,IF(N18<=Assumptions!$C$34,Assumptions!$H$34+(N18-Assumptions!$B$34)/(Assumptions!$C$34-Assumptions!$B$34)*(Assumptions!$I$34-Assumptions!$H$34),IF(N18<=Assumptions!$D$34,Assumptions!$I$34+(N18-Assumptions!$C$34)/(Assumptions!$D$34-Assumptions!$C$34)*(Assumptions!$J$34-Assumptions!$I$34),IF(N18<=Assumptions!$E$34,Assumptions!$J$34+(N18-Assumptions!$D$34)/(Assumptions!$E$34-Assumptions!$D$34)*(Assumptions!$K$34-Assumptions!$J$34),IF(N18<=Assumptions!$F$34,Assumptions!$K$34+(N18-Assumptions!$E$34)/(Assumptions!$F$34-Assumptions!$E$34)*(Assumptions!$L$34-Assumptions!$K$34),IF(N18<=Assumptions!$G$34,Assumptions!$L$34+(N18-Assumptions!$F$34)/(Assumptions!$G$34-Assumptions!$F$34)*(Assumptions!$M$34-Assumptions!$L$34),Assumptions!$M$34)))))) -> 24.5 | W18: =IF(S18="",PERCENTILE($S$6:$S$30,Assumptions!$B$36),S18) -> 43.333333 | X18: =IF(T18="",PERCENTILE($T$6:$T$30,Assumptions!$B$36),T18) -> 40.4 | Y18: =IF(O18="",PERCENTILE($O$6:$O$30,Assumptions!$B$36),O18) -> 63 | Z18: =W18*Assumptions!$B$16+X18*Assumptions!$B$17 -> 41.866667 | AA18: =U18*Assumptions!$B$18+V18*Assumptions!$B$19 -> 26 | AB18: =AVERAGE(P18:R18) -> 57.333333 | AC18: 0 | AD18: =MIN(100,Z18*Assumptions!$B$11+AA18*Assumptions!$B$12+Y18*Assumptions!$B$13+AB18*Assumptions!$B$14+AC18*Assumptions!$B$20) -> 44.143333 | AE18: =MIN(1,SUMIFS(Network!$V$15:$V$30,Network!$D$15:$D$30,$A18,Network!$U$15:$U$30,1)) -> 1 | AF18: =MIN(1,SUMIFS(Network!$W$15:$W$30,Network!$D$15:$D$30,$A18,Network!$U$15:$U$30,1)) -> 1 | AG18: =MIN(1,SUMIFS(Network!$X$15:$X$30,Network!$D$15:$D$30,$A18,Network!$U$15:$U$30,1)) -> 1 | AH18: =AE18*Assumptions!$B$5+AF18*Assumptions!$B$6+AG18*Assumptions!$B$7 -> 1560 | AI18: =AH18/Assumptions!$B$8 -> 1 | AJ18: =AH18/52 -> 30 | AK18: =AJ18*I18 -> 300 | AL18: =MIN(100,I18/Assumptions!$B$26*100) -> 27.777778 | AM18: =MIN(100,H18/Assumptions!$B$27*100) -> 66.666667 | AN18: =AI18*100*Assumptions!$B$23+AL18*Assumptions!$B$24+AM18*Assumptions!$B$25 -> 71.666667 | AO18: =AN18*AD18/100 -> 31.636056 | AP18: =RANK(AO18,$AO$6:$AO$30)+COUNTIF($AO$6:AO18,AO18)-1 -> 7 | AQ18: =IF(AO18>=Assumptions!$B$39,"Critical",IF(AO18>=Assumptions!$B$40,"High",IF(AO18>=Assumptions!$B$41,"Elevated","Watch"))) -> High | AR18: =IF(AND(AN18>=Assumptions!$B$42,AD18>=Assumptions!$B$43),"Act now",IF(AN18>=Assumptions!$B$42,"Protect (structural)",IF(AD18>=Assumptions!$B$43,"Remediate supplier","Routine"))) -> Protect (structural) | AS18: =_xlfn.MAXIFS(Network!$T$5:$T$36,Network!$D$5:$D$36,$A18) -> 2 | AT18: =COUNT(K18:R18) -> 8 | AU18: =IF(AT18>=8,2,IF(AT18>=6,1,0)) -> 2 | AV18: =IF(OR(C18=1,LEFT(G18,9)="Confirmed"),1,0) -> 0 | AW18: =AS18+AU18+AV18 -> 4 | AX18: =IF(AW18>=Assumptions!$B$44,"High",IF(AW18>=Assumptions!$B$45,"Medium","Low")) -> Medium | AY18: =IF(OR(AQ18="Critical",AQ18="High"),IF(AX18="Low","VERIFY first – urgent sub-tier fact-find",IF(OR(AQ18="Critical",AV18=1),"ACT – mitigate now","CONFIRM sole-source status, then qualify alternate")),IF(AQ18="Elevated",IF(AX18="Low","VERIFY – add to N-tier survey","PLAN – qualify alternate in 90 days"),"MONITOR – quarterly review")) -> CONFIRM sole-source status, then qualify alternate | AZ18: =IF(K18&L18&O18<>"",IF(OR(K18="",L18="",O18=""),TRIM(IF(K18="","Current ratio; ","")&IF(L18="","Net debt/EBITDA; ","")&IF(O18="","Assurance gap","")),"—"),"Current ratio; Net debt/EBITDA; Assurance gap") -> —
A19: ORG-708 | B19: =INDEX(Data!$B$5:$B$34,MATCH($A19,Data!$A$5:$A$34,0)) -> Orion Ceramics Ltd. | C19: 2 | D19: Tier-2: ceramic substrates → Aster & Boreal | E19: =INDEX(Data!$G$38:$G$67,MATCH($A19,Data!$A$38:$A$67,0)) -> SITE-116 | F19: =INDEX(Data!$I$38:$I$67,MATCH($A19,Data!$A$38:$A$67,0)) -> Z01 | G19: Presumed sole – not disclosed | H19: 2 | I19: 20 | J19: Assumption: substrate change forces module reliability requal (>16 wks) | K19: =IF(INDEX(Data!$C$5:$C$34,MATCH($A19,Data!$A$5:$A$34,0))="","",INDEX(Data!$C$5:$C$34,MATCH($A19,Data!$A$5:$A$34,0))) -> 2.29 | L19: =IF(INDEX(Data!$D$5:$D$34,MATCH($A19,Data!$A$5:$A$34,0))="","",INDEX(Data!$D$5:$D$34,MATCH($A19,Data!$A$5:$A$34,0))) -> 2.67 | M19: =IF(INDEX(Data!$E$5:$E$34,MATCH($A19,Data!$A$5:$A$34,0))="","",INDEX(Data!$E$5:$E$34,MATCH($A19,Data!$A$5:$A$34,0))) -> 82.2 | N19: =IF(INDEX(Data!$F$5:$F$34,MATCH($A19,Data!$A$5:$A$34,0))="","",INDEX(Data!$F$5:$F$34,MATCH($A19,Data!$A$5:$A$34,0))) -> 0.7 | O19: =IF(INDEX(Data!$G$5:$G$34,MATCH($A19,Data!$A$5:$A$34,0))="","",INDEX(Data!$G$5:$G$34,MATCH($A19,Data!$A$5:$A$34,0))) -> 30 | P19: =IF(INDEX(Data!$H$5:$H$34,MATCH($A19,Data!$A$5:$A$34,0))="","",INDEX(Data!$H$5:$H$34,MATCH($A19,Data!$A$5:$A$34,0))) -> 82 | Q19: =IF(INDEX(Data!$I$5:$I$34,MATCH($A19,Data!$A$5:$A$34,0))="","",INDEX(Data!$I$5:$I$34,MATCH($A19,Data!$A$5:$A$34,0))) -> 76 | R19: =IF(INDEX(Data!$J$5:$J$34,MATCH($A19,Data!$A$5:$A$34,0))="","",INDEX(Data!$J$5:$J$34,MATCH($A19,Data!$A$5:$A$34,0))) -> 71 | S19: =IF(L19="","",IF(L19<=Assumptions!$B$31,Assumptions!$H$31,IF(L19<=Assumptions!$C$31,Assumptions!$H$31+(L19-Assumptions!$B$31)/(Assumptions!$C$31-Assumptions!$B$31)*(Assumptions!$I$31-Assumptions!$H$31),IF(L19<=Assumptions!$D$31,Assumptions!$I$31+(L19-Assumptions!$C$31)/(Assumptions!$D$31-Assumptions!$C$31)*(Assumptions!$J$31-Assumptions!$I$31),IF(L19<=Assumptions!$E$31,Assumptions!$J$31+(L19-Assumptions!$D$31)/(Assumptions!$E$31-Assumptions!$D$31)*(Assumptions!$K$31-Assumptions!$J$31),IF(L19<=Assumptions!$F$31,Assumptions!$K$31+(L19-Assumptions!$E$31)/(Assumptions!$F$31-Assumptions!$E$31)*(Assumptions!$L$31-Assumptions!$K$31),IF(L19<=Assumptions!$G$31,Assumptions!$L$31+(L19-Assumptions!$F$31)/(Assumptions!$G$31-Assumptions!$F$31)*(Assumptions!$M$31-Assumptions!$L$31),Assumptions!$M$31))))))) -> 34.533333 | T19: =IF(K19="","",IF(K19<=Assumptions!$B$32,Assumptions!$H$32,IF(K19<=Assumptions!$C$32,Assumptions!$H$32+(K19-Assumptions!$B$32)/(Assumptions!$C$32-Assumptions!$B$32)*(Assumptions!$I$32-Assumptions!$H$32),IF(K19<=Assumptions!$D$32,Assumptions!$I$32+(K19-Assumptions!$C$32)/(Assumptions!$D$32-Assumptions!$C$32)*(Assumptions!$J$32-Assumptions!$I$32),IF(K19<=Assumptions!$E$32,Assumptions!$J$32+(K19-Assumptions!$D$32)/(Assumptions!$E$32-Assumptions!$D$32)*(Assumptions!$K$32-Assumptions!$J$32),IF(K19<=Assumptions!$F$32,Assumptions!$K$32+(K19-Assumptions!$E$32)/(Assumptions!$F$32-Assumptions!$E$32)*(Assumptions!$L$32-Assumptions!$K$32),IF(K19<=Assumptions!$G$32,Assumptions!$L$32+(K19-Assumptions!$F$32)/(Assumptions!$G$32-Assumptions!$F$32)*(Assumptions!$M$32-Assumptions!$L$32),Assumptions!$M$32))))))) -> 6.3 | U19: =IF(M19<=Assumptions!$B$33,Assumptions!$H$33,IF(M19<=Assumptions!$C$33,Assumptions!$H$33+(M19-Assumptions!$B$33)/(Assumptions!$C$33-Assumptions!$B$33)*(Assumptions!$I$33-Assumptions!$H$33),IF(M19<=Assumptions!$D$33,Assumptions!$I$33+(M19-Assumptions!$C$33)/(Assumptions!$D$33-Assumptions!$C$33)*(Assumptions!$J$33-Assumptions!$I$33),IF(M19<=Assumptions!$E$33,Assumptions!$J$33+(M19-Assumptions!$D$33)/(Assumptions!$E$33-Assumptions!$D$33)*(Assumptions!$K$33-Assumptions!$J$33),IF(M19<=Assumptions!$F$33,Assumptions!$K$33+(M19-Assumptions!$E$33)/(Assumptions!$F$33-Assumptions!$E$33)*(Assumptions!$L$33-Assumptions!$K$33),IF(M19<=Assumptions!$G$33,Assumptions!$L$33+(M19-Assumptions!$F$33)/(Assumptions!$G$33-Assumptions!$F$33)*(Assumptions!$M$33-Assumptions!$L$33),Assumptions!$M$33)))))) -> 64 | V19: =IF(N19<=Assumptions!$B$34,Assumptions!$H$34,IF(N19<=Assumptions!$C$34,Assumptions!$H$34+(N19-Assumptions!$B$34)/(Assumptions!$C$34-Assumptions!$B$34)*(Assumptions!$I$34-Assumptions!$H$34),IF(N19<=Assumptions!$D$34,Assumptions!$I$34+(N19-Assumptions!$C$34)/(Assumptions!$D$34-Assumptions!$C$34)*(Assumptions!$J$34-Assumptions!$I$34),IF(N19<=Assumptions!$E$34,Assumptions!$J$34+(N19-Assumptions!$D$34)/(Assumptions!$E$34-Assumptions!$D$34)*(Assumptions!$K$34-Assumptions!$J$34),IF(N19<=Assumptions!$F$34,Assumptions!$K$34+(N19-Assumptions!$E$34)/(Assumptions!$F$34-Assumptions!$E$34)*(Assumptions!$L$34-Assumptions!$K$34),IF(N19<=Assumptions!$G$34,Assumptions!$L$34+(N19-Assumptions!$F$34)/(Assumptions!$G$34-Assumptions!$F$34)*(Assumptions!$M$34-Assumptions!$L$34),Assumptions!$M$34)))))) -> 13 | W19: =IF(S19="",PERCENTILE($S$6:$S$30,Assumptions!$B$36),S19) -> 34.533333 | X19: =IF(T19="",PERCENTILE($T$6:$T$30,Assumptions!$B$36),T19) -> 6.3 | Y19: =IF(O19="",PERCENTILE($O$6:$O$30,Assumptions!$B$36),O19) -> 30 | Z19: =W19*Assumptions!$B$16+X19*Assumptions!$B$17 -> 20.416667 | AA19: =U19*Assumptions!$B$18+V19*Assumptions!$B$19 -> 38.5 | AB19: =AVERAGE(P19:R19) -> 76.333333 | AC19: 0 | AD19: =MIN(100,Z19*Assumptions!$B$11+AA19*Assumptions!$B$12+Y19*Assumptions!$B$13+AB19*Assumptions!$B$14+AC19*Assumptions!$B$20) -> 41.258333 | AE19: =MIN(1,SUMIFS(Network!$V$15:$V$30,Network!$D$15:$D$30,$A19,Network!$U$15:$U$30,1)) -> 1 | AF19: =MIN(1,SUMIFS(Network!$W$15:$W$30,Network!$D$15:$D$30,$A19,Network!$U$15:$U$30,1)) -> 1 | AG19: =MIN(1,SUMIFS(Network!$X$15:$X$30,Network!$D$15:$D$30,$A19,Network!$U$15:$U$30,1)) -> 1 | AH19: =AE19*Assumptions!$B$5+AF19*Assumptions!$B$6+AG19*Assumptions!$B$7 -> 1560 | AI19: =AH19/Assumptions!$B$8 -> 1 | AJ19: =AH19/52 -> 30 | AK19: =AJ19*I19 -> 600 | AL19: =MIN(100,I19/Assumptions!$B$26*100) -> 55.555556 | AM19: =MIN(100,H19/Assumptions!$B$27*100) -> 66.666667 | AN19: =AI19*100*Assumptions!$B$23+AL19*Assumptions!$B$24+AM19*Assumptions!$B$25 -> 80 | AO19: =AN19*AD19/100 -> 33.006667 | AP19: =RANK(AO19,$AO$6:$AO$30)+COUNTIF($AO$6:AO19,AO19)-1 -> 6 | AQ19: =IF(AO19>=Assumptions!$B$39,"Critical",IF(AO19>=Assumptions!$B$40,"High",IF(AO19>=Assumptions!$B$41,"Elevated","Watch"))) -> High | AR19: =IF(AND(AN19>=Assumptions!$B$42,AD19>=Assumptions!$B$43),"Act now",IF(AN19>=Assumptions!$B$42,"Protect (structural)",IF(AD19>=Assumptions!$B$43,"Remediate supplier","Routine"))) -> Protect (structural) | AS19: =_xlfn.MAXIFS(Network!$T$5:$T$36,Network!$D$5:$D$36,$A19) -> 2 | AT19: =COUNT(K19:R19) -> 8 | AU19: =IF(AT19>=8,2,IF(AT19>=6,1,0)) -> 2 | AV19: =IF(OR(C19=1,LEFT(G19,9)="Confirmed"),1,0) -> 0 | AW19: =AS19+AU19+AV19 -> 4 | AX19: =IF(AW19>=Assumptions!$B$44,"High",IF(AW19>=Assumptions!$B$45,"Medium","Low")) -> Medium | AY19: =IF(OR(AQ19="Critical",AQ19="High"),IF(AX19="Low","VERIFY first – urgent sub-tier fact-find",IF(OR(AQ19="Critical",AV19=1),"ACT – mitigate now","CONFIRM sole-source status, then qualify alternate")),IF(AQ19="Elevated",IF(AX19="Low","VERIFY – add to N-tier survey","PLAN – qualify alternate in 90 days"),"MONITOR – quarterly review")) -> CONFIRM sole-source status, then qualify alternate | AZ19: =IF(K19&L19&O19<>"",IF(OR(K19="",L19="",O19=""),TRIM(IF(K19="","Current ratio; ","")&IF(L19="","Net debt/EBITDA; ","")&IF(O19="","Assurance gap","")),"—"),"Current ratio; Net debt/EBITDA; Assurance gap") -> —
A20: ORG-469 | B20: =INDEX(Data!$B$5:$B$34,MATCH($A20,Data!$A$5:$A$34,0)) -> Rill Connectors Ltd. | C20: 2 | D20: Tier-2: connectors → Cobalt | E20: =INDEX(Data!$G$38:$G$67,MATCH($A20,Data!$A$38:$A$67,0)) -> SITE-137 | F20: =INDEX(Data!$I$38:$I$67,MATCH($A20,Data!$A$38:$A$67,0)) -> Z04 | G20: Presumed sole – not disclosed | H20: 1 | I20: 6 | J20: Assumption: connectors are usually form-fit multi-sourceable | K20: =IF(INDEX(Data!$C$5:$C$34,MATCH($A20,Data!$A$5:$A$34,0))="","",INDEX(Data!$C$5:$C$34,MATCH($A20,Data!$A$5:$A$34,0))) -> 2.04 | L20: =IF(INDEX(Data!$D$5:$D$34,MATCH($A20,Data!$A$5:$A$34,0))="","",INDEX(Data!$D$5:$D$34,MATCH($A20,Data!$A$5:$A$34,0))) -> 2.33 | M20: =IF(INDEX(Data!$E$5:$E$34,MATCH($A20,Data!$A$5:$A$34,0))="","",INDEX(Data!$E$5:$E$34,MATCH($A20,Data!$A$5:$A$34,0))) -> 89.3 | N20: =IF(INDEX(Data!$F$5:$F$34,MATCH($A20,Data!$A$5:$A$34,0))="","",INDEX(Data!$F$5:$F$34,MATCH($A20,Data!$A$5:$A$34,0))) -> 0.3 | O20: =IF(INDEX(Data!$G$5:$G$34,MATCH($A20,Data!$A$5:$A$34,0))="","",INDEX(Data!$G$5:$G$34,MATCH($A20,Data!$A$5:$A$34,0))) -> 57 | P20: =IF(INDEX(Data!$H$5:$H$34,MATCH($A20,Data!$A$5:$A$34,0))="","",INDEX(Data!$H$5:$H$34,MATCH($A20,Data!$A$5:$A$34,0))) -> 58 | Q20: =IF(INDEX(Data!$I$5:$I$34,MATCH($A20,Data!$A$5:$A$34,0))="","",INDEX(Data!$I$5:$I$34,MATCH($A20,Data!$A$5:$A$34,0))) -> 62 | R20: =IF(INDEX(Data!$J$5:$J$34,MATCH($A20,Data!$A$5:$A$34,0))="","",INDEX(Data!$J$5:$J$34,MATCH($A20,Data!$A$5:$A$34,0))) -> 52 | S20: =IF(L20="","",IF(L20<=Assumptions!$B$31,Assumptions!$H$31,IF(L20<=Assumptions!$C$31,Assumptions!$H$31+(L20-Assumptions!$B$31)/(Assumptions!$C$31-Assumptions!$B$31)*(Assumptions!$I$31-Assumptions!$H$31),IF(L20<=Assumptions!$D$31,Assumptions!$I$31+(L20-Assumptions!$C$31)/(Assumptions!$D$31-Assumptions!$C$31)*(Assumptions!$J$31-Assumptions!$I$31),IF(L20<=Assumptions!$E$31,Assumptions!$J$31+(L20-Assumptions!$D$31)/(Assumptions!$E$31-Assumptions!$D$31)*(Assumptions!$K$31-Assumptions!$J$31),IF(L20<=Assumptions!$F$31,Assumptions!$K$31+(L20-Assumptions!$E$31)/(Assumptions!$F$31-Assumptions!$E$31)*(Assumptions!$L$31-Assumptions!$K$31),IF(L20<=Assumptions!$G$31,Assumptions!$L$31+(L20-Assumptions!$F$31)/(Assumptions!$G$31-Assumptions!$F$31)*(Assumptions!$M$31-Assumptions!$L$31),Assumptions!$M$31))))))) -> 27.96 | T20: =IF(K20="","",IF(K20<=Assumptions!$B$32,Assumptions!$H$32,IF(K20<=Assumptions!$C$32,Assumptions!$H$32+(K20-Assumptions!$B$32)/(Assumptions!$C$32-Assumptions!$B$32)*(Assumptions!$I$32-Assumptions!$H$32),IF(K20<=Assumptions!$D$32,Assumptions!$I$32+(K20-Assumptions!$C$32)/(Assumptions!$D$32-Assumptions!$C$32)*(Assumptions!$J$32-Assumptions!$I$32),IF(K20<=Assumptions!$E$32,Assumptions!$J$32+(K20-Assumptions!$D$32)/(Assumptions!$E$32-Assumptions!$D$32)*(Assumptions!$K$32-Assumptions!$J$32),IF(K20<=Assumptions!$F$32,Assumptions!$K$32+(K20-Assumptions!$E$32)/(Assumptions!$F$32-Assumptions!$E$32)*(Assumptions!$L$32-Assumptions!$K$32),IF(K20<=Assumptions!$G$32,Assumptions!$L$32+(K20-Assumptions!$F$32)/(Assumptions!$G$32-Assumptions!$F$32)*(Assumptions!$M$32-Assumptions!$L$32),Assumptions!$M$32))))))) -> 13.8 | U20: =IF(M20<=Assumptions!$B$33,Assumptions!$H$33,IF(M20<=Assumptions!$C$33,Assumptions!$H$33+(M20-Assumptions!$B$33)/(Assumptions!$C$33-Assumptions!$B$33)*(Assumptions!$I$33-Assumptions!$H$33),IF(M20<=Assumptions!$D$33,Assumptions!$I$33+(M20-Assumptions!$C$33)/(Assumptions!$D$33-Assumptions!$C$33)*(Assumptions!$J$33-Assumptions!$I$33),IF(M20<=Assumptions!$E$33,Assumptions!$J$33+(M20-Assumptions!$D$33)/(Assumptions!$E$33-Assumptions!$D$33)*(Assumptions!$K$33-Assumptions!$J$33),IF(M20<=Assumptions!$F$33,Assumptions!$K$33+(M20-Assumptions!$E$33)/(Assumptions!$F$33-Assumptions!$E$33)*(Assumptions!$L$33-Assumptions!$K$33),IF(M20<=Assumptions!$G$33,Assumptions!$L$33+(M20-Assumptions!$F$33)/(Assumptions!$G$33-Assumptions!$F$33)*(Assumptions!$M$33-Assumptions!$L$33),Assumptions!$M$33)))))) -> 28.5 | V20: =IF(N20<=Assumptions!$B$34,Assumptions!$H$34,IF(N20<=Assumptions!$C$34,Assumptions!$H$34+(N20-Assumptions!$B$34)/(Assumptions!$C$34-Assumptions!$B$34)*(Assumptions!$I$34-Assumptions!$H$34),IF(N20<=Assumptions!$D$34,Assumptions!$I$34+(N20-Assumptions!$C$34)/(Assumptions!$D$34-Assumptions!$C$34)*(Assumptions!$J$34-Assumptions!$I$34),IF(N20<=Assumptions!$E$34,Assumptions!$J$34+(N20-Assumptions!$D$34)/(Assumptions!$E$34-Assumptions!$D$34)*(Assumptions!$K$34-Assumptions!$J$34),IF(N20<=Assumptions!$F$34,Assumptions!$K$34+(N20-Assumptions!$E$34)/(Assumptions!$F$34-Assumptions!$E$34)*(Assumptions!$L$34-Assumptions!$K$34),IF(N20<=Assumptions!$G$34,Assumptions!$L$34+(N20-Assumptions!$F$34)/(Assumptions!$G$34-Assumptions!$F$34)*(Assumptions!$M$34-Assumptions!$L$34),Assumptions!$M$34)))))) -> 17 | W20: =IF(S20="",PERCENTILE($S$6:$S$30,Assumptions!$B$36),S20) -> 27.96 | X20: =IF(T20="",PERCENTILE($T$6:$T$30,Assumptions!$B$36),T20) -> 13.8 | Y20: =IF(O20="",PERCENTILE($O$6:$O$30,Assumptions!$B$36),O20) -> 57 | Z20: =W20*Assumptions!$B$16+X20*Assumptions!$B$17 -> 20.88 | AA20: =U20*Assumptions!$B$18+V20*Assumptions!$B$19 -> 22.75 | AB20: =AVERAGE(P20:R20) -> 57.333333 | AC20: 0 | AD20: =MIN(100,Z20*Assumptions!$B$11+AA20*Assumptions!$B$12+Y20*Assumptions!$B$13+AB20*Assumptions!$B$14+AC20*Assumptions!$B$20) -> 35.972333 | AE20: =MIN(1,SUMIFS(Network!$V$15:$V$30,Network!$D$15:$D$30,$A20,Network!$U$15:$U$30,1)) -> 1 | AF20: =MIN(1,SUMIFS(Network!$W$15:$W$30,Network!$D$15:$D$30,$A20,Network!$U$15:$U$30,1)) -> 1 | AG20: =MIN(1,SUMIFS(Network!$X$15:$X$30,Network!$D$15:$D$30,$A20,Network!$U$15:$U$30,1)) -> 1 | AH20: =AE20*Assumptions!$B$5+AF20*Assumptions!$B$6+AG20*Assumptions!$B$7 -> 1560 | AI20: =AH20/Assumptions!$B$8 -> 1 | AJ20: =AH20/52 -> 30 | AK20: =AJ20*I20 -> 180 | AL20: =MIN(100,I20/Assumptions!$B$26*100) -> 16.666667 | AM20: =MIN(100,H20/Assumptions!$B$27*100) -> 33.333333 | AN20: =AI20*100*Assumptions!$B$23+AL20*Assumptions!$B$24+AM20*Assumptions!$B$25 -> 61.666667 | AO20: =AN20*AD20/100 -> 22.182939 | AP20: =RANK(AO20,$AO$6:$AO$30)+COUNTIF($AO$6:AO20,AO20)-1 -> 13 | AQ20: =IF(AO20>=Assumptions!$B$39,"Critical",IF(AO20>=Assumptions!$B$40,"High",IF(AO20>=Assumptions!$B$41,"Elevated","Watch"))) -> Elevated | AR20: =IF(AND(AN20>=Assumptions!$B$42,AD20>=Assumptions!$B$43),"Act now",IF(AN20>=Assumptions!$B$42,"Protect (structural)",IF(AD20>=Assumptions!$B$43,"Remediate supplier","Routine"))) -> Protect (structural) | AS20: =_xlfn.MAXIFS(Network!$T$5:$T$36,Network!$D$5:$D$36,$A20) -> 2 | AT20: =COUNT(K20:R20) -> 8 | AU20: =IF(AT20>=8,2,IF(AT20>=6,1,0)) -> 2 | AV20: =IF(OR(C20=1,LEFT(G20,9)="Confirmed"),1,0) -> 0 | AW20: =AS20+AU20+AV20 -> 4 | AX20: =IF(AW20>=Assumptions!$B$44,"High",IF(AW20>=Assumptions!$B$45,"Medium","Low")) -> Medium | AY20: =IF(OR(AQ20="Critical",AQ20="High"),IF(AX20="Low","VERIFY first – urgent sub-tier fact-find",IF(OR(AQ20="Critical",AV20=1),"ACT – mitigate now","CONFIRM sole-source status, then qualify alternate")),IF(AQ20="Elevated",IF(AX20="Low","VERIFY – add to N-tier survey","PLAN – qualify alternate in 90 days"),"MONITOR – quarterly review")) -> PLAN – qualify alternate in 90 days | AZ20: =IF(K20&L20&O20<>"",IF(OR(K20="",L20="",O20=""),TRIM(IF(K20="","Current ratio; ","")&IF(L20="","Net debt/EBITDA; ","")&IF(O20="","Assurance gap","")),"—"),"Current ratio; Net debt/EBITDA; Assurance gap") -> —
A21: ORG-210 | B21: =INDEX(Data!$B$5:$B$34,MATCH($A21,Data!$A$5:$A$34,0)) -> Meridian Dielectrics Ltd. | C21: 2 | D21: Tier-2: dielectric film → Delta (C20) | E21: =INDEX(Data!$G$38:$G$67,MATCH($A21,Data!$A$38:$A$67,0)) -> SITE-102 | F21: =INDEX(Data!$I$38:$I$67,MATCH($A21,Data!$A$38:$A$67,0)) -> Z03 | G21: Presumed sole – not disclosed | H21: 1 | I21: 12 | J21: Assumption: film change needs capacitor requal at Delta (8 wks) + film validation | K21: =IF(INDEX(Data!$C$5:$C$34,MATCH($A21,Data!$A$5:$A$34,0))="","",INDEX(Data!$C$5:$C$34,MATCH($A21,Data!$A$5:$A$34,0))) -> 0.62 | L21: =IF(INDEX(Data!$D$5:$D$34,MATCH($A21,Data!$A$5:$A$34,0))="","",INDEX(Data!$D$5:$D$34,MATCH($A21,Data!$A$5:$A$34,0))) -> 7.2 | M21: =IF(INDEX(Data!$E$5:$E$34,MATCH($A21,Data!$A$5:$A$34,0))="","",INDEX(Data!$E$5:$E$34,MATCH($A21,Data!$A$5:$A$34,0))) -> 76.4 | N21: =IF(INDEX(Data!$F$5:$F$34,MATCH($A21,Data!$A$5:$A$34,0))="","",INDEX(Data!$F$5:$F$34,MATCH($A21,Data!$A$5:$A$34,0))) -> -17.6 | O21: =IF(INDEX(Data!$G$5:$G$34,MATCH($A21,Data!$A$5:$A$34,0))="","",INDEX(Data!$G$5:$G$34,MATCH($A21,Data!$A$5:$A$34,0))) -> 72 | P21: =IF(INDEX(Data!$H$5:$H$34,MATCH($A21,Data!$A$5:$A$34,0))="","",INDEX(Data!$H$5:$H$34,MATCH($A21,Data!$A$5:$A$34,0))) -> 19 | Q21: =IF(INDEX(Data!$I$5:$I$34,MATCH($A21,Data!$A$5:$A$34,0))="","",INDEX(Data!$I$5:$I$34,MATCH($A21,Data!$A$5:$A$34,0))) -> 26 | R21: =IF(INDEX(Data!$J$5:$J$34,MATCH($A21,Data!$A$5:$A$34,0))="","",INDEX(Data!$J$5:$J$34,MATCH($A21,Data!$A$5:$A$34,0))) -> 25 | S21: =IF(L21="","",IF(L21<=Assumptions!$B$31,Assumptions!$H$31,IF(L21<=Assumptions!$C$31,Assumptions!$H$31+(L21-Assumptions!$B$31)/(Assumptions!$C$31-Assumptions!$B$31)*(Assumptions!$I$31-Assumptions!$H$31),IF(L21<=Assumptions!$D$31,Assumptions!$I$31+(L21-Assumptions!$C$31)/(Assumptions!$D$31-Assumptions!$C$31)*(Assumptions!$J$31-Assumptions!$I$31),IF(L21<=Assumptions!$E$31,Assumptions!$J$31+(L21-Assumptions!$D$31)/(Assumptions!$E$31-Assumptions!$D$31)*(Assumptions!$K$31-Assumptions!$J$31),IF(L21<=Assumptions!$F$31,Assumptions!$K$31+(L21-Assumptions!$E$31)/(Assumptions!$F$31-Assumptions!$E$31)*(Assumptions!$L$31-Assumptions!$K$31),IF(L21<=Assumptions!$G$31,Assumptions!$L$31+(L21-Assumptions!$F$31)/(Assumptions!$G$31-Assumptions!$F$31)*(Assumptions!$M$31-Assumptions!$L$31),Assumptions!$M$31))))))) -> 100 | T21: =IF(K21="","",IF(K21<=Assumptions!$B$32,Assumptions!$H$32,IF(K21<=Assumptions!$C$32,Assumptions!$H$32+(K21-Assumptions!$B$32)/(Assumptions!$C$32-Assumptions!$B$32)*(Assumptions!$I$32-Assumptions!$H$32),IF(K21<=Assumptions!$D$32,Assumptions!$I$32+(K21-Assumptions!$C$32)/(Assumptions!$D$32-Assumptions!$C$32)*(Assumptions!$J$32-Assumptions!$I$32),IF(K21<=Assumptions!$E$32,Assumptions!$J$32+(K21-Assumptions!$D$32)/(Assumptions!$E$32-Assumptions!$D$32)*(Assumptions!$K$32-Assumptions!$J$32),IF(K21<=Assumptions!$F$32,Assumptions!$K$32+(K21-Assumptions!$E$32)/(Assumptions!$F$32-Assumptions!$E$32)*(Assumptions!$L$32-Assumptions!$K$32),IF(K21<=Assumptions!$G$32,Assumptions!$L$32+(K21-Assumptions!$F$32)/(Assumptions!$G$32-Assumptions!$F$32)*(Assumptions!$M$32-Assumptions!$L$32),Assumptions!$M$32))))))) -> 92.8 | U21: =IF(M21<=Assumptions!$B$33,Assumptions!$H$33,IF(M21<=Assumptions!$C$33,Assumptions!$H$33+(M21-Assumptions!$B$33)/(Assumptions!$C$33-Assumptions!$B$33)*(Assumptions!$I$33-Assumptions!$H$33),IF(M21<=Assumptions!$D$33,Assumptions!$I$33+(M21-Assumptions!$C$33)/(Assumptions!$D$33-Assumptions!$C$33)*(Assumptions!$J$33-Assumptions!$I$33),IF(M21<=Assumptions!$E$33,Assumptions!$J$33+(M21-Assumptions!$D$33)/(Assumptions!$E$33-Assumptions!$D$33)*(Assumptions!$K$33-Assumptions!$J$33),IF(M21<=Assumptions!$F$33,Assumptions!$K$33+(M21-Assumptions!$E$33)/(Assumptions!$F$33-Assumptions!$E$33)*(Assumptions!$L$33-Assumptions!$K$33),IF(M21<=Assumptions!$G$33,Assumptions!$L$33+(M21-Assumptions!$F$33)/(Assumptions!$G$33-Assumptions!$F$33)*(Assumptions!$M$33-Assumptions!$L$33),Assumptions!$M$33)))))) -> 93 | V21: =IF(N21<=Assumptions!$B$34,Assumptions!$H$34,IF(N21<=Assumptions!$C$34,Assumptions!$H$34+(N21-Assumptions!$B$34)/(Assumptions!$C$34-Assumptions!$B$34)*(Assumptions!$I$34-Assumptions!$H$34),IF(N21<=Assumptions!$D$34,Assumptions!$I$34+(N21-Assumptions!$C$34)/(Assumptions!$D$34-Assumptions!$C$34)*(Assumptions!$J$34-Assumptions!$I$34),IF(N21<=Assumptions!$E$34,Assumptions!$J$34+(N21-Assumptions!$D$34)/(Assumptions!$E$34-Assumptions!$D$34)*(Assumptions!$K$34-Assumptions!$J$34),IF(N21<=Assumptions!$F$34,Assumptions!$K$34+(N21-Assumptions!$E$34)/(Assumptions!$F$34-Assumptions!$E$34)*(Assumptions!$L$34-Assumptions!$K$34),IF(N21<=Assumptions!$G$34,Assumptions!$L$34+(N21-Assumptions!$F$34)/(Assumptions!$G$34-Assumptions!$F$34)*(Assumptions!$M$34-Assumptions!$L$34),Assumptions!$M$34)))))) -> 100 | W21: =IF(S21="",PERCENTILE($S$6:$S$30,Assumptions!$B$36),S21) -> 100 | X21: =IF(T21="",PERCENTILE($T$6:$T$30,Assumptions!$B$36),T21) -> 92.8 | Y21: =IF(O21="",PERCENTILE($O$6:$O$30,Assumptions!$B$36),O21) -> 72 | Z21: =W21*Assumptions!$B$16+X21*Assumptions!$B$17 -> 96.4 | AA21: =U21*Assumptions!$B$18+V21*Assumptions!$B$19 -> 96.5 | AB21: =AVERAGE(P21:R21) -> 23.333333 | AC21: 1 | AD21: =MIN(100,Z21*Assumptions!$B$11+AA21*Assumptions!$B$12+Y21*Assumptions!$B$13+AB21*Assumptions!$B$14+AC21*Assumptions!$B$20) -> 84.503333 | AE21: =MIN(1,SUMIFS(Network!$V$15:$V$30,Network!$D$15:$D$30,$A21,Network!$U$15:$U$30,1)) -> 1 | AF21: =MIN(1,SUMIFS(Network!$W$15:$W$30,Network!$D$15:$D$30,$A21,Network!$U$15:$U$30,1)) -> 1 | AG21: =MIN(1,SUMIFS(Network!$X$15:$X$30,Network!$D$15:$D$30,$A21,Network!$U$15:$U$30,1)) -> 0 | AH21: =AE21*Assumptions!$B$5+AF21*Assumptions!$B$6+AG21*Assumptions!$B$7 -> 1144 | AI21: =AH21/Assumptions!$B$8 -> 0.73333333 | AJ21: =AH21/52 -> 22 | AK21: =AJ21*I21 -> 264 | AL21: =MIN(100,I21/Assumptions!$B$26*100) -> 33.333333 | AM21: =MIN(100,H21/Assumptions!$B$27*100) -> 33.333333 | AN21: =AI21*100*Assumptions!$B$23+AL21*Assumptions!$B$24+AM21*Assumptions!$B$25 -> 53.333333 | AO21: =AN21*AD21/100 -> 45.068444 | AP21: =RANK(AO21,$AO$6:$AO$30)+COUNTIF($AO$6:AO21,AO21)-1 -> 3 | AQ21: =IF(AO21>=Assumptions!$B$39,"Critical",IF(AO21>=Assumptions!$B$40,"High",IF(AO21>=Assumptions!$B$41,"Elevated","Watch"))) -> Critical | AR21: =IF(AND(AN21>=Assumptions!$B$42,AD21>=Assumptions!$B$43),"Act now",IF(AN21>=Assumptions!$B$42,"Protect (structural)",IF(AD21>=Assumptions!$B$43,"Remediate supplier","Routine"))) -> Remediate supplier | AS21: =_xlfn.MAXIFS(Network!$T$5:$T$36,Network!$D$5:$D$36,$A21) -> 2 | AT21: =COUNT(K21:R21) -> 8 | AU21: =IF(AT21>=8,2,IF(AT21>=6,1,0)) -> 2 | AV21: =IF(OR(C21=1,LEFT(G21,9)="Confirmed"),1,0) -> 0 | AW21: =AS21+AU21+AV21 -> 4 | AX21: =IF(AW21>=Assumptions!$B$44,"High",IF(AW21>=Assumptions!$B$45,"Medium","Low")) -> Medium | AY21: =IF(OR(AQ21="Critical",AQ21="High"),IF(AX21="Low","VERIFY first – urgent sub-tier fact-find",IF(OR(AQ21="Critical",AV21=1),"ACT – mitigate now","CONFIRM sole-source status, then qualify alternate")),IF(AQ21="Elevated",IF(AX21="Low","VERIFY – add to N-tier survey","PLAN – qualify alternate in 90 days"),"MONITOR – quarterly review")) -> ACT – mitigate now | AZ21: =IF(K21&L21&O21<>"",IF(OR(K21="",L21="",O21=""),TRIM(IF(K21="","Current ratio; ","")&IF(L21="","Net debt/EBITDA; ","")&IF(O21="","Assurance gap","")),"—"),"Current ratio; Net debt/EBITDA; Assurance gap") -> —
A22: ORG-849 | B22: =INDEX(Data!$B$5:$B$34,MATCH($A22,Data!$A$5:$A$34,0)) -> Nacre Foils Ltd. | C22: 2 | D22: Tier-2: aluminium foil → Delta (C20) | E22: =INDEX(Data!$G$38:$G$67,MATCH($A22,Data!$A$38:$A$67,0)) -> SITE-109 | F22: =INDEX(Data!$I$38:$I$67,MATCH($A22,Data!$A$38:$A$67,0)) -> Z06 | G22: Presumed sole – not disclosed | H22: 1 | I22: 8 | J22: Assumption: foil change ≈ C20 requal | K22: =IF(INDEX(Data!$C$5:$C$34,MATCH($A22,Data!$A$5:$A$34,0))="","",INDEX(Data!$C$5:$C$34,MATCH($A22,Data!$A$5:$A$34,0))) -> 1.54 | L22: =IF(INDEX(Data!$D$5:$D$34,MATCH($A22,Data!$A$5:$A$34,0))="","",INDEX(Data!$D$5:$D$34,MATCH($A22,Data!$A$5:$A$34,0))) -> 1.67 | M22: =IF(INDEX(Data!$E$5:$E$34,MATCH($A22,Data!$A$5:$A$34,0))="","",INDEX(Data!$E$5:$E$34,MATCH($A22,Data!$A$5:$A$34,0))) -> 79.3 | N22: =IF(INDEX(Data!$F$5:$F$34,MATCH($A22,Data!$A$5:$A$34,0))="","",INDEX(Data!$F$5:$F$34,MATCH($A22,Data!$A$5:$A$34,0))) -> -3.5 | O22: =IF(INDEX(Data!$G$5:$G$34,MATCH($A22,Data!$A$5:$A$34,0))="","",INDEX(Data!$G$5:$G$34,MATCH($A22,Data!$A$5:$A$34,0))) -> 21 | P22: =IF(INDEX(Data!$H$5:$H$34,MATCH($A22,Data!$A$5:$A$34,0))="","",INDEX(Data!$H$5:$H$34,MATCH($A22,Data!$A$5:$A$34,0))) -> 67 | Q22: =IF(INDEX(Data!$I$5:$I$34,MATCH($A22,Data!$A$5:$A$34,0))="","",INDEX(Data!$I$5:$I$34,MATCH($A22,Data!$A$5:$A$34,0))) -> 59 | R22: =IF(INDEX(Data!$J$5:$J$34,MATCH($A22,Data!$A$5:$A$34,0))="","",INDEX(Data!$J$5:$J$34,MATCH($A22,Data!$A$5:$A$34,0))) -> 54 | S22: =IF(L22="","",IF(L22<=Assumptions!$B$31,Assumptions!$H$31,IF(L22<=Assumptions!$C$31,Assumptions!$H$31+(L22-Assumptions!$B$31)/(Assumptions!$C$31-Assumptions!$B$31)*(Assumptions!$I$31-Assumptions!$H$31),IF(L22<=Assumptions!$D$31,Assumptions!$I$31+(L22-Assumptions!$C$31)/(Assumptions!$D$31-Assumptions!$C$31)*(Assumptions!$J$31-Assumptions!$I$31),IF(L22<=Assumptions!$E$31,Assumptions!$J$31+(L22-Assumptions!$D$31)/(Assumptions!$E$31-Assumptions!$D$31)*(Assumptions!$K$31-Assumptions!$J$31),IF(L22<=Assumptions!$F$31,Assumptions!$K$31+(L22-Assumptions!$E$31)/(Assumptions!$F$31-Assumptions!$E$31)*(Assumptions!$L$31-Assumptions!$K$31),IF(L22<=Assumptions!$G$31,Assumptions!$L$31+(L22-Assumptions!$F$31)/(Assumptions!$G$31-Assumptions!$F$31)*(Assumptions!$M$31-Assumptions!$L$31),Assumptions!$M$31))))))) -> 20.04 | T22: =IF(K22="","",IF(K22<=Assumptions!$B$32,Assumptions!$H$32,IF(K22<=Assumptions!$C$32,Assumptions!$H$32+(K22-Assumptions!$B$32)/(Assumptions!$C$32-Assumptions!$B$32)*(Assumptions!$I$32-Assumptions!$H$32),IF(K22<=Assumptions!$D$32,Assumptions!$I$32+(K22-Assumptions!$C$32)/(Assumptions!$D$32-Assumptions!$C$32)*(Assumptions!$J$32-Assumptions!$I$32),IF(K22<=Assumptions!$E$32,Assumptions!$J$32+(K22-Assumptions!$D$32)/(Assumptions!$E$32-Assumptions!$D$32)*(Assumptions!$K$32-Assumptions!$J$32),IF(K22<=Assumptions!$F$32,Assumptions!$K$32+(K22-Assumptions!$E$32)/(Assumptions!$F$32-Assumptions!$E$32)*(Assumptions!$L$32-Assumptions!$K$32),IF(K22<=Assumptions!$G$32,Assumptions!$L$32+(K22-Assumptions!$F$32)/(Assumptions!$G$32-Assumptions!$F$32)*(Assumptions!$M$32-Assumptions!$L$32),Assumptions!$M$32))))))) -> 28.8 | U22: =IF(M22<=Assumptions!$B$33,Assumptions!$H$33,IF(M22<=Assumptions!$C$33,Assumptions!$H$33+(M22-Assumptions!$B$33)/(Assumptions!$C$33-Assumptions!$B$33)*(Assumptions!$I$33-Assumptions!$H$33),IF(M22<=Assumptions!$D$33,Assumptions!$I$33+(M22-Assumptions!$C$33)/(Assumptions!$D$33-Assumptions!$C$33)*(Assumptions!$J$33-Assumptions!$I$33),IF(M22<=Assumptions!$E$33,Assumptions!$J$33+(M22-Assumptions!$D$33)/(Assumptions!$E$33-Assumptions!$D$33)*(Assumptions!$K$33-Assumptions!$J$33),IF(M22<=Assumptions!$F$33,Assumptions!$K$33+(M22-Assumptions!$E$33)/(Assumptions!$F$33-Assumptions!$E$33)*(Assumptions!$L$33-Assumptions!$K$33),IF(M22<=Assumptions!$G$33,Assumptions!$L$33+(M22-Assumptions!$F$33)/(Assumptions!$G$33-Assumptions!$F$33)*(Assumptions!$M$33-Assumptions!$L$33),Assumptions!$M$33)))))) -> 78.5 | V22: =IF(N22<=Assumptions!$B$34,Assumptions!$H$34,IF(N22<=Assumptions!$C$34,Assumptions!$H$34+(N22-Assumptions!$B$34)/(Assumptions!$C$34-Assumptions!$B$34)*(Assumptions!$I$34-Assumptions!$H$34),IF(N22<=Assumptions!$D$34,Assumptions!$I$34+(N22-Assumptions!$C$34)/(Assumptions!$D$34-Assumptions!$C$34)*(Assumptions!$J$34-Assumptions!$I$34),IF(N22<=Assumptions!$E$34,Assumptions!$J$34+(N22-Assumptions!$D$34)/(Assumptions!$E$34-Assumptions!$D$34)*(Assumptions!$K$34-Assumptions!$J$34),IF(N22<=Assumptions!$F$34,Assumptions!$K$34+(N22-Assumptions!$E$34)/(Assumptions!$F$34-Assumptions!$E$34)*(Assumptions!$L$34-Assumptions!$K$34),IF(N22<=Assumptions!$G$34,Assumptions!$L$34+(N22-Assumptions!$F$34)/(Assumptions!$G$34-Assumptions!$F$34)*(Assumptions!$M$34-Assumptions!$L$34),Assumptions!$M$34)))))) -> 45 | W22: =IF(S22="",PERCENTILE($S$6:$S$30,Assumptions!$B$36),S22) -> 20.04 | X22: =IF(T22="",PERCENTILE($T$6:$T$30,Assumptions!$B$36),T22) -> 28.8 | Y22: =IF(O22="",PERCENTILE($O$6:$O$30,Assumptions!$B$36),O22) -> 21 | Z22: =W22*Assumptions!$B$16+X22*Assumptions!$B$17 -> 24.42 | AA22: =U22*Assumptions!$B$18+V22*Assumptions!$B$19 -> 61.75 | AB22: =AVERAGE(P22:R22) -> 60 | AC22: 0 | AD22: =MIN(100,Z22*Assumptions!$B$11+AA22*Assumptions!$B$12+Y22*Assumptions!$B$13+AB22*Assumptions!$B$14+AC22*Assumptions!$B$20) -> 44.001 | AE22: =MIN(1,SUMIFS(Network!$V$15:$V$30,Network!$D$15:$D$30,$A22,Network!$U$15:$U$30,1)) -> 1 | AF22: =MIN(1,SUMIFS(Network!$W$15:$W$30,Network!$D$15:$D$30,$A22,Network!$U$15:$U$30,1)) -> 1 | AG22: =MIN(1,SUMIFS(Network!$X$15:$X$30,Network!$D$15:$D$30,$A22,Network!$U$15:$U$30,1)) -> 0 | AH22: =AE22*Assumptions!$B$5+AF22*Assumptions!$B$6+AG22*Assumptions!$B$7 -> 1144 | AI22: =AH22/Assumptions!$B$8 -> 0.73333333 | AJ22: =AH22/52 -> 22 | AK22: =AJ22*I22 -> 176 | AL22: =MIN(100,I22/Assumptions!$B$26*100) -> 22.222222 | AM22: =MIN(100,H22/Assumptions!$B$27*100) -> 33.333333 | AN22: =AI22*100*Assumptions!$B$23+AL22*Assumptions!$B$24+AM22*Assumptions!$B$25 -> 50 | AO22: =AN22*AD22/100 -> 22.0005 | AP22: =RANK(AO22,$AO$6:$AO$30)+COUNTIF($AO$6:AO22,AO22)-1 -> 14 | AQ22: =IF(AO22>=Assumptions!$B$39,"Critical",IF(AO22>=Assumptions!$B$40,"High",IF(AO22>=Assumptions!$B$41,"Elevated","Watch"))) -> Elevated | AR22: =IF(AND(AN22>=Assumptions!$B$42,AD22>=Assumptions!$B$43),"Act now",IF(AN22>=Assumptions!$B$42,"Protect (structural)",IF(AD22>=Assumptions!$B$43,"Remediate supplier","Routine"))) -> Routine | AS22: =_xlfn.MAXIFS(Network!$T$5:$T$36,Network!$D$5:$D$36,$A22) -> 2 | AT22: =COUNT(K22:R22) -> 8 | AU22: =IF(AT22>=8,2,IF(AT22>=6,1,0)) -> 2 | AV22: =IF(OR(C22=1,LEFT(G22,9)="Confirmed"),1,0) -> 0 | AW22: =AS22+AU22+AV22 -> 4 | AX22: =IF(AW22>=Assumptions!$B$44,"High",IF(AW22>=Assumptions!$B$45,"Medium","Low")) -> Medium | AY22: =IF(OR(AQ22="Critical",AQ22="High"),IF(AX22="Low","VERIFY first – urgent sub-tier fact-find",IF(OR(AQ22="Critical",AV22=1),"ACT – mitigate now","CONFIRM sole-source status, then qualify alternate")),IF(AQ22="Elevated",IF(AX22="Low","VERIFY – add to N-tier survey","PLAN – qualify alternate in 90 days"),"MONITOR – quarterly review")) -> PLAN – qualify alternate in 90 days | AZ22: =IF(K22&L22&O22<>"",IF(OR(K22="",L22="",O22=""),TRIM(IF(K22="","Current ratio; ","")&IF(L22="","Net debt/EBITDA; ","")&IF(O22="","Assurance gap","")),"—"),"Current ratio; Net debt/EBITDA; Assurance gap") -> —
A23: ORG-274 | B23: =INDEX(Data!$B$5:$B$34,MATCH($A23,Data!$A$5:$A$34,0)) -> Pine Thermal Metals Ltd. | C23: 2 | D23: Tier-2: thermal metals → Estuary (H20) | E23: =INDEX(Data!$G$38:$G$67,MATCH($A23,Data!$A$38:$A$67,0)) -> SITE-123 | F23: =INDEX(Data!$I$38:$I$67,MATCH($A23,Data!$A$38:$A$67,0)) -> Z06 | G23: Presumed sole – not disclosed | H23: 1 | I23: 4 | J23: Assumption: commodity metal, short requal | K23: =IF(INDEX(Data!$C$5:$C$34,MATCH($A23,Data!$A$5:$A$34,0))="","",INDEX(Data!$C$5:$C$34,MATCH($A23,Data!$A$5:$A$34,0))) -> 1.79 | L23: =IF(INDEX(Data!$D$5:$D$34,MATCH($A23,Data!$A$5:$A$34,0))="","",INDEX(Data!$D$5:$D$34,MATCH($A23,Data!$A$5:$A$34,0))) -> 3.67 | M23: =IF(INDEX(Data!$E$5:$E$34,MATCH($A23,Data!$A$5:$A$34,0))="","",INDEX(Data!$E$5:$E$34,MATCH($A23,Data!$A$5:$A$34,0))) -> 85.6 | N23: =IF(INDEX(Data!$F$5:$F$34,MATCH($A23,Data!$A$5:$A$34,0))="","",INDEX(Data!$F$5:$F$34,MATCH($A23,Data!$A$5:$A$34,0))) -> 0.8 | O23: =IF(INDEX(Data!$G$5:$G$34,MATCH($A23,Data!$A$5:$A$34,0))="","",INDEX(Data!$G$5:$G$34,MATCH($A23,Data!$A$5:$A$34,0))) -> 39 | P23: =IF(INDEX(Data!$H$5:$H$34,MATCH($A23,Data!$A$5:$A$34,0))="","",INDEX(Data!$H$5:$H$34,MATCH($A23,Data!$A$5:$A$34,0))) -> 67 | Q23: =IF(INDEX(Data!$I$5:$I$34,MATCH($A23,Data!$A$5:$A$34,0))="","",INDEX(Data!$I$5:$I$34,MATCH($A23,Data!$A$5:$A$34,0))) -> 59 | R23: =IF(INDEX(Data!$J$5:$J$34,MATCH($A23,Data!$A$5:$A$34,0))="","",INDEX(Data!$J$5:$J$34,MATCH($A23,Data!$A$5:$A$34,0))) -> 54 | S23: =IF(L23="","",IF(L23<=Assumptions!$B$31,Assumptions!$H$31,IF(L23<=Assumptions!$C$31,Assumptions!$H$31+(L23-Assumptions!$B$31)/(Assumptions!$C$31-Assumptions!$B$31)*(Assumptions!$I$31-Assumptions!$H$31),IF(L23<=Assumptions!$D$31,Assumptions!$I$31+(L23-Assumptions!$C$31)/(Assumptions!$D$31-Assumptions!$C$31)*(Assumptions!$J$31-Assumptions!$I$31),IF(L23<=Assumptions!$E$31,Assumptions!$J$31+(L23-Assumptions!$D$31)/(Assumptions!$E$31-Assumptions!$D$31)*(Assumptions!$K$31-Assumptions!$J$31),IF(L23<=Assumptions!$F$31,Assumptions!$K$31+(L23-Assumptions!$E$31)/(Assumptions!$F$31-Assumptions!$E$31)*(Assumptions!$L$31-Assumptions!$K$31),IF(L23<=Assumptions!$G$31,Assumptions!$L$31+(L23-Assumptions!$F$31)/(Assumptions!$G$31-Assumptions!$F$31)*(Assumptions!$M$31-Assumptions!$L$31),Assumptions!$M$31))))))) -> 61.2 | T23: =IF(K23="","",IF(K23<=Assumptions!$B$32,Assumptions!$H$32,IF(K23<=Assumptions!$C$32,Assumptions!$H$32+(K23-Assumptions!$B$32)/(Assumptions!$C$32-Assumptions!$B$32)*(Assumptions!$I$32-Assumptions!$H$32),IF(K23<=Assumptions!$D$32,Assumptions!$I$32+(K23-Assumptions!$C$32)/(Assumptions!$D$32-Assumptions!$C$32)*(Assumptions!$J$32-Assumptions!$I$32),IF(K23<=Assumptions!$E$32,Assumptions!$J$32+(K23-Assumptions!$D$32)/(Assumptions!$E$32-Assumptions!$D$32)*(Assumptions!$K$32-Assumptions!$J$32),IF(K23<=Assumptions!$F$32,Assumptions!$K$32+(K23-Assumptions!$E$32)/(Assumptions!$F$32-Assumptions!$E$32)*(Assumptions!$L$32-Assumptions!$K$32),IF(K23<=Assumptions!$G$32,Assumptions!$L$32+(K23-Assumptions!$F$32)/(Assumptions!$G$32-Assumptions!$F$32)*(Assumptions!$M$32-Assumptions!$L$32),Assumptions!$M$32))))))) -> 21.3 | U23: =IF(M23<=Assumptions!$B$33,Assumptions!$H$33,IF(M23<=Assumptions!$C$33,Assumptions!$H$33+(M23-Assumptions!$B$33)/(Assumptions!$C$33-Assumptions!$B$33)*(Assumptions!$I$33-Assumptions!$H$33),IF(M23<=Assumptions!$D$33,Assumptions!$I$33+(M23-Assumptions!$C$33)/(Assumptions!$D$33-Assumptions!$C$33)*(Assumptions!$J$33-Assumptions!$I$33),IF(M23<=Assumptions!$E$33,Assumptions!$J$33+(M23-Assumptions!$D$33)/(Assumptions!$E$33-Assumptions!$D$33)*(Assumptions!$K$33-Assumptions!$J$33),IF(M23<=Assumptions!$F$33,Assumptions!$K$33+(M23-Assumptions!$E$33)/(Assumptions!$F$33-Assumptions!$E$33)*(Assumptions!$L$33-Assumptions!$K$33),IF(M23<=Assumptions!$G$33,Assumptions!$L$33+(M23-Assumptions!$F$33)/(Assumptions!$G$33-Assumptions!$F$33)*(Assumptions!$M$33-Assumptions!$L$33),Assumptions!$M$33)))))) -> 47 | V23: =IF(N23<=Assumptions!$B$34,Assumptions!$H$34,IF(N23<=Assumptions!$C$34,Assumptions!$H$34+(N23-Assumptions!$B$34)/(Assumptions!$C$34-Assumptions!$B$34)*(Assumptions!$I$34-Assumptions!$H$34),IF(N23<=Assumptions!$D$34,Assumptions!$I$34+(N23-Assumptions!$C$34)/(Assumptions!$D$34-Assumptions!$C$34)*(Assumptions!$J$34-Assumptions!$I$34),IF(N23<=Assumptions!$E$34,Assumptions!$J$34+(N23-Assumptions!$D$34)/(Assumptions!$E$34-Assumptions!$D$34)*(Assumptions!$K$34-Assumptions!$J$34),IF(N23<=Assumptions!$F$34,Assumptions!$K$34+(N23-Assumptions!$E$34)/(Assumptions!$F$34-Assumptions!$E$34)*(Assumptions!$L$34-Assumptions!$K$34),IF(N23<=Assumptions!$G$34,Assumptions!$L$34+(N23-Assumptions!$F$34)/(Assumptions!$G$34-Assumptions!$F$34)*(Assumptions!$M$34-Assumptions!$L$34),Assumptions!$M$34)))))) -> 12 | W23: =IF(S23="",PERCENTILE($S$6:$S$30,Assumptions!$B$36),S23) -> 61.2 | X23: =IF(T23="",PERCENTILE($T$6:$T$30,Assumptions!$B$36),T23) -> 21.3 | Y23: =IF(O23="",PERCENTILE($O$6:$O$30,Assumptions!$B$36),O23) -> 39 | Z23: =W23*Assumptions!$B$16+X23*Assumptions!$B$17 -> 41.25 | AA23: =U23*Assumptions!$B$18+V23*Assumptions!$B$19 -> 29.5 | AB23: =AVERAGE(P23:R23) -> 60 | AC23: 0 | AD23: =MIN(100,Z23*Assumptions!$B$11+AA23*Assumptions!$B$12+Y23*Assumptions!$B$13+AB23*Assumptions!$B$14+AC23*Assumptions!$B$20) -> 42.075 | AE23: =MIN(1,SUMIFS(Network!$V$15:$V$30,Network!$D$15:$D$30,$A23,Network!$U$15:$U$30,1)) -> 0 | AF23: =MIN(1,SUMIFS(Network!$W$15:$W$30,Network!$D$15:$D$30,$A23,Network!$U$15:$U$30,1)) -> 1 | AG23: =MIN(1,SUMIFS(Network!$X$15:$X$30,Network!$D$15:$D$30,$A23,Network!$U$15:$U$30,1)) -> 1 | AH23: =AE23*Assumptions!$B$5+AF23*Assumptions!$B$6+AG23*Assumptions!$B$7 -> 936 | AI23: =AH23/Assumptions!$B$8 -> 0.6 | AJ23: =AH23/52 -> 18 | AK23: =AJ23*I23 -> 72 | AL23: =MIN(100,I23/Assumptions!$B$26*100) -> 11.111111 | AM23: =MIN(100,H23/Assumptions!$B$27*100) -> 33.333333 | AN23: =AI23*100*Assumptions!$B$23+AL23*Assumptions!$B$24+AM23*Assumptions!$B$25 -> 40 | AO23: =AN23*AD23/100 -> 16.83 | AP23: =RANK(AO23,$AO$6:$AO$30)+COUNTIF($AO$6:AO23,AO23)-1 -> 17 | AQ23: =IF(AO23>=Assumptions!$B$39,"Critical",IF(AO23>=Assumptions!$B$40,"High",IF(AO23>=Assumptions!$B$41,"Elevated","Watch"))) -> Watch | AR23: =IF(AND(AN23>=Assumptions!$B$42,AD23>=Assumptions!$B$43),"Act now",IF(AN23>=Assumptions!$B$42,"Protect (structural)",IF(AD23>=Assumptions!$B$43,"Remediate supplier","Routine"))) -> Routine | AS23: =_xlfn.MAXIFS(Network!$T$5:$T$36,Network!$D$5:$D$36,$A23) -> 2 | AT23: =COUNT(K23:R23) -> 8 | AU23: =IF(AT23>=8,2,IF(AT23>=6,1,0)) -> 2 | AV23: =IF(OR(C23=1,LEFT(G23,9)="Confirmed"),1,0) -> 0 | AW23: =AS23+AU23+AV23 -> 4 | AX23: =IF(AW23>=Assumptions!$B$44,"High",IF(AW23>=Assumptions!$B$45,"Medium","Low")) -> Medium | AY23: =IF(OR(AQ23="Critical",AQ23="High"),IF(AX23="Low","VERIFY first – urgent sub-tier fact-find",IF(OR(AQ23="Critical",AV23=1),"ACT – mitigate now","CONFIRM sole-source status, then qualify alternate")),IF(AQ23="Elevated",IF(AX23="Low","VERIFY – add to N-tier survey","PLAN – qualify alternate in 90 days"),"MONITOR – quarterly review")) -> MONITOR – quarterly review | AZ23: =IF(K23&L23&O23<>"",IF(OR(K23="",L23="",O23=""),TRIM(IF(K23="","Current ratio; ","")&IF(L23="","Net debt/EBITDA; ","")&IF(O23="","Assurance gap","")),"—"),"Current ratio; Net debt/EBITDA; Assurance gap") -> —
A24: ORG-329 | B24: =INDEX(Data!$B$5:$B$34,MATCH($A24,Data!$A$5:$A$34,0)) -> Quartz Alloy Ltd. | C24: 2 | D24: Tier-2: aluminium alloy → ForgeLine (H10) | E24: =INDEX(Data!$G$38:$G$67,MATCH($A24,Data!$A$38:$A$67,0)) -> SITE-130 | F24: =INDEX(Data!$I$38:$I$67,MATCH($A24,Data!$A$38:$A$67,0)) -> Z02 | G24: Presumed sole – not disclosed | H24: 1 | I24: 4 | J24: Assumption: commodity alloy, short requal | K24: =IF(INDEX(Data!$C$5:$C$34,MATCH($A24,Data!$A$5:$A$34,0))="","",INDEX(Data!$C$5:$C$34,MATCH($A24,Data!$A$5:$A$34,0))) -> 2.43 | L24: =IF(INDEX(Data!$D$5:$D$34,MATCH($A24,Data!$A$5:$A$34,0))="","",INDEX(Data!$D$5:$D$34,MATCH($A24,Data!$A$5:$A$34,0))) -> 1.33 | M24: =IF(INDEX(Data!$E$5:$E$34,MATCH($A24,Data!$A$5:$A$34,0))="","",INDEX(Data!$E$5:$E$34,MATCH($A24,Data!$A$5:$A$34,0))) -> 84.6 | N24: =IF(INDEX(Data!$F$5:$F$34,MATCH($A24,Data!$A$5:$A$34,0))="","",INDEX(Data!$F$5:$F$34,MATCH($A24,Data!$A$5:$A$34,0))) -> -2.1 | O24: =IF(INDEX(Data!$G$5:$G$34,MATCH($A24,Data!$A$5:$A$34,0))="","",INDEX(Data!$G$5:$G$34,MATCH($A24,Data!$A$5:$A$34,0))) -> 48 | P24: =IF(INDEX(Data!$H$5:$H$34,MATCH($A24,Data!$A$5:$A$34,0))="","",INDEX(Data!$H$5:$H$34,MATCH($A24,Data!$A$5:$A$34,0))) -> 27 | Q24: =IF(INDEX(Data!$I$5:$I$34,MATCH($A24,Data!$A$5:$A$34,0))="","",INDEX(Data!$I$5:$I$34,MATCH($A24,Data!$A$5:$A$34,0))) -> 30 | R24: =IF(INDEX(Data!$J$5:$J$34,MATCH($A24,Data!$A$5:$A$34,0))="","",INDEX(Data!$J$5:$J$34,MATCH($A24,Data!$A$5:$A$34,0))) -> 24 | S24: =IF(L24="","",IF(L24<=Assumptions!$B$31,Assumptions!$H$31,IF(L24<=Assumptions!$C$31,Assumptions!$H$31+(L24-Assumptions!$B$31)/(Assumptions!$C$31-Assumptions!$B$31)*(Assumptions!$I$31-Assumptions!$H$31),IF(L24<=Assumptions!$D$31,Assumptions!$I$31+(L24-Assumptions!$C$31)/(Assumptions!$D$31-Assumptions!$C$31)*(Assumptions!$J$31-Assumptions!$I$31),IF(L24<=Assumptions!$E$31,Assumptions!$J$31+(L24-Assumptions!$D$31)/(Assumptions!$E$31-Assumptions!$D$31)*(Assumptions!$K$31-Assumptions!$J$31),IF(L24<=Assumptions!$F$31,Assumptions!$K$31+(L24-Assumptions!$E$31)/(Assumptions!$F$31-Assumptions!$E$31)*(Assumptions!$L$31-Assumptions!$K$31),IF(L24<=Assumptions!$G$31,Assumptions!$L$31+(L24-Assumptions!$F$31)/(Assumptions!$G$31-Assumptions!$F$31)*(Assumptions!$M$31-Assumptions!$L$31),Assumptions!$M$31))))))) -> 15.96 | T24: =IF(K24="","",IF(K24<=Assumptions!$B$32,Assumptions!$H$32,IF(K24<=Assumptions!$C$32,Assumptions!$H$32+(K24-Assumptions!$B$32)/(Assumptions!$C$32-Assumptions!$B$32)*(Assumptions!$I$32-Assumptions!$H$32),IF(K24<=Assumptions!$D$32,Assumptions!$I$32+(K24-Assumptions!$C$32)/(Assumptions!$D$32-Assumptions!$C$32)*(Assumptions!$J$32-Assumptions!$I$32),IF(K24<=Assumptions!$E$32,Assumptions!$J$32+(K24-Assumptions!$D$32)/(Assumptions!$E$32-Assumptions!$D$32)*(Assumptions!$K$32-Assumptions!$J$32),IF(K24<=Assumptions!$F$32,Assumptions!$K$32+(K24-Assumptions!$E$32)/(Assumptions!$F$32-Assumptions!$E$32)*(Assumptions!$L$32-Assumptions!$K$32),IF(K24<=Assumptions!$G$32,Assumptions!$L$32+(K24-Assumptions!$F$32)/(Assumptions!$G$32-Assumptions!$F$32)*(Assumptions!$M$32-Assumptions!$L$32),Assumptions!$M$32))))))) -> 2.1 | U24: =IF(M24<=Assumptions!$B$33,Assumptions!$H$33,IF(M24<=Assumptions!$C$33,Assumptions!$H$33+(M24-Assumptions!$B$33)/(Assumptions!$C$33-Assumptions!$B$33)*(Assumptions!$I$33-Assumptions!$H$33),IF(M24<=Assumptions!$D$33,Assumptions!$I$33+(M24-Assumptions!$C$33)/(Assumptions!$D$33-Assumptions!$C$33)*(Assumptions!$J$33-Assumptions!$I$33),IF(M24<=Assumptions!$E$33,Assumptions!$J$33+(M24-Assumptions!$D$33)/(Assumptions!$E$33-Assumptions!$D$33)*(Assumptions!$K$33-Assumptions!$J$33),IF(M24<=Assumptions!$F$33,Assumptions!$K$33+(M24-Assumptions!$E$33)/(Assumptions!$F$33-Assumptions!$E$33)*(Assumptions!$L$33-Assumptions!$K$33),IF(M24<=Assumptions!$G$33,Assumptions!$L$33+(M24-Assumptions!$F$33)/(Assumptions!$G$33-Assumptions!$F$33)*(Assumptions!$M$33-Assumptions!$L$33),Assumptions!$M$33)))))) -> 52 | V24: =IF(N24<=Assumptions!$B$34,Assumptions!$H$34,IF(N24<=Assumptions!$C$34,Assumptions!$H$34+(N24-Assumptions!$B$34)/(Assumptions!$C$34-Assumptions!$B$34)*(Assumptions!$I$34-Assumptions!$H$34),IF(N24<=Assumptions!$D$34,Assumptions!$I$34+(N24-Assumptions!$C$34)/(Assumptions!$D$34-Assumptions!$C$34)*(Assumptions!$J$34-Assumptions!$I$34),IF(N24<=Assumptions!$E$34,Assumptions!$J$34+(N24-Assumptions!$D$34)/(Assumptions!$E$34-Assumptions!$D$34)*(Assumptions!$K$34-Assumptions!$J$34),IF(N24<=Assumptions!$F$34,Assumptions!$K$34+(N24-Assumptions!$E$34)/(Assumptions!$F$34-Assumptions!$E$34)*(Assumptions!$L$34-Assumptions!$K$34),IF(N24<=Assumptions!$G$34,Assumptions!$L$34+(N24-Assumptions!$F$34)/(Assumptions!$G$34-Assumptions!$F$34)*(Assumptions!$M$34-Assumptions!$L$34),Assumptions!$M$34)))))) -> 35.666667 | W24: =IF(S24="",PERCENTILE($S$6:$S$30,Assumptions!$B$36),S24) -> 15.96 | X24: =IF(T24="",PERCENTILE($T$6:$T$30,Assumptions!$B$36),T24) -> 2.1 | Y24: =IF(O24="",PERCENTILE($O$6:$O$30,Assumptions!$B$36),O24) -> 48 | Z24: =W24*Assumptions!$B$16+X24*Assumptions!$B$17 -> 9.03 | AA24: =U24*Assumptions!$B$18+V24*Assumptions!$B$19 -> 43.833333 | AB24: =AVERAGE(P24:R24) -> 27 | AC24: 0 | AD24: =MIN(100,Z24*Assumptions!$B$11+AA24*Assumptions!$B$12+Y24*Assumptions!$B$13+AB24*Assumptions!$B$14+AC24*Assumptions!$B$20) -> 29.809 | AE24: =MIN(1,SUMIFS(Network!$V$15:$V$30,Network!$D$15:$D$30,$A24,Network!$U$15:$U$30,1)) -> 1 | AF24: =MIN(1,SUMIFS(Network!$W$15:$W$30,Network!$D$15:$D$30,$A24,Network!$U$15:$U$30,1)) -> 0 | AG24: =MIN(1,SUMIFS(Network!$X$15:$X$30,Network!$D$15:$D$30,$A24,Network!$U$15:$U$30,1)) -> 0 | AH24: =AE24*Assumptions!$B$5+AF24*Assumptions!$B$6+AG24*Assumptions!$B$7 -> 624 | AI24: =AH24/Assumptions!$B$8 -> 0.4 | AJ24: =AH24/52 -> 12 | AK24: =AJ24*I24 -> 48 | AL24: =MIN(100,I24/Assumptions!$B$26*100) -> 11.111111 | AM24: =MIN(100,H24/Assumptions!$B$27*100) -> 33.333333 | AN24: =AI24*100*Assumptions!$B$23+AL24*Assumptions!$B$24+AM24*Assumptions!$B$25 -> 30 | AO24: =AN24*AD24/100 -> 8.9427 | AP24: =RANK(AO24,$AO$6:$AO$30)+COUNTIF($AO$6:AO24,AO24)-1 -> 24 | AQ24: =IF(AO24>=Assumptions!$B$39,"Critical",IF(AO24>=Assumptions!$B$40,"High",IF(AO24>=Assumptions!$B$41,"Elevated","Watch"))) -> Watch | AR24: =IF(AND(AN24>=Assumptions!$B$42,AD24>=Assumptions!$B$43),"Act now",IF(AN24>=Assumptions!$B$42,"Protect (structural)",IF(AD24>=Assumptions!$B$43,"Remediate supplier","Routine"))) -> Routine | AS24: =_xlfn.MAXIFS(Network!$T$5:$T$36,Network!$D$5:$D$36,$A24) -> 2 | AT24: =COUNT(K24:R24) -> 8 | AU24: =IF(AT24>=8,2,IF(AT24>=6,1,0)) -> 2 | AV24: =IF(OR(C24=1,LEFT(G24,9)="Confirmed"),1,0) -> 0 | AW24: =AS24+AU24+AV24 -> 4 | AX24: =IF(AW24>=Assumptions!$B$44,"High",IF(AW24>=Assumptions!$B$45,"Medium","Low")) -> Medium | AY24: =IF(OR(AQ24="Critical",AQ24="High"),IF(AX24="Low","VERIFY first – urgent sub-tier fact-find",IF(OR(AQ24="Critical",AV24=1),"ACT – mitigate now","CONFIRM sole-source status, then qualify alternate")),IF(AQ24="Elevated",IF(AX24="Low","VERIFY – add to N-tier survey","PLAN – qualify alternate in 90 days"),"MONITOR – quarterly review")) -> MONITOR – quarterly review | AZ24: =IF(K24&L24&O24<>"",IF(OR(K24="",L24="",O24=""),TRIM(IF(K24="","Current ratio; ","")&IF(L24="","Net debt/EBITDA; ","")&IF(O24="","Assurance gap","")),"—"),"Current ratio; Net debt/EBITDA; Assurance gap") -> —
A25: ORG-455 | B25: =INDEX(Data!$B$5:$B$34,MATCH($A25,Data!$A$5:$A$34,0)) -> Umber Silicon Carbide Ltd. | C25: 3 | D25: Tier-3: SiC wafers → IonPeak | E25: =INDEX(Data!$G$38:$G$67,MATCH($A25,Data!$A$38:$A$67,0)) -> SITE-158 | F25: =INDEX(Data!$I$38:$I$67,MATCH($A25,Data!$A$38:$A$67,0)) -> Z01 | G25: Presumed sole – not disclosed | H25: 2 | I25: 36 | J25: Assumption: tied to die requalification | K25: =IF(INDEX(Data!$C$5:$C$34,MATCH($A25,Data!$A$5:$A$34,0))="","",INDEX(Data!$C$5:$C$34,MATCH($A25,Data!$A$5:$A$34,0))) | L25: =IF(INDEX(Data!$D$5:$D$34,MATCH($A25,Data!$A$5:$A$34,0))="","",INDEX(Data!$D$5:$D$34,MATCH($A25,Data!$A$5:$A$34,0))) | M25: =IF(INDEX(Data!$E$5:$E$34,MATCH($A25,Data!$A$5:$A$34,0))="","",INDEX(Data!$E$5:$E$34,MATCH($A25,Data!$A$5:$A$34,0))) -> 80.5 | N25: =IF(INDEX(Data!$F$5:$F$34,MATCH($A25,Data!$A$5:$A$34,0))="","",INDEX(Data!$F$5:$F$34,MATCH($A25,Data!$A$5:$A$34,0))) -> -2.2 | O25: =IF(INDEX(Data!$G$5:$G$34,MATCH($A25,Data!$A$5:$A$34,0))="","",INDEX(Data!$G$5:$G$34,MATCH($A25,Data!$A$5:$A$34,0))) | P25: =IF(INDEX(Data!$H$5:$H$34,MATCH($A25,Data!$A$5:$A$34,0))="","",INDEX(Data!$H$5:$H$34,MATCH($A25,Data!$A$5:$A$34,0))) -> 82 | Q25: =IF(INDEX(Data!$I$5:$I$34,MATCH($A25,Data!$A$5:$A$34,0))="","",INDEX(Data!$I$5:$I$34,MATCH($A25,Data!$A$5:$A$34,0))) -> 76 | R25: =IF(INDEX(Data!$J$5:$J$34,MATCH($A25,Data!$A$5:$A$34,0))="","",INDEX(Data!$J$5:$J$34,MATCH($A25,Data!$A$5:$A$34,0))) -> 71 | S25: =IF(L25="","",IF(L25<=Assumptions!$B$31,Assumptions!$H$31,IF(L25<=Assumptions!$C$31,Assumptions!$H$31+(L25-Assumptions!$B$31)/(Assumptions!$C$31-Assumptions!$B$31)*(Assumptions!$I$31-Assumptions!$H$31),IF(L25<=Assumptions!$D$31,Assumptions!$I$31+(L25-Assumptions!$C$31)/(Assumptions!$D$31-Assumptions!$C$31)*(Assumptions!$J$31-Assumptions!$I$31),IF(L25<=Assumptions!$E$31,Assumptions!$J$31+(L25-Assumptions!$D$31)/(Assumptions!$E$31-Assumptions!$D$31)*(Assumptions!$K$31-Assumptions!$J$31),IF(L25<=Assumptions!$F$31,Assumptions!$K$31+(L25-Assumptions!$E$31)/(Assumptions!$F$31-Assumptions!$E$31)*(Assumptions!$L$31-Assumptions!$K$31),IF(L25<=Assumptions!$G$31,Assumptions!$L$31+(L25-Assumptions!$F$31)/(Assumptions!$G$31-Assumptions!$F$31)*(Assumptions!$M$31-Assumptions!$L$31),Assumptions!$M$31))))))) | T25: =IF(K25="","",IF(K25<=Assumptions!$B$32,Assumptions!$H$32,IF(K25<=Assumptions!$C$32,Assumptions!$H$32+(K25-Assumptions!$B$32)/(Assumptions!$C$32-Assumptions!$B$32)*(Assumptions!$I$32-Assumptions!$H$32),IF(K25<=Assumptions!$D$32,Assumptions!$I$32+(K25-Assumptions!$C$32)/(Assumptions!$D$32-Assumptions!$C$32)*(Assumptions!$J$32-Assumptions!$I$32),IF(K25<=Assumptions!$E$32,Assumptions!$J$32+(K25-Assumptions!$D$32)/(Assumptions!$E$32-Assumptions!$D$32)*(Assumptions!$K$32-Assumptions!$J$32),IF(K25<=Assumptions!$F$32,Assumptions!$K$32+(K25-Assumptions!$E$32)/(Assumptions!$F$32-Assumptions!$E$32)*(Assumptions!$L$32-Assumptions!$K$32),IF(K25<=Assumptions!$G$32,Assumptions!$L$32+(K25-Assumptions!$F$32)/(Assumptions!$G$32-Assumptions!$F$32)*(Assumptions!$M$32-Assumptions!$L$32),Assumptions!$M$32))))))) | U25: =IF(M25<=Assumptions!$B$33,Assumptions!$H$33,IF(M25<=Assumptions!$C$33,Assumptions!$H$33+(M25-Assumptions!$B$33)/(Assumptions!$C$33-Assumptions!$B$33)*(Assumptions!$I$33-Assumptions!$H$33),IF(M25<=Assumptions!$D$33,Assumptions!$I$33+(M25-Assumptions!$C$33)/(Assumptions!$D$33-Assumptions!$C$33)*(Assumptions!$J$33-Assumptions!$I$33),IF(M25<=Assumptions!$E$33,Assumptions!$J$33+(M25-Assumptions!$D$33)/(Assumptions!$E$33-Assumptions!$D$33)*(Assumptions!$K$33-Assumptions!$J$33),IF(M25<=Assumptions!$F$33,Assumptions!$K$33+(M25-Assumptions!$E$33)/(Assumptions!$F$33-Assumptions!$E$33)*(Assumptions!$L$33-Assumptions!$K$33),IF(M25<=Assumptions!$G$33,Assumptions!$L$33+(M25-Assumptions!$F$33)/(Assumptions!$G$33-Assumptions!$F$33)*(Assumptions!$M$33-Assumptions!$L$33),Assumptions!$M$33)))))) -> 72.5 | V25: =IF(N25<=Assumptions!$B$34,Assumptions!$H$34,IF(N25<=Assumptions!$C$34,Assumptions!$H$34+(N25-Assumptions!$B$34)/(Assumptions!$C$34-Assumptions!$B$34)*(Assumptions!$I$34-Assumptions!$H$34),IF(N25<=Assumptions!$D$34,Assumptions!$I$34+(N25-Assumptions!$C$34)/(Assumptions!$D$34-Assumptions!$C$34)*(Assumptions!$J$34-Assumptions!$I$34),IF(N25<=Assumptions!$E$34,Assumptions!$J$34+(N25-Assumptions!$D$34)/(Assumptions!$E$34-Assumptions!$D$34)*(Assumptions!$K$34-Assumptions!$J$34),IF(N25<=Assumptions!$F$34,Assumptions!$K$34+(N25-Assumptions!$E$34)/(Assumptions!$F$34-Assumptions!$E$34)*(Assumptions!$L$34-Assumptions!$K$34),IF(N25<=Assumptions!$G$34,Assumptions!$L$34+(N25-Assumptions!$F$34)/(Assumptions!$G$34-Assumptions!$F$34)*(Assumptions!$M$34-Assumptions!$L$34),Assumptions!$M$34)))))) -> 36.333333 | W25: =IF(S25="",PERCENTILE($S$6:$S$30,Assumptions!$B$36),S25) -> 44.666667 | X25: =IF(T25="",PERCENTILE($T$6:$T$30,Assumptions!$B$36),T25) -> 28.65 | Y25: =IF(O25="",PERCENTILE($O$6:$O$30,Assumptions!$B$36),O25) -> 55.5 | Z25: =W25*Assumptions!$B$16+X25*Assumptions!$B$17 -> 36.658333 | AA25: =U25*Assumptions!$B$18+V25*Assumptions!$B$19 -> 54.416667 | AB25: =AVERAGE(P25:R25) -> 76.333333 | AC25: 0 | AD25: =MIN(100,Z25*Assumptions!$B$11+AA25*Assumptions!$B$12+Y25*Assumptions!$B$13+AB25*Assumptions!$B$14+AC25*Assumptions!$B$20) -> 54.730833 | AE25: =MIN(1,SUMIFS(Network!$V$31:$V$36,Network!$D$31:$D$36,$A25,Network!$U$31:$U$36,1)) -> 1 | AF25: =MIN(1,SUMIFS(Network!$W$31:$W$36,Network!$D$31:$D$36,$A25,Network!$U$31:$U$36,1)) -> 1 | AG25: =MIN(1,SUMIFS(Network!$X$31:$X$36,Network!$D$31:$D$36,$A25,Network!$U$31:$U$36,1)) -> 1 | AH25: =AE25*Assumptions!$B$5+AF25*Assumptions!$B$6+AG25*Assumptions!$B$7 -> 1560 | AI25: =AH25/Assumptions!$B$8 -> 1 | AJ25: =AH25/52 -> 30 | AK25: =AJ25*I25 -> 1080 | AL25: =MIN(100,I25/Assumptions!$B$26*100) -> 100 | AM25: =MIN(100,H25/Assumptions!$B$27*100) -> 66.666667 | AN25: =AI25*100*Assumptions!$B$23+AL25*Assumptions!$B$24+AM25*Assumptions!$B$25 -> 93.333333 | AO25: =AN25*AD25/100 -> 51.082111 | AP25: =RANK(AO25,$AO$6:$AO$30)+COUNTIF($AO$6:AO25,AO25)-1 -> 1 | AQ25: =IF(AO25>=Assumptions!$B$39,"Critical",IF(AO25>=Assumptions!$B$40,"High",IF(AO25>=Assumptions!$B$41,"Elevated","Watch"))) -> Critical | AR25: =IF(AND(AN25>=Assumptions!$B$42,AD25>=Assumptions!$B$43),"Act now",IF(AN25>=Assumptions!$B$42,"Protect (structural)",IF(AD25>=Assumptions!$B$43,"Remediate supplier","Routine"))) -> Act now | AS25: =_xlfn.MAXIFS(Network!$T$5:$T$36,Network!$D$5:$D$36,$A25) -> 2 | AT25: =COUNT(K25:R25) -> 5 | AU25: =IF(AT25>=8,2,IF(AT25>=6,1,0)) -> 0 | AV25: =IF(OR(C25=1,LEFT(G25,9)="Confirmed"),1,0) -> 0 | AW25: =AS25+AU25+AV25 -> 2 | AX25: =IF(AW25>=Assumptions!$B$44,"High",IF(AW25>=Assumptions!$B$45,"Medium","Low")) -> Low | AY25: =IF(OR(AQ25="Critical",AQ25="High"),IF(AX25="Low","VERIFY first – urgent sub-tier fact-find",IF(OR(AQ25="Critical",AV25=1),"ACT – mitigate now","CONFIRM sole-source status, then qualify alternate")),IF(AQ25="Elevated",IF(AX25="Low","VERIFY – add to N-tier survey","PLAN – qualify alternate in 90 days"),"MONITOR – quarterly review")) -> VERIFY first – urgent sub-tier fact-find | AZ25: =IF(K25&L25&O25<>"",IF(OR(K25="",L25="",O25=""),TRIM(IF(K25="","Current ratio; ","")&IF(L25="","Net debt/EBITDA; ","")&IF(O25="","Assurance gap","")),"—"),"Current ratio; Net debt/EBITDA; Assurance gap") -> Current ratio; Net debt/EBITDA; Assurance gap
A26: ORG-736 | B26: =INDEX(Data!$B$5:$B$34,MATCH($A26,Data!$A$5:$A$34,0)) -> Verdant Process Gases Ltd. | C26: 3 | D26: Tier-3: process gases → IonPeak (inferred) | E26: =INDEX(Data!$G$38:$G$67,MATCH($A26,Data!$A$38:$A$67,0)) -> SITE-165 | F26: =INDEX(Data!$I$38:$I$67,MATCH($A26,Data!$A$38:$A$67,0)) -> Z01 | G26: Inferred link only | H26: 2 | I26: 8 | J26: Assumption: fab gas-supplier switch | K26: =IF(INDEX(Data!$C$5:$C$34,MATCH($A26,Data!$A$5:$A$34,0))="","",INDEX(Data!$C$5:$C$34,MATCH($A26,Data!$A$5:$A$34,0))) | L26: =IF(INDEX(Data!$D$5:$D$34,MATCH($A26,Data!$A$5:$A$34,0))="","",INDEX(Data!$D$5:$D$34,MATCH($A26,Data!$A$5:$A$34,0))) | M26: =IF(INDEX(Data!$E$5:$E$34,MATCH($A26,Data!$A$5:$A$34,0))="","",INDEX(Data!$E$5:$E$34,MATCH($A26,Data!$A$5:$A$34,0))) -> 81.9 | N26: =IF(INDEX(Data!$F$5:$F$34,MATCH($A26,Data!$A$5:$A$34,0))="","",INDEX(Data!$F$5:$F$34,MATCH($A26,Data!$A$5:$A$34,0))) -> -0.9 | O26: =IF(INDEX(Data!$G$5:$G$34,MATCH($A26,Data!$A$5:$A$34,0))="","",INDEX(Data!$G$5:$G$34,MATCH($A26,Data!$A$5:$A$34,0))) | P26: =IF(INDEX(Data!$H$5:$H$34,MATCH($A26,Data!$A$5:$A$34,0))="","",INDEX(Data!$H$5:$H$34,MATCH($A26,Data!$A$5:$A$34,0))) -> 82 | Q26: =IF(INDEX(Data!$I$5:$I$34,MATCH($A26,Data!$A$5:$A$34,0))="","",INDEX(Data!$I$5:$I$34,MATCH($A26,Data!$A$5:$A$34,0))) -> 76 | R26: =IF(INDEX(Data!$J$5:$J$34,MATCH($A26,Data!$A$5:$A$34,0))="","",INDEX(Data!$J$5:$J$34,MATCH($A26,Data!$A$5:$A$34,0))) -> 71 | S26: =IF(L26="","",IF(L26<=Assumptions!$B$31,Assumptions!$H$31,IF(L26<=Assumptions!$C$31,Assumptions!$H$31+(L26-Assumptions!$B$31)/(Assumptions!$C$31-Assumptions!$B$31)*(Assumptions!$I$31-Assumptions!$H$31),IF(L26<=Assumptions!$D$31,Assumptions!$I$31+(L26-Assumptions!$C$31)/(Assumptions!$D$31-Assumptions!$C$31)*(Assumptions!$J$31-Assumptions!$I$31),IF(L26<=Assumptions!$E$31,Assumptions!$J$31+(L26-Assumptions!$D$31)/(Assumptions!$E$31-Assumptions!$D$31)*(Assumptions!$K$31-Assumptions!$J$31),IF(L26<=Assumptions!$F$31,Assumptions!$K$31+(L26-Assumptions!$E$31)/(Assumptions!$F$31-Assumptions!$E$31)*(Assumptions!$L$31-Assumptions!$K$31),IF(L26<=Assumptions!$G$31,Assumptions!$L$31+(L26-Assumptions!$F$31)/(Assumptions!$G$31-Assumptions!$F$31)*(Assumptions!$M$31-Assumptions!$L$31),Assumptions!$M$31))))))) | T26: =IF(K26="","",IF(K26<=Assumptions!$B$32,Assumptions!$H$32,IF(K26<=Assumptions!$C$32,Assumptions!$H$32+(K26-Assumptions!$B$32)/(Assumptions!$C$32-Assumptions!$B$32)*(Assumptions!$I$32-Assumptions!$H$32),IF(K26<=Assumptions!$D$32,Assumptions!$I$32+(K26-Assumptions!$C$32)/(Assumptions!$D$32-Assumptions!$C$32)*(Assumptions!$J$32-Assumptions!$I$32),IF(K26<=Assumptions!$E$32,Assumptions!$J$32+(K26-Assumptions!$D$32)/(Assumptions!$E$32-Assumptions!$D$32)*(Assumptions!$K$32-Assumptions!$J$32),IF(K26<=Assumptions!$F$32,Assumptions!$K$32+(K26-Assumptions!$E$32)/(Assumptions!$F$32-Assumptions!$E$32)*(Assumptions!$L$32-Assumptions!$K$32),IF(K26<=Assumptions!$G$32,Assumptions!$L$32+(K26-Assumptions!$F$32)/(Assumptions!$G$32-Assumptions!$F$32)*(Assumptions!$M$32-Assumptions!$L$32),Assumptions!$M$32))))))) | U26: =IF(M26<=Assumptions!$B$33,Assumptions!$H$33,IF(M26<=Assumptions!$C$33,Assumptions!$H$33+(M26-Assumptions!$B$33)/(Assumptions!$C$33-Assumptions!$B$33)*(Assumptions!$I$33-Assumptions!$H$33),IF(M26<=Assumptions!$D$33,Assumptions!$I$33+(M26-Assumptions!$C$33)/(Assumptions!$D$33-Assumptions!$C$33)*(Assumptions!$J$33-Assumptions!$I$33),IF(M26<=Assumptions!$E$33,Assumptions!$J$33+(M26-Assumptions!$D$33)/(Assumptions!$E$33-Assumptions!$D$33)*(Assumptions!$K$33-Assumptions!$J$33),IF(M26<=Assumptions!$F$33,Assumptions!$K$33+(M26-Assumptions!$E$33)/(Assumptions!$F$33-Assumptions!$E$33)*(Assumptions!$L$33-Assumptions!$K$33),IF(M26<=Assumptions!$G$33,Assumptions!$L$33+(M26-Assumptions!$F$33)/(Assumptions!$G$33-Assumptions!$F$33)*(Assumptions!$M$33-Assumptions!$L$33),Assumptions!$M$33)))))) -> 65.5 | V26: =IF(N26<=Assumptions!$B$34,Assumptions!$H$34,IF(N26<=Assumptions!$C$34,Assumptions!$H$34+(N26-Assumptions!$B$34)/(Assumptions!$C$34-Assumptions!$B$34)*(Assumptions!$I$34-Assumptions!$H$34),IF(N26<=Assumptions!$D$34,Assumptions!$I$34+(N26-Assumptions!$C$34)/(Assumptions!$D$34-Assumptions!$C$34)*(Assumptions!$J$34-Assumptions!$I$34),IF(N26<=Assumptions!$E$34,Assumptions!$J$34+(N26-Assumptions!$D$34)/(Assumptions!$E$34-Assumptions!$D$34)*(Assumptions!$K$34-Assumptions!$J$34),IF(N26<=Assumptions!$F$34,Assumptions!$K$34+(N26-Assumptions!$E$34)/(Assumptions!$F$34-Assumptions!$E$34)*(Assumptions!$L$34-Assumptions!$K$34),IF(N26<=Assumptions!$G$34,Assumptions!$L$34+(N26-Assumptions!$F$34)/(Assumptions!$G$34-Assumptions!$F$34)*(Assumptions!$M$34-Assumptions!$L$34),Assumptions!$M$34)))))) -> 26.75 | W26: =IF(S26="",PERCENTILE($S$6:$S$30,Assumptions!$B$36),S26) -> 44.666667 | X26: =IF(T26="",PERCENTILE($T$6:$T$30,Assumptions!$B$36),T26) -> 28.65 | Y26: =IF(O26="",PERCENTILE($O$6:$O$30,Assumptions!$B$36),O26) -> 55.5 | Z26: =W26*Assumptions!$B$16+X26*Assumptions!$B$17 -> 36.658333 | AA26: =U26*Assumptions!$B$18+V26*Assumptions!$B$19 -> 46.125 | AB26: =AVERAGE(P26:R26) -> 76.333333 | AC26: 0 | AD26: =MIN(100,Z26*Assumptions!$B$11+AA26*Assumptions!$B$12+Y26*Assumptions!$B$13+AB26*Assumptions!$B$14+AC26*Assumptions!$B$20) -> 52.243333 | AE26: =MIN(1,SUMIFS(Network!$V$31:$V$36,Network!$D$31:$D$36,$A26,Network!$U$31:$U$36,1)) -> 1 | AF26: =MIN(1,SUMIFS(Network!$W$31:$W$36,Network!$D$31:$D$36,$A26,Network!$U$31:$U$36,1)) -> 1 | AG26: =MIN(1,SUMIFS(Network!$X$31:$X$36,Network!$D$31:$D$36,$A26,Network!$U$31:$U$36,1)) -> 1 | AH26: =AE26*Assumptions!$B$5+AF26*Assumptions!$B$6+AG26*Assumptions!$B$7 -> 1560 | AI26: =AH26/Assumptions!$B$8 -> 1 | AJ26: =AH26/52 -> 30 | AK26: =AJ26*I26 -> 240 | AL26: =MIN(100,I26/Assumptions!$B$26*100) -> 22.222222 | AM26: =MIN(100,H26/Assumptions!$B$27*100) -> 66.666667 | AN26: =AI26*100*Assumptions!$B$23+AL26*Assumptions!$B$24+AM26*Assumptions!$B$25 -> 70 | AO26: =AN26*AD26/100 -> 36.570333 | AP26: =RANK(AO26,$AO$6:$AO$30)+COUNTIF($AO$6:AO26,AO26)-1 -> 5 | AQ26: =IF(AO26>=Assumptions!$B$39,"Critical",IF(AO26>=Assumptions!$B$40,"High",IF(AO26>=Assumptions!$B$41,"Elevated","Watch"))) -> High | AR26: =IF(AND(AN26>=Assumptions!$B$42,AD26>=Assumptions!$B$43),"Act now",IF(AN26>=Assumptions!$B$42,"Protect (structural)",IF(AD26>=Assumptions!$B$43,"Remediate supplier","Routine"))) -> Act now | AS26: =_xlfn.MAXIFS(Network!$T$5:$T$36,Network!$D$5:$D$36,$A26) -> 1 | AT26: =COUNT(K26:R26) -> 5 | AU26: =IF(AT26>=8,2,IF(AT26>=6,1,0)) -> 0 | AV26: =IF(OR(C26=1,LEFT(G26,9)="Confirmed"),1,0) -> 0 | AW26: =AS26+AU26+AV26 -> 1 | AX26: =IF(AW26>=Assumptions!$B$44,"High",IF(AW26>=Assumptions!$B$45,"Medium","Low")) -> Low | AY26: =IF(OR(AQ26="Critical",AQ26="High"),IF(AX26="Low","VERIFY first – urgent sub-tier fact-find",IF(OR(AQ26="Critical",AV26=1),"ACT – mitigate now","CONFIRM sole-source status, then qualify alternate")),IF(AQ26="Elevated",IF(AX26="Low","VERIFY – add to N-tier survey","PLAN – qualify alternate in 90 days"),"MONITOR – quarterly review")) -> VERIFY first – urgent sub-tier fact-find | AZ26: =IF(K26&L26&O26<>"",IF(OR(K26="",L26="",O26=""),TRIM(IF(K26="","Current ratio; ","")&IF(L26="","Net debt/EBITDA; ","")&IF(O26="","Assurance gap","")),"—"),"Current ratio; Net debt/EBITDA; Assurance gap") -> Current ratio; Net debt/EBITDA; Assurance gap
A27: ORG-520 | B27: =INDEX(Data!$B$5:$B$34,MATCH($A27,Data!$A$5:$A$34,0)) -> Yarrow Specialty Minerals Ltd. | C27: 3 | D27: Tier-3: specialty minerals → Orion | E27: =INDEX(Data!$G$38:$G$67,MATCH($A27,Data!$A$38:$A$67,0)) -> SITE-186 | F27: =INDEX(Data!$I$38:$I$67,MATCH($A27,Data!$A$38:$A$67,0)) -> Z08 | G27: Presumed sole – not disclosed | H27: 2 | I27: 12 | J27: Assumption | K27: =IF(INDEX(Data!$C$5:$C$34,MATCH($A27,Data!$A$5:$A$34,0))="","",INDEX(Data!$C$5:$C$34,MATCH($A27,Data!$A$5:$A$34,0))) | L27: =IF(INDEX(Data!$D$5:$D$34,MATCH($A27,Data!$A$5:$A$34,0))="","",INDEX(Data!$D$5:$D$34,MATCH($A27,Data!$A$5:$A$34,0))) | M27: =IF(INDEX(Data!$E$5:$E$34,MATCH($A27,Data!$A$5:$A$34,0))="","",INDEX(Data!$E$5:$E$34,MATCH($A27,Data!$A$5:$A$34,0))) -> 90.1 | N27: =IF(INDEX(Data!$F$5:$F$34,MATCH($A27,Data!$A$5:$A$34,0))="","",INDEX(Data!$F$5:$F$34,MATCH($A27,Data!$A$5:$A$34,0))) -> -1.2 | O27: =IF(INDEX(Data!$G$5:$G$34,MATCH($A27,Data!$A$5:$A$34,0))="","",INDEX(Data!$G$5:$G$34,MATCH($A27,Data!$A$5:$A$34,0))) | P27: =IF(INDEX(Data!$H$5:$H$34,MATCH($A27,Data!$A$5:$A$34,0))="","",INDEX(Data!$H$5:$H$34,MATCH($A27,Data!$A$5:$A$34,0))) -> 39 | Q27: =IF(INDEX(Data!$I$5:$I$34,MATCH($A27,Data!$A$5:$A$34,0))="","",INDEX(Data!$I$5:$I$34,MATCH($A27,Data!$A$5:$A$34,0))) -> 47 | R27: =IF(INDEX(Data!$J$5:$J$34,MATCH($A27,Data!$A$5:$A$34,0))="","",INDEX(Data!$J$5:$J$34,MATCH($A27,Data!$A$5:$A$34,0))) -> 41 | S27: =IF(L27="","",IF(L27<=Assumptions!$B$31,Assumptions!$H$31,IF(L27<=Assumptions!$C$31,Assumptions!$H$31+(L27-Assumptions!$B$31)/(Assumptions!$C$31-Assumptions!$B$31)*(Assumptions!$I$31-Assumptions!$H$31),IF(L27<=Assumptions!$D$31,Assumptions!$I$31+(L27-Assumptions!$C$31)/(Assumptions!$D$31-Assumptions!$C$31)*(Assumptions!$J$31-Assumptions!$I$31),IF(L27<=Assumptions!$E$31,Assumptions!$J$31+(L27-Assumptions!$D$31)/(Assumptions!$E$31-Assumptions!$D$31)*(Assumptions!$K$31-Assumptions!$J$31),IF(L27<=Assumptions!$F$31,Assumptions!$K$31+(L27-Assumptions!$E$31)/(Assumptions!$F$31-Assumptions!$E$31)*(Assumptions!$L$31-Assumptions!$K$31),IF(L27<=Assumptions!$G$31,Assumptions!$L$31+(L27-Assumptions!$F$31)/(Assumptions!$G$31-Assumptions!$F$31)*(Assumptions!$M$31-Assumptions!$L$31),Assumptions!$M$31))))))) | T27: =IF(K27="","",IF(K27<=Assumptions!$B$32,Assumptions!$H$32,IF(K27<=Assumptions!$C$32,Assumptions!$H$32+(K27-Assumptions!$B$32)/(Assumptions!$C$32-Assumptions!$B$32)*(Assumptions!$I$32-Assumptions!$H$32),IF(K27<=Assumptions!$D$32,Assumptions!$I$32+(K27-Assumptions!$C$32)/(Assumptions!$D$32-Assumptions!$C$32)*(Assumptions!$J$32-Assumptions!$I$32),IF(K27<=Assumptions!$E$32,Assumptions!$J$32+(K27-Assumptions!$D$32)/(Assumptions!$E$32-Assumptions!$D$32)*(Assumptions!$K$32-Assumptions!$J$32),IF(K27<=Assumptions!$F$32,Assumptions!$K$32+(K27-Assumptions!$E$32)/(Assumptions!$F$32-Assumptions!$E$32)*(Assumptions!$L$32-Assumptions!$K$32),IF(K27<=Assumptions!$G$32,Assumptions!$L$32+(K27-Assumptions!$F$32)/(Assumptions!$G$32-Assumptions!$F$32)*(Assumptions!$M$32-Assumptions!$L$32),Assumptions!$M$32))))))) | U27: =IF(M27<=Assumptions!$B$33,Assumptions!$H$33,IF(M27<=Assumptions!$C$33,Assumptions!$H$33+(M27-Assumptions!$B$33)/(Assumptions!$C$33-Assumptions!$B$33)*(Assumptions!$I$33-Assumptions!$H$33),IF(M27<=Assumptions!$D$33,Assumptions!$I$33+(M27-Assumptions!$C$33)/(Assumptions!$D$33-Assumptions!$C$33)*(Assumptions!$J$33-Assumptions!$I$33),IF(M27<=Assumptions!$E$33,Assumptions!$J$33+(M27-Assumptions!$D$33)/(Assumptions!$E$33-Assumptions!$D$33)*(Assumptions!$K$33-Assumptions!$J$33),IF(M27<=Assumptions!$F$33,Assumptions!$K$33+(M27-Assumptions!$E$33)/(Assumptions!$F$33-Assumptions!$E$33)*(Assumptions!$L$33-Assumptions!$K$33),IF(M27<=Assumptions!$G$33,Assumptions!$L$33+(M27-Assumptions!$F$33)/(Assumptions!$G$33-Assumptions!$F$33)*(Assumptions!$M$33-Assumptions!$L$33),Assumptions!$M$33)))))) -> 24.5 | V27: =IF(N27<=Assumptions!$B$34,Assumptions!$H$34,IF(N27<=Assumptions!$C$34,Assumptions!$H$34+(N27-Assumptions!$B$34)/(Assumptions!$C$34-Assumptions!$B$34)*(Assumptions!$I$34-Assumptions!$H$34),IF(N27<=Assumptions!$D$34,Assumptions!$I$34+(N27-Assumptions!$C$34)/(Assumptions!$D$34-Assumptions!$C$34)*(Assumptions!$J$34-Assumptions!$I$34),IF(N27<=Assumptions!$E$34,Assumptions!$J$34+(N27-Assumptions!$D$34)/(Assumptions!$E$34-Assumptions!$D$34)*(Assumptions!$K$34-Assumptions!$J$34),IF(N27<=Assumptions!$F$34,Assumptions!$K$34+(N27-Assumptions!$E$34)/(Assumptions!$F$34-Assumptions!$E$34)*(Assumptions!$L$34-Assumptions!$K$34),IF(N27<=Assumptions!$G$34,Assumptions!$L$34+(N27-Assumptions!$F$34)/(Assumptions!$G$34-Assumptions!$F$34)*(Assumptions!$M$34-Assumptions!$L$34),Assumptions!$M$34)))))) -> 29 | W27: =IF(S27="",PERCENTILE($S$6:$S$30,Assumptions!$B$36),S27) -> 44.666667 | X27: =IF(T27="",PERCENTILE($T$6:$T$30,Assumptions!$B$36),T27) -> 28.65 | Y27: =IF(O27="",PERCENTILE($O$6:$O$30,Assumptions!$B$36),O27) -> 55.5 | Z27: =W27*Assumptions!$B$16+X27*Assumptions!$B$17 -> 36.658333 | AA27: =U27*Assumptions!$B$18+V27*Assumptions!$B$19 -> 26.75 | AB27: =AVERAGE(P27:R27) -> 42.333333 | AC27: 0 | AD27: =MIN(100,Z27*Assumptions!$B$11+AA27*Assumptions!$B$12+Y27*Assumptions!$B$13+AB27*Assumptions!$B$14+AC27*Assumptions!$B$20) -> 37.930833 | AE27: =MIN(1,SUMIFS(Network!$V$31:$V$36,Network!$D$31:$D$36,$A27,Network!$U$31:$U$36,1)) -> 1 | AF27: =MIN(1,SUMIFS(Network!$W$31:$W$36,Network!$D$31:$D$36,$A27,Network!$U$31:$U$36,1)) -> 1 | AG27: =MIN(1,SUMIFS(Network!$X$31:$X$36,Network!$D$31:$D$36,$A27,Network!$U$31:$U$36,1)) -> 1 | AH27: =AE27*Assumptions!$B$5+AF27*Assumptions!$B$6+AG27*Assumptions!$B$7 -> 1560 | AI27: =AH27/Assumptions!$B$8 -> 1 | AJ27: =AH27/52 -> 30 | AK27: =AJ27*I27 -> 360 | AL27: =MIN(100,I27/Assumptions!$B$26*100) -> 33.333333 | AM27: =MIN(100,H27/Assumptions!$B$27*100) -> 66.666667 | AN27: =AI27*100*Assumptions!$B$23+AL27*Assumptions!$B$24+AM27*Assumptions!$B$25 -> 73.333333 | AO27: =AN27*AD27/100 -> 27.815944 | AP27: =RANK(AO27,$AO$6:$AO$30)+COUNTIF($AO$6:AO27,AO27)-1 -> 11 | AQ27: =IF(AO27>=Assumptions!$B$39,"Critical",IF(AO27>=Assumptions!$B$40,"High",IF(AO27>=Assumptions!$B$41,"Elevated","Watch"))) -> Elevated | AR27: =IF(AND(AN27>=Assumptions!$B$42,AD27>=Assumptions!$B$43),"Act now",IF(AN27>=Assumptions!$B$42,"Protect (structural)",IF(AD27>=Assumptions!$B$43,"Remediate supplier","Routine"))) -> Protect (structural) | AS27: =_xlfn.MAXIFS(Network!$T$5:$T$36,Network!$D$5:$D$36,$A27) -> 2 | AT27: =COUNT(K27:R27) -> 5 | AU27: =IF(AT27>=8,2,IF(AT27>=6,1,0)) -> 0 | AV27: =IF(OR(C27=1,LEFT(G27,9)="Confirmed"),1,0) -> 0 | AW27: =AS27+AU27+AV27 -> 2 | AX27: =IF(AW27>=Assumptions!$B$44,"High",IF(AW27>=Assumptions!$B$45,"Medium","Low")) -> Low | AY27: =IF(OR(AQ27="Critical",AQ27="High"),IF(AX27="Low","VERIFY first – urgent sub-tier fact-find",IF(OR(AQ27="Critical",AV27=1),"ACT – mitigate now","CONFIRM sole-source status, then qualify alternate")),IF(AQ27="Elevated",IF(AX27="Low","VERIFY – add to N-tier survey","PLAN – qualify alternate in 90 days"),"MONITOR – quarterly review")) -> VERIFY – add to N-tier survey | AZ27: =IF(K27&L27&O27<>"",IF(OR(K27="",L27="",O27=""),TRIM(IF(K27="","Current ratio; ","")&IF(L27="","Net debt/EBITDA; ","")&IF(O27="","Assurance gap","")),"—"),"Current ratio; Net debt/EBITDA; Assurance gap") -> Current ratio; Net debt/EBITDA; Assurance gap
A28: ORG-873 | B28: =INDEX(Data!$B$5:$B$34,MATCH($A28,Data!$A$5:$A$34,0)) -> Warden Copper Foil Ltd. | C28: 3 | D28: Tier-3: copper foil → Jade | E28: =INDEX(Data!$G$38:$G$67,MATCH($A28,Data!$A$38:$A$67,0)) -> SITE-172 | F28: =INDEX(Data!$I$38:$I$67,MATCH($A28,Data!$A$38:$A$67,0)) -> Z06 | G28: Presumed sole – not disclosed | H28: 3 | I28: 8 | J28: Assumption | K28: =IF(INDEX(Data!$C$5:$C$34,MATCH($A28,Data!$A$5:$A$34,0))="","",INDEX(Data!$C$5:$C$34,MATCH($A28,Data!$A$5:$A$34,0))) | L28: =IF(INDEX(Data!$D$5:$D$34,MATCH($A28,Data!$A$5:$A$34,0))="","",INDEX(Data!$D$5:$D$34,MATCH($A28,Data!$A$5:$A$34,0))) | M28: =IF(INDEX(Data!$E$5:$E$34,MATCH($A28,Data!$A$5:$A$34,0))="","",INDEX(Data!$E$5:$E$34,MATCH($A28,Data!$A$5:$A$34,0))) -> 87.4 | N28: =IF(INDEX(Data!$F$5:$F$34,MATCH($A28,Data!$A$5:$A$34,0))="","",INDEX(Data!$F$5:$F$34,MATCH($A28,Data!$A$5:$A$34,0))) -> 1.8 | O28: =IF(INDEX(Data!$G$5:$G$34,MATCH($A28,Data!$A$5:$A$34,0))="","",INDEX(Data!$G$5:$G$34,MATCH($A28,Data!$A$5:$A$34,0))) | P28: =IF(INDEX(Data!$H$5:$H$34,MATCH($A28,Data!$A$5:$A$34,0))="","",INDEX(Data!$H$5:$H$34,MATCH($A28,Data!$A$5:$A$34,0))) -> 67 | Q28: =IF(INDEX(Data!$I$5:$I$34,MATCH($A28,Data!$A$5:$A$34,0))="","",INDEX(Data!$I$5:$I$34,MATCH($A28,Data!$A$5:$A$34,0))) -> 59 | R28: =IF(INDEX(Data!$J$5:$J$34,MATCH($A28,Data!$A$5:$A$34,0))="","",INDEX(Data!$J$5:$J$34,MATCH($A28,Data!$A$5:$A$34,0))) -> 54 | S28: =IF(L28="","",IF(L28<=Assumptions!$B$31,Assumptions!$H$31,IF(L28<=Assumptions!$C$31,Assumptions!$H$31+(L28-Assumptions!$B$31)/(Assumptions!$C$31-Assumptions!$B$31)*(Assumptions!$I$31-Assumptions!$H$31),IF(L28<=Assumptions!$D$31,Assumptions!$I$31+(L28-Assumptions!$C$31)/(Assumptions!$D$31-Assumptions!$C$31)*(Assumptions!$J$31-Assumptions!$I$31),IF(L28<=Assumptions!$E$31,Assumptions!$J$31+(L28-Assumptions!$D$31)/(Assumptions!$E$31-Assumptions!$D$31)*(Assumptions!$K$31-Assumptions!$J$31),IF(L28<=Assumptions!$F$31,Assumptions!$K$31+(L28-Assumptions!$E$31)/(Assumptions!$F$31-Assumptions!$E$31)*(Assumptions!$L$31-Assumptions!$K$31),IF(L28<=Assumptions!$G$31,Assumptions!$L$31+(L28-Assumptions!$F$31)/(Assumptions!$G$31-Assumptions!$F$31)*(Assumptions!$M$31-Assumptions!$L$31),Assumptions!$M$31))))))) | T28: =IF(K28="","",IF(K28<=Assumptions!$B$32,Assumptions!$H$32,IF(K28<=Assumptions!$C$32,Assumptions!$H$32+(K28-Assumptions!$B$32)/(Assumptions!$C$32-Assumptions!$B$32)*(Assumptions!$I$32-Assumptions!$H$32),IF(K28<=Assumptions!$D$32,Assumptions!$I$32+(K28-Assumptions!$C$32)/(Assumptions!$D$32-Assumptions!$C$32)*(Assumptions!$J$32-Assumptions!$I$32),IF(K28<=Assumptions!$E$32,Assumptions!$J$32+(K28-Assumptions!$D$32)/(Assumptions!$E$32-Assumptions!$D$32)*(Assumptions!$K$32-Assumptions!$J$32),IF(K28<=Assumptions!$F$32,Assumptions!$K$32+(K28-Assumptions!$E$32)/(Assumptions!$F$32-Assumptions!$E$32)*(Assumptions!$L$32-Assumptions!$K$32),IF(K28<=Assumptions!$G$32,Assumptions!$L$32+(K28-Assumptions!$F$32)/(Assumptions!$G$32-Assumptions!$F$32)*(Assumptions!$M$32-Assumptions!$L$32),Assumptions!$M$32))))))) | U28: =IF(M28<=Assumptions!$B$33,Assumptions!$H$33,IF(M28<=Assumptions!$C$33,Assumptions!$H$33+(M28-Assumptions!$B$33)/(Assumptions!$C$33-Assumptions!$B$33)*(Assumptions!$I$33-Assumptions!$H$33),IF(M28<=Assumptions!$D$33,Assumptions!$I$33+(M28-Assumptions!$C$33)/(Assumptions!$D$33-Assumptions!$C$33)*(Assumptions!$J$33-Assumptions!$I$33),IF(M28<=Assumptions!$E$33,Assumptions!$J$33+(M28-Assumptions!$D$33)/(Assumptions!$E$33-Assumptions!$D$33)*(Assumptions!$K$33-Assumptions!$J$33),IF(M28<=Assumptions!$F$33,Assumptions!$K$33+(M28-Assumptions!$E$33)/(Assumptions!$F$33-Assumptions!$E$33)*(Assumptions!$L$33-Assumptions!$K$33),IF(M28<=Assumptions!$G$33,Assumptions!$L$33+(M28-Assumptions!$F$33)/(Assumptions!$G$33-Assumptions!$F$33)*(Assumptions!$M$33-Assumptions!$L$33),Assumptions!$M$33)))))) -> 38 | V28: =IF(N28<=Assumptions!$B$34,Assumptions!$H$34,IF(N28<=Assumptions!$C$34,Assumptions!$H$34+(N28-Assumptions!$B$34)/(Assumptions!$C$34-Assumptions!$B$34)*(Assumptions!$I$34-Assumptions!$H$34),IF(N28<=Assumptions!$D$34,Assumptions!$I$34+(N28-Assumptions!$C$34)/(Assumptions!$D$34-Assumptions!$C$34)*(Assumptions!$J$34-Assumptions!$I$34),IF(N28<=Assumptions!$E$34,Assumptions!$J$34+(N28-Assumptions!$D$34)/(Assumptions!$E$34-Assumptions!$D$34)*(Assumptions!$K$34-Assumptions!$J$34),IF(N28<=Assumptions!$F$34,Assumptions!$K$34+(N28-Assumptions!$E$34)/(Assumptions!$F$34-Assumptions!$E$34)*(Assumptions!$L$34-Assumptions!$K$34),IF(N28<=Assumptions!$G$34,Assumptions!$L$34+(N28-Assumptions!$F$34)/(Assumptions!$G$34-Assumptions!$F$34)*(Assumptions!$M$34-Assumptions!$L$34),Assumptions!$M$34)))))) -> 2 | W28: =IF(S28="",PERCENTILE($S$6:$S$30,Assumptions!$B$36),S28) -> 44.666667 | X28: =IF(T28="",PERCENTILE($T$6:$T$30,Assumptions!$B$36),T28) -> 28.65 | Y28: =IF(O28="",PERCENTILE($O$6:$O$30,Assumptions!$B$36),O28) -> 55.5 | Z28: =W28*Assumptions!$B$16+X28*Assumptions!$B$17 -> 36.658333 | AA28: =U28*Assumptions!$B$18+V28*Assumptions!$B$19 -> 20 | AB28: =AVERAGE(P28:R28) -> 60 | AC28: 0 | AD28: =MIN(100,Z28*Assumptions!$B$11+AA28*Assumptions!$B$12+Y28*Assumptions!$B$13+AB28*Assumptions!$B$14+AC28*Assumptions!$B$20) -> 40.3225 | AE28: =MIN(1,SUMIFS(Network!$V$31:$V$36,Network!$D$31:$D$36,$A28,Network!$U$31:$U$36,1)) -> 1 | AF28: =MIN(1,SUMIFS(Network!$W$31:$W$36,Network!$D$31:$D$36,$A28,Network!$U$31:$U$36,1)) -> 1 | AG28: =MIN(1,SUMIFS(Network!$X$31:$X$36,Network!$D$31:$D$36,$A28,Network!$U$31:$U$36,1)) -> 1 | AH28: =AE28*Assumptions!$B$5+AF28*Assumptions!$B$6+AG28*Assumptions!$B$7 -> 1560 | AI28: =AH28/Assumptions!$B$8 -> 1 | AJ28: =AH28/52 -> 30 | AK28: =AJ28*I28 -> 240 | AL28: =MIN(100,I28/Assumptions!$B$26*100) -> 22.222222 | AM28: =MIN(100,H28/Assumptions!$B$27*100) -> 100 | AN28: =AI28*100*Assumptions!$B$23+AL28*Assumptions!$B$24+AM28*Assumptions!$B$25 -> 76.666667 | AO28: =AN28*AD28/100 -> 30.913917 | AP28: =RANK(AO28,$AO$6:$AO$30)+COUNTIF($AO$6:AO28,AO28)-1 -> 8 | AQ28: =IF(AO28>=Assumptions!$B$39,"Critical",IF(AO28>=Assumptions!$B$40,"High",IF(AO28>=Assumptions!$B$41,"Elevated","Watch"))) -> High | AR28: =IF(AND(AN28>=Assumptions!$B$42,AD28>=Assumptions!$B$43),"Act now",IF(AN28>=Assumptions!$B$42,"Protect (structural)",IF(AD28>=Assumptions!$B$43,"Remediate supplier","Routine"))) -> Protect (structural) | AS28: =_xlfn.MAXIFS(Network!$T$5:$T$36,Network!$D$5:$D$36,$A28) -> 2 | AT28: =COUNT(K28:R28) -> 5 | AU28: =IF(AT28>=8,2,IF(AT28>=6,1,0)) -> 0 | AV28: =IF(OR(C28=1,LEFT(G28,9)="Confirmed"),1,0) -> 0 | AW28: =AS28+AU28+AV28 -> 2 | AX28: =IF(AW28>=Assumptions!$B$44,"High",IF(AW28>=Assumptions!$B$45,"Medium","Low")) -> Low | AY28: =IF(OR(AQ28="Critical",AQ28="High"),IF(AX28="Low","VERIFY first – urgent sub-tier fact-find",IF(OR(AQ28="Critical",AV28=1),"ACT – mitigate now","CONFIRM sole-source status, then qualify alternate")),IF(AQ28="Elevated",IF(AX28="Low","VERIFY – add to N-tier survey","PLAN – qualify alternate in 90 days"),"MONITOR – quarterly review")) -> VERIFY first – urgent sub-tier fact-find | AZ28: =IF(K28&L28&O28<>"",IF(OR(K28="",L28="",O28=""),TRIM(IF(K28="","Current ratio; ","")&IF(L28="","Net debt/EBITDA; ","")&IF(O28="","Assurance gap","")),"—"),"Current ratio; Net debt/EBITDA; Assurance gap") -> Current ratio; Net debt/EBITDA; Assurance gap
A29: ORG-179 | B29: =INDEX(Data!$B$5:$B$34,MATCH($A29,Data!$A$5:$A$34,0)) -> Xenon Resin Ltd. | C29: 3 | D29: Tier-3: resin → Jade | E29: =INDEX(Data!$G$38:$G$67,MATCH($A29,Data!$A$38:$A$67,0)) -> SITE-179 | F29: =INDEX(Data!$I$38:$I$67,MATCH($A29,Data!$A$38:$A$67,0)) -> Z04 | G29: Presumed sole – not disclosed | H29: 3 | I29: 8 | J29: Assumption | K29: =IF(INDEX(Data!$C$5:$C$34,MATCH($A29,Data!$A$5:$A$34,0))="","",INDEX(Data!$C$5:$C$34,MATCH($A29,Data!$A$5:$A$34,0))) | L29: =IF(INDEX(Data!$D$5:$D$34,MATCH($A29,Data!$A$5:$A$34,0))="","",INDEX(Data!$D$5:$D$34,MATCH($A29,Data!$A$5:$A$34,0))) | M29: =IF(INDEX(Data!$E$5:$E$34,MATCH($A29,Data!$A$5:$A$34,0))="","",INDEX(Data!$E$5:$E$34,MATCH($A29,Data!$A$5:$A$34,0))) -> 87.3 | N29: =IF(INDEX(Data!$F$5:$F$34,MATCH($A29,Data!$A$5:$A$34,0))="","",INDEX(Data!$F$5:$F$34,MATCH($A29,Data!$A$5:$A$34,0))) -> 1.8 | O29: =IF(INDEX(Data!$G$5:$G$34,MATCH($A29,Data!$A$5:$A$34,0))="","",INDEX(Data!$G$5:$G$34,MATCH($A29,Data!$A$5:$A$34,0))) | P29: =IF(INDEX(Data!$H$5:$H$34,MATCH($A29,Data!$A$5:$A$34,0))="","",INDEX(Data!$H$5:$H$34,MATCH($A29,Data!$A$5:$A$34,0))) -> 58 | Q29: =IF(INDEX(Data!$I$5:$I$34,MATCH($A29,Data!$A$5:$A$34,0))="","",INDEX(Data!$I$5:$I$34,MATCH($A29,Data!$A$5:$A$34,0))) -> 62 | R29: =IF(INDEX(Data!$J$5:$J$34,MATCH($A29,Data!$A$5:$A$34,0))="","",INDEX(Data!$J$5:$J$34,MATCH($A29,Data!$A$5:$A$34,0))) -> 52 | S29: =IF(L29="","",IF(L29<=Assumptions!$B$31,Assumptions!$H$31,IF(L29<=Assumptions!$C$31,Assumptions!$H$31+(L29-Assumptions!$B$31)/(Assumptions!$C$31-Assumptions!$B$31)*(Assumptions!$I$31-Assumptions!$H$31),IF(L29<=Assumptions!$D$31,Assumptions!$I$31+(L29-Assumptions!$C$31)/(Assumptions!$D$31-Assumptions!$C$31)*(Assumptions!$J$31-Assumptions!$I$31),IF(L29<=Assumptions!$E$31,Assumptions!$J$31+(L29-Assumptions!$D$31)/(Assumptions!$E$31-Assumptions!$D$31)*(Assumptions!$K$31-Assumptions!$J$31),IF(L29<=Assumptions!$F$31,Assumptions!$K$31+(L29-Assumptions!$E$31)/(Assumptions!$F$31-Assumptions!$E$31)*(Assumptions!$L$31-Assumptions!$K$31),IF(L29<=Assumptions!$G$31,Assumptions!$L$31+(L29-Assumptions!$F$31)/(Assumptions!$G$31-Assumptions!$F$31)*(Assumptions!$M$31-Assumptions!$L$31),Assumptions!$M$31))))))) | T29: =IF(K29="","",IF(K29<=Assumptions!$B$32,Assumptions!$H$32,IF(K29<=Assumptions!$C$32,Assumptions!$H$32+(K29-Assumptions!$B$32)/(Assumptions!$C$32-Assumptions!$B$32)*(Assumptions!$I$32-Assumptions!$H$32),IF(K29<=Assumptions!$D$32,Assumptions!$I$32+(K29-Assumptions!$C$32)/(Assumptions!$D$32-Assumptions!$C$32)*(Assumptions!$J$32-Assumptions!$I$32),IF(K29<=Assumptions!$E$32,Assumptions!$J$32+(K29-Assumptions!$D$32)/(Assumptions!$E$32-Assumptions!$D$32)*(Assumptions!$K$32-Assumptions!$J$32),IF(K29<=Assumptions!$F$32,Assumptions!$K$32+(K29-Assumptions!$E$32)/(Assumptions!$F$32-Assumptions!$E$32)*(Assumptions!$L$32-Assumptions!$K$32),IF(K29<=Assumptions!$G$32,Assumptions!$L$32+(K29-Assumptions!$F$32)/(Assumptions!$G$32-Assumptions!$F$32)*(Assumptions!$M$32-Assumptions!$L$32),Assumptions!$M$32))))))) | U29: =IF(M29<=Assumptions!$B$33,Assumptions!$H$33,IF(M29<=Assumptions!$C$33,Assumptions!$H$33+(M29-Assumptions!$B$33)/(Assumptions!$C$33-Assumptions!$B$33)*(Assumptions!$I$33-Assumptions!$H$33),IF(M29<=Assumptions!$D$33,Assumptions!$I$33+(M29-Assumptions!$C$33)/(Assumptions!$D$33-Assumptions!$C$33)*(Assumptions!$J$33-Assumptions!$I$33),IF(M29<=Assumptions!$E$33,Assumptions!$J$33+(M29-Assumptions!$D$33)/(Assumptions!$E$33-Assumptions!$D$33)*(Assumptions!$K$33-Assumptions!$J$33),IF(M29<=Assumptions!$F$33,Assumptions!$K$33+(M29-Assumptions!$E$33)/(Assumptions!$F$33-Assumptions!$E$33)*(Assumptions!$L$33-Assumptions!$K$33),IF(M29<=Assumptions!$G$33,Assumptions!$L$33+(M29-Assumptions!$F$33)/(Assumptions!$G$33-Assumptions!$F$33)*(Assumptions!$M$33-Assumptions!$L$33),Assumptions!$M$33)))))) -> 38.5 | V29: =IF(N29<=Assumptions!$B$34,Assumptions!$H$34,IF(N29<=Assumptions!$C$34,Assumptions!$H$34+(N29-Assumptions!$B$34)/(Assumptions!$C$34-Assumptions!$B$34)*(Assumptions!$I$34-Assumptions!$H$34),IF(N29<=Assumptions!$D$34,Assumptions!$I$34+(N29-Assumptions!$C$34)/(Assumptions!$D$34-Assumptions!$C$34)*(Assumptions!$J$34-Assumptions!$I$34),IF(N29<=Assumptions!$E$34,Assumptions!$J$34+(N29-Assumptions!$D$34)/(Assumptions!$E$34-Assumptions!$D$34)*(Assumptions!$K$34-Assumptions!$J$34),IF(N29<=Assumptions!$F$34,Assumptions!$K$34+(N29-Assumptions!$E$34)/(Assumptions!$F$34-Assumptions!$E$34)*(Assumptions!$L$34-Assumptions!$K$34),IF(N29<=Assumptions!$G$34,Assumptions!$L$34+(N29-Assumptions!$F$34)/(Assumptions!$G$34-Assumptions!$F$34)*(Assumptions!$M$34-Assumptions!$L$34),Assumptions!$M$34)))))) -> 2 | W29: =IF(S29="",PERCENTILE($S$6:$S$30,Assumptions!$B$36),S29) -> 44.666667 | X29: =IF(T29="",PERCENTILE($T$6:$T$30,Assumptions!$B$36),T29) -> 28.65 | Y29: =IF(O29="",PERCENTILE($O$6:$O$30,Assumptions!$B$36),O29) -> 55.5 | Z29: =W29*Assumptions!$B$16+X29*Assumptions!$B$17 -> 36.658333 | AA29: =U29*Assumptions!$B$18+V29*Assumptions!$B$19 -> 20.25 | AB29: =AVERAGE(P29:R29) -> 57.333333 | AC29: 0 | AD29: =MIN(100,Z29*Assumptions!$B$11+AA29*Assumptions!$B$12+Y29*Assumptions!$B$13+AB29*Assumptions!$B$14+AC29*Assumptions!$B$20) -> 39.730833 | AE29: =MIN(1,SUMIFS(Network!$V$31:$V$36,Network!$D$31:$D$36,$A29,Network!$U$31:$U$36,1)) -> 1 | AF29: =MIN(1,SUMIFS(Network!$W$31:$W$36,Network!$D$31:$D$36,$A29,Network!$U$31:$U$36,1)) -> 1 | AG29: =MIN(1,SUMIFS(Network!$X$31:$X$36,Network!$D$31:$D$36,$A29,Network!$U$31:$U$36,1)) -> 1 | AH29: =AE29*Assumptions!$B$5+AF29*Assumptions!$B$6+AG29*Assumptions!$B$7 -> 1560 | AI29: =AH29/Assumptions!$B$8 -> 1 | AJ29: =AH29/52 -> 30 | AK29: =AJ29*I29 -> 240 | AL29: =MIN(100,I29/Assumptions!$B$26*100) -> 22.222222 | AM29: =MIN(100,H29/Assumptions!$B$27*100) -> 100 | AN29: =AI29*100*Assumptions!$B$23+AL29*Assumptions!$B$24+AM29*Assumptions!$B$25 -> 76.666667 | AO29: =AN29*AD29/100 -> 30.460306 | AP29: =RANK(AO29,$AO$6:$AO$30)+COUNTIF($AO$6:AO29,AO29)-1 -> 10 | AQ29: =IF(AO29>=Assumptions!$B$39,"Critical",IF(AO29>=Assumptions!$B$40,"High",IF(AO29>=Assumptions!$B$41,"Elevated","Watch"))) -> High | AR29: =IF(AND(AN29>=Assumptions!$B$42,AD29>=Assumptions!$B$43),"Act now",IF(AN29>=Assumptions!$B$42,"Protect (structural)",IF(AD29>=Assumptions!$B$43,"Remediate supplier","Routine"))) -> Protect (structural) | AS29: =_xlfn.MAXIFS(Network!$T$5:$T$36,Network!$D$5:$D$36,$A29) -> 2 | AT29: =COUNT(K29:R29) -> 5 | AU29: =IF(AT29>=8,2,IF(AT29>=6,1,0)) -> 0 | AV29: =IF(OR(C29=1,LEFT(G29,9)="Confirmed"),1,0) -> 0 | AW29: =AS29+AU29+AV29 -> 2 | AX29: =IF(AW29>=Assumptions!$B$44,"High",IF(AW29>=Assumptions!$B$45,"Medium","Low")) -> Low | AY29: =IF(OR(AQ29="Critical",AQ29="High"),IF(AX29="Low","VERIFY first – urgent sub-tier fact-find",IF(OR(AQ29="Critical",AV29=1),"ACT – mitigate now","CONFIRM sole-source status, then qualify alternate")),IF(AQ29="Elevated",IF(AX29="Low","VERIFY – add to N-tier survey","PLAN – qualify alternate in 90 days"),"MONITOR – quarterly review")) -> VERIFY first – urgent sub-tier fact-find | AZ29: =IF(K29&L29&O29<>"",IF(OR(K29="",L29="",O29=""),TRIM(IF(K29="","Current ratio; ","")&IF(L29="","Net debt/EBITDA; ","")&IF(O29="","Assurance gap","")),"—"),"Current ratio; Net debt/EBITDA; Assurance gap") -> Current ratio; Net debt/EBITDA; Assurance gap
A30: ORG-659 | B30: =INDEX(Data!$B$5:$B$34,MATCH($A30,Data!$A$5:$A$34,0)) -> Zenith Polymer Ltd. | C30: 3 | D30: Tier-3: polymer → Meridian | E30: =INDEX(Data!$G$38:$G$67,MATCH($A30,Data!$A$38:$A$67,0)) -> SITE-193 | F30: =INDEX(Data!$I$38:$I$67,MATCH($A30,Data!$A$38:$A$67,0)) -> Z03 | G30: Presumed sole – not disclosed | H30: 1 | I30: 12 | J30: Assumption | K30: =IF(INDEX(Data!$C$5:$C$34,MATCH($A30,Data!$A$5:$A$34,0))="","",INDEX(Data!$C$5:$C$34,MATCH($A30,Data!$A$5:$A$34,0))) | L30: =IF(INDEX(Data!$D$5:$D$34,MATCH($A30,Data!$A$5:$A$34,0))="","",INDEX(Data!$D$5:$D$34,MATCH($A30,Data!$A$5:$A$34,0))) | M30: =IF(INDEX(Data!$E$5:$E$34,MATCH($A30,Data!$A$5:$A$34,0))="","",INDEX(Data!$E$5:$E$34,MATCH($A30,Data!$A$5:$A$34,0))) -> 90.9 | N30: =IF(INDEX(Data!$F$5:$F$34,MATCH($A30,Data!$A$5:$A$34,0))="","",INDEX(Data!$F$5:$F$34,MATCH($A30,Data!$A$5:$A$34,0))) -> -0.9 | O30: =IF(INDEX(Data!$G$5:$G$34,MATCH($A30,Data!$A$5:$A$34,0))="","",INDEX(Data!$G$5:$G$34,MATCH($A30,Data!$A$5:$A$34,0))) | P30: =IF(INDEX(Data!$H$5:$H$34,MATCH($A30,Data!$A$5:$A$34,0))="","",INDEX(Data!$H$5:$H$34,MATCH($A30,Data!$A$5:$A$34,0))) -> 19 | Q30: =IF(INDEX(Data!$I$5:$I$34,MATCH($A30,Data!$A$5:$A$34,0))="","",INDEX(Data!$I$5:$I$34,MATCH($A30,Data!$A$5:$A$34,0))) -> 26 | R30: =IF(INDEX(Data!$J$5:$J$34,MATCH($A30,Data!$A$5:$A$34,0))="","",INDEX(Data!$J$5:$J$34,MATCH($A30,Data!$A$5:$A$34,0))) -> 25 | S30: =IF(L30="","",IF(L30<=Assumptions!$B$31,Assumptions!$H$31,IF(L30<=Assumptions!$C$31,Assumptions!$H$31+(L30-Assumptions!$B$31)/(Assumptions!$C$31-Assumptions!$B$31)*(Assumptions!$I$31-Assumptions!$H$31),IF(L30<=Assumptions!$D$31,Assumptions!$I$31+(L30-Assumptions!$C$31)/(Assumptions!$D$31-Assumptions!$C$31)*(Assumptions!$J$31-Assumptions!$I$31),IF(L30<=Assumptions!$E$31,Assumptions!$J$31+(L30-Assumptions!$D$31)/(Assumptions!$E$31-Assumptions!$D$31)*(Assumptions!$K$31-Assumptions!$J$31),IF(L30<=Assumptions!$F$31,Assumptions!$K$31+(L30-Assumptions!$E$31)/(Assumptions!$F$31-Assumptions!$E$31)*(Assumptions!$L$31-Assumptions!$K$31),IF(L30<=Assumptions!$G$31,Assumptions!$L$31+(L30-Assumptions!$F$31)/(Assumptions!$G$31-Assumptions!$F$31)*(Assumptions!$M$31-Assumptions!$L$31),Assumptions!$M$31))))))) | T30: =IF(K30="","",IF(K30<=Assumptions!$B$32,Assumptions!$H$32,IF(K30<=Assumptions!$C$32,Assumptions!$H$32+(K30-Assumptions!$B$32)/(Assumptions!$C$32-Assumptions!$B$32)*(Assumptions!$I$32-Assumptions!$H$32),IF(K30<=Assumptions!$D$32,Assumptions!$I$32+(K30-Assumptions!$C$32)/(Assumptions!$D$32-Assumptions!$C$32)*(Assumptions!$J$32-Assumptions!$I$32),IF(K30<=Assumptions!$E$32,Assumptions!$J$32+(K30-Assumptions!$D$32)/(Assumptions!$E$32-Assumptions!$D$32)*(Assumptions!$K$32-Assumptions!$J$32),IF(K30<=Assumptions!$F$32,Assumptions!$K$32+(K30-Assumptions!$E$32)/(Assumptions!$F$32-Assumptions!$E$32)*(Assumptions!$L$32-Assumptions!$K$32),IF(K30<=Assumptions!$G$32,Assumptions!$L$32+(K30-Assumptions!$F$32)/(Assumptions!$G$32-Assumptions!$F$32)*(Assumptions!$M$32-Assumptions!$L$32),Assumptions!$M$32))))))) | U30: =IF(M30<=Assumptions!$B$33,Assumptions!$H$33,IF(M30<=Assumptions!$C$33,Assumptions!$H$33+(M30-Assumptions!$B$33)/(Assumptions!$C$33-Assumptions!$B$33)*(Assumptions!$I$33-Assumptions!$H$33),IF(M30<=Assumptions!$D$33,Assumptions!$I$33+(M30-Assumptions!$C$33)/(Assumptions!$D$33-Assumptions!$C$33)*(Assumptions!$J$33-Assumptions!$I$33),IF(M30<=Assumptions!$E$33,Assumptions!$J$33+(M30-Assumptions!$D$33)/(Assumptions!$E$33-Assumptions!$D$33)*(Assumptions!$K$33-Assumptions!$J$33),IF(M30<=Assumptions!$F$33,Assumptions!$K$33+(M30-Assumptions!$E$33)/(Assumptions!$F$33-Assumptions!$E$33)*(Assumptions!$L$33-Assumptions!$K$33),IF(M30<=Assumptions!$G$33,Assumptions!$L$33+(M30-Assumptions!$F$33)/(Assumptions!$G$33-Assumptions!$F$33)*(Assumptions!$M$33-Assumptions!$L$33),Assumptions!$M$33)))))) -> 20.5 | V30: =IF(N30<=Assumptions!$B$34,Assumptions!$H$34,IF(N30<=Assumptions!$C$34,Assumptions!$H$34+(N30-Assumptions!$B$34)/(Assumptions!$C$34-Assumptions!$B$34)*(Assumptions!$I$34-Assumptions!$H$34),IF(N30<=Assumptions!$D$34,Assumptions!$I$34+(N30-Assumptions!$C$34)/(Assumptions!$D$34-Assumptions!$C$34)*(Assumptions!$J$34-Assumptions!$I$34),IF(N30<=Assumptions!$E$34,Assumptions!$J$34+(N30-Assumptions!$D$34)/(Assumptions!$E$34-Assumptions!$D$34)*(Assumptions!$K$34-Assumptions!$J$34),IF(N30<=Assumptions!$F$34,Assumptions!$K$34+(N30-Assumptions!$E$34)/(Assumptions!$F$34-Assumptions!$E$34)*(Assumptions!$L$34-Assumptions!$K$34),IF(N30<=Assumptions!$G$34,Assumptions!$L$34+(N30-Assumptions!$F$34)/(Assumptions!$G$34-Assumptions!$F$34)*(Assumptions!$M$34-Assumptions!$L$34),Assumptions!$M$34)))))) -> 26.75 | W30: =IF(S30="",PERCENTILE($S$6:$S$30,Assumptions!$B$36),S30) -> 44.666667 | X30: =IF(T30="",PERCENTILE($T$6:$T$30,Assumptions!$B$36),T30) -> 28.65 | Y30: =IF(O30="",PERCENTILE($O$6:$O$30,Assumptions!$B$36),O30) -> 55.5 | Z30: =W30*Assumptions!$B$16+X30*Assumptions!$B$17 -> 36.658333 | AA30: =U30*Assumptions!$B$18+V30*Assumptions!$B$19 -> 23.625 | AB30: =AVERAGE(P30:R30) -> 23.333333 | AC30: 0 | AD30: =MIN(100,Z30*Assumptions!$B$11+AA30*Assumptions!$B$12+Y30*Assumptions!$B$13+AB30*Assumptions!$B$14+AC30*Assumptions!$B$20) -> 32.243333 | AE30: =MIN(1,SUMIFS(Network!$V$31:$V$36,Network!$D$31:$D$36,$A30,Network!$U$31:$U$36,1)) -> 1 | AF30: =MIN(1,SUMIFS(Network!$W$31:$W$36,Network!$D$31:$D$36,$A30,Network!$U$31:$U$36,1)) -> 1 | AG30: =MIN(1,SUMIFS(Network!$X$31:$X$36,Network!$D$31:$D$36,$A30,Network!$U$31:$U$36,1)) -> 0 | AH30: =AE30*Assumptions!$B$5+AF30*Assumptions!$B$6+AG30*Assumptions!$B$7 -> 1144 | AI30: =AH30/Assumptions!$B$8 -> 0.73333333 | AJ30: =AH30/52 -> 22 | AK30: =AJ30*I30 -> 264 | AL30: =MIN(100,I30/Assumptions!$B$26*100) -> 33.333333 | AM30: =MIN(100,H30/Assumptions!$B$27*100) -> 33.333333 | AN30: =AI30*100*Assumptions!$B$23+AL30*Assumptions!$B$24+AM30*Assumptions!$B$25 -> 53.333333 | AO30: =AN30*AD30/100 -> 17.196444 | AP30: =RANK(AO30,$AO$6:$AO$30)+COUNTIF($AO$6:AO30,AO30)-1 -> 16 | AQ30: =IF(AO30>=Assumptions!$B$39,"Critical",IF(AO30>=Assumptions!$B$40,"High",IF(AO30>=Assumptions!$B$41,"Elevated","Watch"))) -> Watch | AR30: =IF(AND(AN30>=Assumptions!$B$42,AD30>=Assumptions!$B$43),"Act now",IF(AN30>=Assumptions!$B$42,"Protect (structural)",IF(AD30>=Assumptions!$B$43,"Remediate supplier","Routine"))) -> Routine | AS30: =_xlfn.MAXIFS(Network!$T$5:$T$36,Network!$D$5:$D$36,$A30) -> 2 | AT30: =COUNT(K30:R30) -> 5 | AU30: =IF(AT30>=8,2,IF(AT30>=6,1,0)) -> 0 | AV30: =IF(OR(C30=1,LEFT(G30,9)="Confirmed"),1,0) -> 0 | AW30: =AS30+AU30+AV30 -> 2 | AX30: =IF(AW30>=Assumptions!$B$44,"High",IF(AW30>=Assumptions!$B$45,"Medium","Low")) -> Low | AY30: =IF(OR(AQ30="Critical",AQ30="High"),IF(AX30="Low","VERIFY first – urgent sub-tier fact-find",IF(OR(AQ30="Critical",AV30=1),"ACT – mitigate now","CONFIRM sole-source status, then qualify alternate")),IF(AQ30="Elevated",IF(AX30="Low","VERIFY – add to N-tier survey","PLAN – qualify alternate in 90 days"),"MONITOR – quarterly review")) -> MONITOR – quarterly review | AZ30: =IF(K30&L30&O30<>"",IF(OR(K30="",L30="",O30=""),TRIM(IF(K30="","Current ratio; ","")&IF(L30="","Net debt/EBITDA; ","")&IF(O30="","Assurance gap","")),"—"),"Current ratio; Net debt/EBITDA; Assurance gap") -> Current ratio; Net debt/EBITDA; Assurance gap
A32: Notes
A33: Exposure = share of each product's volume that would stop if the node failed and no buffer existed. Tier-1 = allocation; upstream nodes inherit their customers' exposure (capped at 100%). Presumed-sole links are treated as single-sourced (upper bound) until verified – consistent with "missing ≠ low risk".
A34: Revenue-at-risk over TTR = weekly revenue exposed × time-to-recover. Gross revenue, no inventory buffer (none disclosed) – an upper bound for sizing, not a forecast.
A35: Group node ORG-268 (CommonSpan) shows the true M10/M20 concentration hidden by the Aster/Boreal "dual source". It is scored on the parent's own indicators.
A36: Event overlay: +points only where an event independently confirms entity-level stress (EV-003 → Meridian). Zone watches (EV-001) are handled on the Alerts tab, not baked into the structural score.
A37: Holding company / logistics entities (Jade Holdings, Harbor Freight) are context nodes – shown on Network tab, not scored as suppliers.

Sheet Network
A1: Reconstructed supplier network (Tier-1 → Tier-3) with evidence grade
A2: Rows are grouped by supplier tier so exposure formulas flow upward without circular references. Exposure columns = share of each product's volume that depends on this link.
A4: Link | B4: Link type | C4: Supplier tier | D4: Supplier ID | E4: Supplier | F4: Customer ID | G4: Customer | H4: Component / input | I4: Products | J4: P1 | K4: P2 | L4: P3 | M4: Allocation | N4: Supplier site | O4: Site zone | P4: Evidence IDs | Q4: Independent source families | R4: Link status | S4: Grade | T4: Grade pts | U4: Include in exposure | V4: Exp P1 | W4: Exp P2 | X4: Exp P3 | Y4: Notes
A5: L01 | B5: Tier-1 supply | C5: 1 | D5: ORG-247 | E5: Aster Power Assemblies Ltd. | F5: NOVADRIVE | G5: NovaDrive Technologies | H5: M10 | I5: P1,P3 | J5: 1 | K5: 0 | L5: 1 | M5: 0.6 | N5: SITE-018 | O5: Z02 | P5: DOC-001; DOC-002; SHP-00002 | Q5: 3 | R5: Confirmed | S5: A | T5: 3 | U5: 1 | V5: =$M5*J5 -> 0.6 | W5: =$M5*K5 -> 0 | X5: =$M5*L5 -> 0.6 | Y5: Allocation is a planning share, not realised deliveries.
A6: L02 | B6: Tier-1 supply | C6: 1 | D6: ORG-247 | E6: Aster Power Assemblies Ltd. | F6: NOVADRIVE | G6: NovaDrive Technologies | H6: M20 | I6: P2 | J6: 0 | K6: 1 | L6: 0 | M6: 0.7 | N6: SITE-018 | O6: Z02 | P6: DOC-003; DOC-004 | Q6: 2 | R6: Confirmed | S6: A | T6: 3 | U6: 1 | V6: =$M6*J6 -> 0 | W6: =$M6*K6 -> 0.7 | X6: =$M6*L6 -> 0 | Y6: Allocation is a planning share, not realised deliveries.
A7: L03 | B7: Tier-1 supply | C7: 1 | D7: ORG-725 | E7: Boreal Power Systems Ltd. | F7: NOVADRIVE | G7: NovaDrive Technologies | H7: M10 | I7: P1,P3 | J7: 1 | K7: 0 | L7: 1 | M7: 0.4 | N7: SITE-025 | O7: Z05 | P7: DOC-005; DOC-006; SHP-00025 | Q7: 3 | R7: Confirmed | S7: A | T7: 3 | U7: 1 | V7: =$M7*J7 -> 0.4 | W7: =$M7*K7 -> 0 | X7: =$M7*L7 -> 0.4 | Y7: Allocation is a planning share, not realised deliveries.
A8: L04 | B8: Tier-1 supply | C8: 1 | D8: ORG-725 | E8: Boreal Power Systems Ltd. | F8: NOVADRIVE | G8: NovaDrive Technologies | H8: M20 | I8: P2 | J8: 0 | K8: 1 | L8: 0 | M8: 0.3 | N8: SITE-025 | O8: Z05 | P8: DOC-007; DOC-008 | Q8: 2 | R8: Confirmed | S8: A | T8: 3 | U8: 1 | V8: =$M8*J8 -> 0 | W8: =$M8*K8 -> 0.3 | X8: =$M8*L8 -> 0 | Y8: Allocation is a planning share, not realised deliveries.
A9: L05 | B9: Tier-1 supply | C9: 1 | D9: ORG-119 | E9: Cobalt Control Electronics Ltd. | F9: NOVADRIVE | G9: NovaDrive Technologies | H9: C10 | I9: P1,P2,P3 | J9: 1 | K9: 1 | L9: 1 | M9: 1 | N9: SITE-032 | O9: Z04 | P9: DOC-009; DOC-010; SHP-00050 | Q9: 3 | R9: Confirmed | S9: A | T9: 3 | U9: 1 | V9: =$M9*J9 -> 1 | W9: =$M9*K9 -> 1 | X9: =$M9*L9 -> 1 | Y9: Sole Tier-1 source (100% allocation).
A10: L06 | B10: Tier-1 supply | C10: 1 | D10: ORG-922 | E10: Delta Capacitor Works Ltd. | F10: NOVADRIVE | G10: NovaDrive Technologies | H10: C20 | I10: P1,P2 | J10: 1 | K10: 1 | L10: 0 | M10: 1 | N10: SITE-039 | O10: Z03 | P10: DOC-011; DOC-012; SHP-00062 | Q10: 3 | R10: Confirmed | S10: A | T10: 3 | U10: 1 | V10: =$M10*J10 -> 1 | W10: =$M10*K10 -> 1 | X10: =$M10*L10 -> 0 | Y10: Sole Tier-1 source (100% allocation).
